Workbook

Sheet LEIA-ME
A1: Análise das Demonstrações Financeiras — Netflix, Inc. (NFLX) · ECO057
A2: Período: 2019T1 a 2026T2 (30 trimestres) · Valores em US$ milhões, salvo indicação.
A4: Como ler esta planilha
A5: • Números em AZUL são dados oficiais (insumos). Números em PRETO são fórmulas — clique na célula para ver o cálculo.
A6: • Linhas verdes são conferências: devem dar zero. O resumo está na aba Validacao.
A7: • "n.d." = não disponível (ex.: indicador LTM precisa de 4 trimestres; AH homóloga precisa do mesmo trimestre do ano anterior).
A9: Abas (ordem sugerida para a apresentação)
A10: 1. Macro e Setor — contexto: juros, inflação, câmbio e a situação dos concorrentes de streaming.
A11: 2. DRE, BP, DFC — demonstrações montadas a partir dos 10-Q/10-K, com conferência contra os totais informados à SEC.
A12: 3. AV — análise vertical (base: receita na DRE e ativo total no BP).
A13: 4. AH e AH_Anual — análise horizontal sequencial (t vs t−1), homóloga (t vs t−4), base fixa e anual.
A14: 5. Indicadores — margens, DuPont (ROA/ROE), liquidez, Fleuriet (CCL/NCG/ST), endividamento, GAO/GAF/GAT.
... A31: • O lucro de 2026T1 é explicado pela multa rescisória da WBD (US$ 2,8 bi) — e não por "créditos fiscais", como constava antes.

Sheet Graficos
A1: Gráficos da análise (atualizam com as fórmulas)
A2: Eixo X: trimestres · Um único eixo Y por gráfico, com unidade no título do eixo.

Sheet DRE
A1: Netflix, Inc. — Demonstração do Resultado (trimestral)
A2: US$ milhões · Fonte: SEC EDGAR, 10-Q e 10-K (XBRL). 4º tri = ano (10-K) − 9 meses (10-Q).
A4: Conta / indicador | B4: Fonte ou fórmula | C4: 2019T1 | D4: 2019T2 | E4: 2019T3 | F4: 2019T4 | G4: 2020T1 | H4: 2020T2 | I4: 2020T3 | J4: 2020T4 | K4: 2021T1 | L4: 2021T2 | M4: 2021T3 | N4: 2021T4 | O4: 2022T1 | P4: 2022T2 | Q4: 2022T3 | R4: 2022T4 | S4: 2023T1 | T4: 2023T2 | U4: 2023T3 | V4: 2023T4 | W4: 2024T1 | X4: 2024T2 | Y4: 2024T3 | Z4: 2024T4 | AA4: 2025T1 | AB4: 2025T2 | AC4: 2025T3 | AD4: 2025T4 | AE4: 2026T1 | AF4: 2026T2
A6: Demonstração do resultado
A7: (=) Receita líquida | B7: us-gaap:Revenues | C7: 4520.992 | D7: 4923.116 | E7: 5244.905 | F7: 5467.434 | G7: 5767.691 | H7: 6148.286 | I7: 6435.637 | J7: 6644.442 | K7: 7163.282 | L7: 7341.777 | M7: 7483.467 | N7: 7709.318 | O7: 7867.767 | P7: 7970.141 | Q7: 7925.589 | R7: 7852.053 | S7: 8161.503 | T7: 8187.301 | U7: 8541.668 | V7: 8832.825 | W7: 9370.44 | X7: 9559.31 | Y7: 9824.703 | Z7: 10246.513 | AA7: 10542.801 | AB7: 11079.166 | AC7: 11510.307 | AD7: 12050.762 | AE7: 12249.757 | AF7: 12559.938
A8: (−) Custo dos serviços (inclui amortização de conteúdo) | B8: us-gaap:CostOfRevenue | C8: 2870.614 | D8: 3005.657 | E8: 3097.919 | F8: 3466.023 | G8: 3599.701 | H8: 3643.707 | I8: 3867.751 | J8: 4165.16 | K8: 3868.511 | L8: 4018.008 | M8: 4206.589 | N8: 5239.575 | O8: 4284.705 | P8: 4690.755 | Q8: 4788.665 | R8: 5404.16 | S8: 4803.625 | T8: 4673.47 | U8: 4930.788 | V8: 5307.485 | W8: 4977.073 | X8: 5174.143 | Y8: 5119.884 | Z8: 5767.364 | AA8: 5263.147 | AB8: 5325.311 | AC8: 6164.25 | AD8: 6522.621 | AE8: 5888.238 | AF8: 6036.965
A9: (=) Lucro bruto | B9: Receita − Custo | C9: =C7-C8 -> 1650.378 | D9: =D7-D8 -> 1917.459 | E9: =E7-E8 -> 2146.986 | F9: =F7-F8 -> 2001.411 | G9: =G7-G8 -> 2167.99 | H9: =H7-H8 -> 2504.579 | I9: =I7-I8 -> 2567.886 | J9: =J7-J8 -> 2479.282 | ... AF9: =AF7-AF8 -> 6522.973
A10: (−) Marketing | B10: SellingAndMarketing / Marketing | C10: 616.578 | D10: 603.15 | E10: 553.797 | F10: 878.937 | G10: 503.83 | H10: 434.37 | I10: 527.597 | J10: 762.565 | K10: 512.512 | L10: 603.973 | M10: 635.948 | N10: 792.713 | O10: 555.978 | P10: 574.96 | Q10: 567.954 | R10: 831.61 | S10: 555.362 | T10: 627.168 | U10: 558.736 | V10: 916.617 | W10: 654.34 | X10: 644.084 | Y10: 642.926 | Z10: 976.204 | AA10: 688.37 | AB10: 713.265 | AC10: 786.295 | AD10: 1113.376 | AE10: 842.217 | AF10: 823.838
A11: (−) Tecnologia e desenvolvimento | B11: T&D / ResearchAndDevelopment | C11: 372.764 | D11: 383.233 | E11: 379.776 | F11: 409.376 | G11: 453.817 | H11: 435.045 | I11: 453.802 | J11: 486.936 | K11: 525.207 | L11: 537.321 | M11: 563.887 | N11: 647.47 | O11: 657.53 | P11: 716.846 | Q11: 662.739 | R11: 673.926 | S11: 687.275 | T11: 657.983 | U11: 657.159 | V11: 673.341 | W11: 702.473 | X11: 711.254 | Y11: 735.063 | Z11: 776.505 | AA11: 822.823 | AB11: 824.683 | AC11: 853.584 | AD11: 890.3 | AE11: 959.696 | AF11: 1007.675
A12: (−) Gerais e administrativas | B12: GeneralAndAdministrative | C12: 201.952 | D12: 224.657 | E12: 233.174 | F12: 254.586 | G12: 252.087 | H12: 277.236 | I12: 271.624 | J12: 275.539 | K12: 297.196 | L12: 334.845 | M12: 321.79 | N12: 397.79 | O12: 397.928 | P12: 409.297 | Q12: 373.213 | R12: 392.453 | S12: 400.924 | T12: 401.497 | U12: 478.591 | V12: 439.273 | W12: 404.02 | X12: 426.992 | Y12: 417.353 | Z12: 453.674 | AA12: 421.462 | AB12: 441.213 | AC12: 457.931 | AD12: 567.802 | AE12: 602.609 | AF12: 498.85
A13: (=) Despesas operacionais | B13: Soma | C13: =C10+C11+C12 -> 1191.294 | D13: =D10+D11+D12 -> 1211.04 | E13: =E10+E11+E12 -> 1166.747 | F13: =F10+F11+F12 -> 1542.899 | G13: =G10+G11+G12 -> 1209.734 | H13: =H10+H11+H12 -> 1146.651 | I13: =I10+I11+I12 -> 1253.023 | J13: =J10+J11+J12 -> 1525.04 | ... AF13: =AF10+AF11+AF12 -> 2330.363
A14: (=) Lucro operacional (EBIT / LAJIR) | B14: Lucro bruto − Desp. operacionais | C14: =C9-C13 -> 459.084 | D14: =D9-D13 -> 706.419 | E14: =E9-E13 -> 980.239 | F14: =F9-F13 -> 458.512 | G14: =G9-G13 -> 958.256 | H14: =H9-H13 -> 1357.928 | I14: =I9-I13 -> 1314.863 | J14: =J9-J13 -> 954.242 | ... AF14: =AF9-AF13 -> 4192.61
A15: (−) Despesa de juros | B15: InterestExpense(Nonoperating) | C15: 135.529 | D15: 152.033 | E15: 160.66 | F15: 177.801 | G15: 184.083 | H15: 189.151 | I15: 197.079 | J15: 197.186 | K15: 194.44 | L15: 191.322 | M15: 190.429 | N15: 189.429 | O15: 187.579 | P15: 175.455 | Q15: 172.575 | R15: 170.603 | S15: 174.239 | T15: 174.812 | U15: 175.563 | V15: 175.212 | W15: 173.314 | X15: 167.986 | Y15: 184.83 | Z15: 192.603 | AA15: 184.172 | AB15: 182.649 | AC15: 175.294 | AD15: 234.395 | AE15: 262.077 | AF15: 175.685
A16: (+/−) Juros e outras receitas/despesas (inclui câmbio) | B16: NonoperatingIncomeExpense | C16: 76.104 | D16: -53.47 | E16: 192.744 | F16: -131.378 | G16: 21.697 | H16: -133.175 | I16: -256.324 | J16: -250.639 | K16: 269.086 | L16: -62.519 | M16: 96.135 | N16: 108.512 | O16: 195.645 | P16: 220.226 | Q16: 261.404 | R16: -339.965 | S16: -71.204 | T16: 26.961 | U16: 168.218 | V16: -172.747 | W16: 155.359 | X16: 79.005 | Y16: -21.693 | Z16: 54.105 | AA16: 50.899 | AB16: 39.63 | AC16: 36.457 | AD16: 45.473 | AE16: 2852.166 | AF16: 51.661
A17: (=) Lucro antes do IR (LAIR) | B17: EBIT − Juros + Outras | C17: =C14-C15+C16 -> 399.659 | D17: =D14-D15+D16 -> 500.916 | E17: =E14-E15+E16 -> 1012.323 | F17: =F14-F15+F16 -> 149.333 | G17: =G14-G15+G16 -> 795.87 | H17: =H14-H15+H16 -> 1035.602 | I17: =I14-I15+I16 -> 861.46 | J17: =J14-J15+J16 -> 506.417 | ... AF17: =AF14-AF15+AF16 -> 4068.586
A18: (−) Imposto de renda (sinal original; benefício = negativo) | B18: IncomeTaxExpenseBenefit | C18: 55.607 | D18: 230.266 | E18: 347.079 | F18: -437.637 | G18: 86.803 | H18: 315.406 | I18: 71.484 | J18: -35.739 | K18: 327.787 | L18: 240.776 | M18: 211.888 | N18: -56.576 | O18: 382.245 | P18: 182.103 | Q18: 223.605 | R18: -15.948 | S18: 163.754 | T18: 191.722 | U18: 231.627 | V18: 210.312 | W18: 282.37 | X18: 366.55 | Y18: 339.445 | Z18: 265.661 | AA18: 323.375 | AB18: 506.262 | AC18: 562.494 | AD18: 349.22 | AE18: 1264.295 | AF18: 667.172
A19: (=) Lucro líquido | B19: LAIR − IR | C19: =C17-C18 -> 344.052 | D19: =D17-D18 -> 270.65 | E19: =E17-E18 -> 665.244 | F19: =F17-F18 -> 586.97 | G19: =G17-G18 -> 709.067 | H19: =H17-H18 -> 720.196 | I19: =I17-I18 -> 789.976 | J19: =J17-J18 -> 542.156 | ... AF19: =AF17-AF18 -> 3401.414
A21: Conferência com os valores informados à SEC (deve dar zero)
A22: EBIT calculado − EBIT informado | B22: OperatingIncomeLoss | C22: =C14-459.084 -> 0 | D22: =D14-706.419 -> 0 | E22: =E14-980.239 -> 0 | F22: =F14-458.512 -> 0 | G22: =G14-958.256 -> 0 | H22: =H14-1357.928 -> 0 | I22: =I14-1314.863 -> 0 | J22: =J14-954.242 -> 0 | K22: =K14-1959.856 -> 0 | L22: =L14-1847.63 -> 0 | M22: =M14-1755.253 -> 0 | N22: =N14-631.77 -> 0 | O22: =O14-1971.626 -> 0 | P22: =P14-1578.283 -> 0 | Q22: =Q14-1533.018 -> 0 | R22: =R14-549.904 -> 0 | S22: =S14-1714.317 -> 0 | T22: =T14-1827.183 -> 0 | U22: =U14-1916.394 -> 0 | V22: =V14-1496.109 -> 0 | W22: =W14-2632.534 -> 0 | X22: =X14-2602.837 -> 0 | Y22: =Y14-2909.477 -> 0 | Z22: =Z14-2272.766 -> 0 | AA22: =AA14-3346.999 -> 0 | AB22: =AB14-3774.694 -> 0 | AC22: =AC14-3248.247 -> 0 | AD22: =AD14-2956.663 -> 0 | AE22: =AE14-3956.997 -> 0 | AF22: =AF14-4192.61 -> 0
A23: LAIR calculado − LAIR informado | B23: IncomeBeforeIncomeTaxes | C23: =C17-399.659 -> 0 | D23: =D17-500.916 -> 0 | E23: =E17-1012.323 -> 0 | F23: =F17-149.333 -> 0 | G23: =G17-795.87 -> 0 | H23: =H17-1035.602 -> 0 | I23: =I17-861.46 -> 0 | J23: =J17-506.417 -> 0 | K23: =K17-2034.502 -> 0 | L23: =L17-1593.789 -> 0 | M23: =M17-1660.959 -> 0 | N23: =N17-550.853 -> 0 | O23: =O17-1979.692 -> 0 | P23: =P17-1623.054 -> 0 | Q23: =Q17-1621.847 -> 0 | R23: =R17-39.336 -> 0 | S23: =S17-1468.874 -> 0 | T23: =T17-1679.332 -> 0 | U23: =U17-1909.049 -> 0 | V23: =V17-1148.15 -> 0 | W23: =W17-2614.579 -> 0 | X23: =X17-2513.856 -> 0 | Y23: =Y17-2702.954 -> 0 | Z23: =Z17-2134.268 -> 0 | AA23: =AA17-3213.726 -> 0 | AB23: =AB17-3631.675 -> 0 | AC23: =AC17-3109.41 -> 0 | AD23: =AD17-2767.741 -> 0 | AE23: =AE17-6547.086 -> 0 | AF23: =AF17-4068.586 -> 0
A24: Lucro líquido calculado − informado | B24: NetIncomeLoss | C24: =C19-344.052 -> 0 | D24: =D19-270.65 -> 0 | E24: =E19-665.244 -> 0 | F24: =F19-586.97 -> 0 | G24: =G19-709.067 -> 0 | H24: =H19-720.196 -> 0 | I24: =I19-789.976 -> 0 | J24: =J19-542.156 -> 0 | K24: =K19-1706.715 -> 0 | L24: =L19-1353.013 -> 0 | M24: =M19-1449.071 -> 0 | N24: =N19-607.429 -> 0 | O24: =O19-1597.447 -> 0 | P24: =P19-1440.951 -> 0 | Q24: =Q19-1398.242 -> 0 | R24: =R19-55.284 -> 0 | S24: =S19-1305.12 -> 0 | T24: =T19-1487.61 -> 0 | U24: =U19-1677.422 -> 0 | V24: =V19-937.838 -> 0 | W24: =W19-2332.209 -> 0 | X24: =X19-2147.306 -> 0 | Y24: =Y19-2363.509 -> 0 | Z24: =Z19-1868.607 -> 0 | AA24: =AA19-2890.351 -> 0 | AB24: =AB19-3125.413 -> 0 | AC24: =AC19-2546.916 -> 0 | AD24: =AD19-2418.521 -> 0 | AE24: =AE19-5282.791 -> 0 | AF24: =AF19-3401.414 -> 0
A26: Itens de memória
A27: Ganho (perda) cambial — incluso em "outras" | B27: ForeignCurrencyTransactionGainLoss | C27: 57.6 | D27: -61.284 | E27: 171.36 | F27: -122.1 | G27: 93.06 | H27: -119.161 | I27: -249.194 | J27: -257.983 | K27: 253.33 | L27: -63.074 | M27: 136.488 | N27: 103.917 | O27: 161.821 | P27: 304.513 | Q27: 348.458 | R27: -461.681 | S27: -80.651 | T27: -28.952 | U27: 172.678 | V27: -239.371 | W27: 130.801 | X27: 42.692 | Y27: -104.809 | Z27: 52.855 | AA27: -28.547 | AB27: -55.238 | AC27: 1.707 | AD27: 9.73 | AE27: 10.11 | AF27: 8.813
A28: Amortização de conteúdo — inclusa no custo | B28: nflx:CostofServicesAmortization... | C28: 2124.686 | D28: 2231.915 | E28: 2279.977 | F28: 2579.669 | G28: 2483.385 | H28: 2607.159 | I28: 2733.743 | J28: 2982.625 | K28: 2719.196 | L28: 2806.803 | M28: 2963.051 | N28: 3741.317 | O28: 3166.365 | P28: 3261.348 | Q28: 3653.592 | R28: 3944.827 | S28: 3459.984 | T28: 3410.021 | U28: 3573.353 | V28: 3754.079 | W28: 3670.805 | X28: 3769.69 | Y28: 3699.521 | Z28: 4161.501 | AA28: 3823.112 | AB28: 3832.074 | AC28: 4002.744 | AD28: 4764.236 | AE28: 4217.9 | AF28: 4311.309
A29: Depreciação e amortização (imobilizado e intangíveis) | B29: DepreciationDepletionAndAmortization | C29: 23.561 | D29: 25.496 | E29: 26.704 | F29: 27.818 | G29: 28.517 | H29: 26.661 | I29: 28.589 | J29: 31.943 | K29: 35.741 | L29: 38.434 | M29: 70.253 | N29: 63.984 | O29: 74.602 | P29: 83.505 | Q29: 85.188 | R29: 93.387 | S29: 90.335 | T29: 89.385 | U29: 90.66 | V29: 86.567 | W29: 87.234 | X29: 81.227 | Y29: 80.914 | Z29: 79.539 | AA29: 80.067 | AB29: 80.013 | AC29: 87.326 | AD29: 85.983 | AE29: 98.575 | AF29: 100.53
A30: (=) EBITDA (EBIT + D&A; conteúdo NÃO é somado de volta) | B30: EBIT + D&A | C30: =C14+C29 -> 482.645 | D30: =D14+D29 -> 731.915 | E30: =E14+E29 -> 1006.943 | F30: =F14+F29 -> 486.33 | G30: =G14+G29 -> 986.773 | H30: =H14+H29 -> 1384.589 | I30: =I14+I29 -> 1343.452 | J30: =J14+J29 -> 986.185 | ... AF30: =AF14+AF29 -> 4293.14
A32: Na Netflix a amortização de conteúdo é custo operacional recorrente (substitui o "estoque" de filmes e séries); por isso não é adicionada ao EBITDA.

Sheet BP
A1: Netflix, Inc. — Balanço Patrimonial (fim de cada trimestre)
A2: US$ milhões · Fonte: SEC EDGAR, 10-Q e 10-K (XBRL).
A4: Conta / indicador | B4: Fonte ou fórmula | C4: 2019T1 | D4: 2019T2 | E4: 2019T3 | F4: 2019T4 | G4: 2020T1 | H4: 2020T2 | I4: 2020T3 | J4: 2020T4 | K4: 2021T1 | L4: 2021T2 | M4: 2021T3 | N4: 2021T4 | O4: 2022T1 | P4: 2022T2 | Q4: 2022T3 | R4: 2022T4 | S4: 2023T1 | T4: 2023T2 | U4: 2023T3 | V4: 2023T4 | W4: 2024T1 | X4: 2024T2 | Y4: 2024T3 | Z4: 2024T4 | AA4: 2025T1 | AB4: 2025T2 | AC4: 2025T3 | AD4: 2025T4 | AE4: 2026T1 | AF4: 2026T2
A6: Ativo
A7: Caixa e equivalentes | B7: CashAndCashEquivalents | C7: 3348.557 | D7: 5004.247 | E7: 4435.018 | F7: 5018.437 | G7: 5151.884 | H7: 7153.248 | I7: 8392.391 | J7: 8205.55 | K7: 8403.705 | L7: 7777.53 | M7: 7526.681 | N7: 6027.804 | O7: 6008.946 | P7: 5819.449 | Q7: 6113.733 | R7: 5147.176 | S7: 6714.594 | T7: 7662.788 | U7: 7353.245 | V7: 7116.913 | W7: 7024.766 | X7: 6624.939 | Y7: 7457.025 | Z7: 7804.733 | AA7: 7199.848 | AB7: 8177.405 | AC7: 9287.287 | AD7: 9033.681 | AE7: 12259.772 | AF7: 9099.232
A8: Aplicações financeiras de curto prazo | B8: ShortTermInvestments | C8: 0 | D8: 0 | E8: 0 | F8: 0 | G8: 0 | H8: 0 | I8: 0 | J8: 0 | K8: 0 | L8: 0 | M8: 0 | N8: 0 | O8: 0 | P8: 0 | Q8: 0 | R8: 911.276 | S8: 1112.91 | T8: 914.201 | U8: 514.201 | V8: 20.973 | W8: 20.973 | X8: 30.973 | Y8: 1766.902 | Z8: 1779.006 | AA8: 1171.142 | AB8: 213.115 | AC8: 37.105 | AD8: 28.678 | AE8: 28.678 | AF8: 28.678
A9: Outros ativos circulantes (recebíveis, adiantamentos) | B9: OtherAssetsCurrent | C9: 820.35 | D9: 872.91 | E9: 892.74 | F9: 1160.067 | G9: 1295.897 | H9: 1410.891 | I9: 1434.089 | J9: 1556.03 | K9: 1703.803 | L9: 1826.746 | M9: 1889.106 | N9: 2042.021 | O9: 2089.069 | P9: 2021.329 | Q9: 2703.17 | R9: 3208.021 | S9: 2655.119 | T9: 2929.347 | U9: 2912.028 | V9: 2780.247 | W9: 2875.574 | X9: 2959.641 | Y9: 2905.172 | Z9: 3516.64 | AA9: 3326.642 | AB9: 3602.586 | AC9: 3638.543 | AD9: 3957.832 | AE9: 4782.532 | AF9: 4725.393
A10: ATIVO CIRCULANTE | B10: Soma | C10: =C7+C8+C9 -> 4168.907 | D10: =D7+D8+D9 -> 5877.157 | E10: =E7+E8+E9 -> 5327.758 | F10: =F7+F8+F9 -> 6178.504 | G10: =G7+G8+G9 -> 6447.781 | H10: =H7+H8+H9 -> 8564.139 | I10: =I7+I8+I9 -> 9826.48 | J10: =J7+J8+J9 -> 9761.58 | ... AF10: =AF7+AF8+AF9 -> 13853.303
A11: Ativos de conteúdo (líquidos) | B11: nflx:ContentAssetsNet | C11: 20888.785 | D11: 21945.74 | E11: 23234.994 | F11: 24504.567 | G11: 25266.889 | H11: 25155.117 | I11: 25067.633 | J11: 25383.95 | K11: 26043.991 | L11: 27291.64 | M11: 28974.045 | N11: 30919.539 | O11: 31191.92 | P11: 32533.199 | Q11: 32777.34 | R11: 32736.713 | S11: 32349.184 | T11: 32520.774 | U11: 31749.861 | V11: 31658.056 | W11: 31662.1 | X11: 31927.355 | Y11: 32175.382 | Z11: 32452.462 | AA11: 32040.839 | AB11: 32089.394 | AC11: 32639.879 | AD11: 32778.392 | AE11: 33376.295 | AF11: 33837.573
A12: Imobilizado líquido | B12: PropertyPlantAndEquipmentNet | C12: 434.372 | D12: 452.399 | E12: 481.992 | F12: 565.221 | G12: 650.455 | H12: 751.941 | I12: 828.118 | J12: 960.183 | K12: 1015.419 | L12: 1107.437 | M12: 1220.114 | N12: 1323.453 | O12: 1383.763 | P12: 1361.92 | Q12: 1372.754 | R12: 1398.257 | S12: 1413.094 | T12: 1471.968 | U12: 1498.391 | V12: 1491.444 | W12: 1501.168 | X12: 1510.958 | Y12: 1568.212 | Z12: 1593.756 | AA12: 1644.346 | AB12: 1743.566 | AC12: 1837.889 | AD12: 2004.35 | AE12: 2147.829 | AF12: 2398.848
A13: Outros ativos não circulantes | B13: Ativo total − demais | C13: =C15-C10-C11-C12 -> 1726.568 | D13: =D15-D10-D11-D12 -> 1896.043 | E13: =E15-E10-E11-E12 -> 1896.967 | F13: =F15-F10-F11-F12 -> 2727.42 | G13: =G15-G10-G11-G12 -> 2694.785 | H13: =H15-H10-H11-H12 -> 2704.084 | I13: =I15-I10-I11-I12 -> 2900.312 | J13: =J15-J10-J11-J12 -> 3174.646 | ... AF13: =AF15-AF10-AF11-AF12 -> 8360.717
A14: ATIVO NÃO CIRCULANTE | B14: Soma | C14: =C11+C12+C13 -> 23049.725 | D14: =D11+D12+D13 -> 24294.182 | E14: =E11+E12+E13 -> 25613.953 | F14: =F11+F12+F13 -> 27797.208 | G14: =G11+G12+G13 -> 28612.129 | H14: =H11+H12+H13 -> 28611.142 | I14: =I11+I12+I13 -> 28796.063 | J14: =J11+J12+J13 -> 29518.779 | ... AF14: =AF11+AF12+AF13 -> 44597.138
A15: ATIVO TOTAL | B15: us-gaap:Assets | C15: 27218.632 | D15: 30171.339 | E15: 30941.711 | F15: 33975.712 | G15: 35059.91 | H15: 37175.281 | I15: 38622.543 | J15: 39280.359 | K15: 40123.014 | L15: 40970.969 | M15: 42739.857 | N15: 44584.663 | O15: 45330.904 | P15: 46350.935 | Q15: 47562.187 | R15: 48594.768 | S15: 49490.345 | T15: 50817.473 | U15: 49501.786 | V15: 48731.992 | W15: 48827.721 | X15: 49098.895 | Y15: 52281.844 | Z15: 53630.374 | AA15: 52087.644 | AB15: 53099.664 | AC15: 54934.835 | AD15: 55596.993 | AE15: 61015.914 | AF15: 58450.441
A17: Passivo e patrimônio líquido
A18: Passivos de conteúdo (curto prazo) | B18: nflx:ContentLiabilitiesCurrent | C18: 4863.351 | D18: 4848.201 | E18: 4860.542 | F18: 4413.561 | G18: 4761.585 | H18: 4664.733 | I18: 4599.654 | J18: 4429.536 | K18: 4297.957 | L18: 4197.874 | M18: 4110.962 | N18: 4292.967 | O18: 4066.289 | P18: 4174.966 | Q18: 4225.89 | R18: 4480.15 | S18: 4344.58 | T18: 4440.412 | U18: 4259.582 | V18: 4466.47 | W18: 4436.021 | X18: 4391.437 | Y18: 4489.971 | Z18: 4393.681 | AA18: 4128.905 | AB18: 4091.77 | AC18: 4102.64 | AD18: 4084.854 | AE18: 4052.278 | AF18: 3866.522
A19: Fornecedores | B19: AccountsPayableCurrent | C19: 439.496 | D19: 442.194 | E19: 444.129 | F19: 674.347 | G19: 545.488 | H19: 446.668 | I19: 541.298 | J19: 656.183 | K19: 532.942 | L19: 622.931 | M19: 643.059 | N19: 837.483 | O19: 617.202 | P19: 504.278 | Q19: 560.156 | R19: 671.513 | S19: 591.987 | T19: 615.374 | U19: 534.429 | V19: 747.412 | W19: 607.348 | X19: 598.557 | Y19: 641.953 | Z19: 899.909 | AA19: 614.489 | AB19: 632.718 | AC19: 793.233 | AD19: 900.612 | AE19: 894.681 | AF19: 814.551
A20: Despesas a pagar e provisões | B20: AccruedLiabilitiesCurrent | C20: 746.268 | D20: 750.812 | E20: 1037.723 | F20: 843.043 | G20: 1061.09 | H20: 986.595 | I20: 1259.124 | J20: 1102.196 | K20: 1291.812 | L20: 1125.591 | M20: 1413.12 | N20: 1449.351 | O20: 1817.117 | P20: 1596.035 | Q20: 1803.555 | R20: 1514.65 | S20: 1718.069 | T20: 1908.714 | U20: 1838.908 | V20: 1803.96 | W20: 1977.428 | X20: 1876.244 | Y20: 2241.758 | Z20: 2156.544 | AA20: 2359.518 | AB20: 2489.486 | AC20: 3111.311 | AD20: 3220.869 | AE20: 4441.986 | AF20: 3172.611
A21: Receita diferida (assinaturas pagas antecipadamente) | B21: ContractWithCustomerLiability | C21: 808.692 | D21: 892.777 | E21: 915.506 | F21: 925 | G21: 987 | H21: 1029 | I21: 1040 | J21: 1118 | K21: 1140 | L21: 1187 | M21: 1183 | N21: 1209 | O21: 1239 | P21: 1225 | Q21: 1176 | R21: 1265 | S21: 1262 | T21: 1312 | U21: 1306 | V21: 1443 | W21: 1469 | X21: 1474 | Y21: 1513 | Z21: 1521 | AA21: 1610 | AB21: 1728 | AC21: 1725 | AD21: 1776 | AE21: 1743 | AF21: 1797
A22: Dívida de curto prazo | B22: ShortTermBorrowings | C22: 0 | D22: 0 | E22: 0 | F22: 0 | G22: 499 | H22: 499 | I22: 500 | J22: 499.878 | K22: 699 | L22: 699 | M22: 699 | N22: 699.823 | O22: 0 | P22: 0 | Q22: 0 | R22: 0 | S22: 399 | T22: 399 | U22: 400 | V22: 399.844 | W22: 799 | X22: 1800 | Y22: 1820 | Z22: 1784.453 | AA22: 1006 | AB22: 0 | AC22: 0 | AD22: 998.865 | AE22: 999 | AF22: 2484
A23: Arredondamento entre balanço e notas (resíduo, < US$ 1 mi) | B23: PC informado − soma das linhas | C23: =C24-(C18+C19+C20+C21+C22) -> 0 | D23: =D24-(D18+D19+D20+D21+D22) -> 0 | E23: =E24-(E18+E19+E20+E21+E22) -> 0 | F23: =F24-(F18+F19+F20+F21+F22) -> -0.255 | G23: =G24-(G18+G19+G20+G21+G22) -> -0.438 | H23: =H24-(H18+H19+H20+H21+H22) -> 0.422 | I23: =I24-(I18+I19+I20+I21+I22) -> -0.281 | J23: =J24-(J18+J19+J20+J21+J22) -> -0.008 | ... AF23: =AF24-(AF18+AF19+AF20+AF21+AF22) -> 0.214
A24: PASSIVO CIRCULANTE | B24: LiabilitiesCurrent | C24: 6857.807 | D24: 6933.984 | E24: 7257.9 | F24: 6855.696 | G24: 7853.725 | H24: 7626.418 | I24: 7939.795 | J24: 7805.785 | K24: 7961.77 | L24: 7832.888 | M24: 8049.246 | N24: 8488.966 | O24: 7739.656 | P24: 7500.022 | Q24: 7765.924 | R24: 7930.974 | S24: 8316.07 | T24: 8675.805 | U24: 8338.718 | V24: 8860.655 | W24: 9289.217 | X24: 10139.999 | Y24: 10707.126 | Z24: 10755.4 | AA24: 9718.519 | AB24: 8942.335 | AC24: 9731.859 | AD24: 10980.93 | AE24: 12131.578 | AF24: 12134.898
A25: Passivos de conteúdo (longo prazo) | B25: nflx:ContentLiabilitiesNoncurrent | C25: 3560.364 | D25: 3564.44 | E25: 3419.552 | F25: 3334.323 | G25: 3206.051 | H25: 3208.164 | I25: 2926.574 | J25: 2618.084 | K25: 2465.626 | L25: 2265.286 | M25: 2301.026 | N25: 3094.213 | O25: 2945.221 | P25: 2989.961 | Q25: 2955.368 | R25: 3081.277 | S25: 2908.029 | T25: 2849.387 | U25: 2668.472 | V25: 2578.173 | W25: 2370.692 | X25: 2028.782 | Y25: 1918.089 | Z25: 1780.806 | AA25: 1696.662 | AB25: 1606.404 | AC25: 1591.973 | AD25: 1579.476 | AE25: 1626.498 | AF25: 1625.6
A26: Dívida de longo prazo | B26: LongTermDebtNoncurrent | C26: 10305.023 | D26: 12594 | E26: 12426 | F26: 14759 | G26: 14170.692 | H26: 15294.998 | I26: 15547.616 | J26: 15809.095 | K26: 14860.552 | L26: 14926.889 | M26: 14793.691 | N26: 14693.072 | O26: 14534.561 | P26: 14233.303 | Q26: 13888.117 | R26: 14353.076 | S26: 14037.965 | T26: 14070.151 | U26: 13900.754 | V26: 14143.417 | W26: 13217.038 | X26: 12180.024 | Y26: 14160.932 | Z26: 13798.351 | AA26: 14011.037 | AB26: 14453.206 | AC26: 14463.02 | AD26: 13463.971 | AE26: 13361.331 | AF26: 11825.548
A27: Outros passivos de longo prazo | B27: OtherLiabilitiesNoncurrent | C27: 792.38 | D27: 973.232 | E27: 977.008 | F27: 1444.276 | G27: 1420.148 | H27: 1710.948 | I27: 1875.235 | J27: 1982.155 | K27: 1950.986 | L27: 2082.035 | M27: 2281.277 | N27: 2459.164 | O27: 2567.427 | P27: 2551.675 | Q27: 2424.637 | R27: 2452.04 | S27: 2400.085 | T27: 2389.915 | U27: 2486.215 | V27: 2561.434 | W27: 2585.364 | X27: 2637.397 | Y27: 2774.961 | Z27: 2552.25 | AA27: 2633.353 | AB27: 3145.82 | AC27: 3193.948 | AD27: 2957.128 | AE27: 2770.108 | AF27: 2712.343
A28: Arredondamento entre balanço e notas (resíduo, < US$ 1 mi) | B28: PNC − soma das linhas | C28: =C29-(C25+C26+C27) -> 0 | D28: =D29-(D25+D26+D27) -> 0.135 | E28: =E29-(E25+E26+E27) -> -0.254 | F28: =F29-(F25+F26+F27) -> 0.26 | G28: =G29-(G25+G26+G27) -> 0 | H28: =H29-(H25+H26+H27) -> 0 | I28: =I29-(I25+I26+I27) -> 0 | J28: =J29-(J25+J26+J27) -> 0 | ... AF28: =AF29-(AF25+AF26+AF27) -> 0
A29: PASSIVO NÃO CIRCULANTE | B29: Passivo total − PC | C29: =C30-C24 -> 14657.767 | D29: =D30-D24 -> 17131.807 | E29: =E30-E24 -> 16822.306 | F29: =F30-F24 -> 19537.859 | G29: =G30-G24 -> 18796.891 | H29: =H30-H24 -> 20214.11 | I29: =I30-I24 -> 20349.425 | J29: =J30-J24 -> 20409.334 | ... AF29: =AF30-AF24 -> 16163.491
A30: PASSIVO TOTAL (exigível) | B30: us-gaap:Liabilities | C30: 21515.574 | D30: 24065.791 | E30: 24080.206 | F30: 26393.555 | G30: 26650.616 | H30: 27840.528 | I30: 28289.22 | J30: 28215.119 | K30: 27238.934 | L30: 27107.098 | M30: 27425.24 | N30: 28735.415 | O30: 27786.865 | P30: 27274.961 | Q30: 27034.046 | R30: 27817.367 | S30: 27662.149 | T30: 27985.258 | U30: 27394.159 | V30: 28143.679 | W30: 27462.311 | X30: 26986.202 | Y30: 29561.108 | Z30: 28886.807 | AA30: 28059.571 | AB30: 28147.765 | AC30: 28980.8 | AD30: 28981.505 | AE30: 29889.515 | AF30: 28298.389
A31: PATRIMÔNIO LÍQUIDO | B31: StockholdersEquity | C31: 5703.058 | D31: 6105.548 | E31: 6861.505 | F31: 7582.157 | G31: 8409.294 | H31: 9334.753 | I31: 10333.323 | J31: 11065.24 | K31: 12884.08 | L31: 13863.871 | M31: 15314.617 | N31: 15849.248 | O31: 17544.039 | P31: 19075.974 | Q31: 20528.141 | R31: 20777.401 | S31: 21828.196 | T31: 22832.215 | U31: 22107.627 | V31: 20588.313 | W31: 21365.41 | X31: 22112.693 | Y31: 22720.736 | Z31: 24743.567 | AA31: 24028.073 | AB31: 24951.899 | AC31: 25954.035 | AD31: 26615.488 | AE31: 31126.399 | AF31: 30152.052
A32: PASSIVO TOTAL + PL | B32: Soma | C32: =C30+C31 -> 27218.632 | D32: =D30+D31 -> 30171.339 | E32: =E30+E31 -> 30941.711 | F32: =F30+F31 -> 33975.712 | G32: =G30+G31 -> 35059.91 | H32: =H30+H31 -> 37175.281 | I32: =I30+I31 -> 38622.543 | J32: =J30+J31 -> 39280.359 | ... AF32: =AF30+AF31 -> 58450.441
A34: Conferências (devem dar zero)
A35: Ativo total − (Passivo + PL) | B35: Identidade contábil | C35: =C15-C32 -> 0 | D35: =D15-D32 -> 0 | E35: =E15-E32 -> 0 | F35: =F15-F32 -> 0 | G35: =G15-G32 -> 0 | H35: =H15-H32 -> 0 | I35: =I15-I32 -> 0 | J35: =J15-J32 -> 0 | ... AF35: =AF15-AF32 -> 0
A36: AC calculado − AC informado | B36: AssetsCurrent | C36: =C10-4168.907 -> 0 | D36: =D10-5877.157 -> 0 | E36: =E10-5327.758 -> 0 | F36: =F10-6178.504 -> 0 | G36: =G10-6447.781 -> 0 | H36: =H10-8564.139 -> 0 | I36: =I10-9826.48 -> 0 | J36: =J10-9761.58 -> 0 | K36: =K10-10107.508 -> 0 | L36: =L10-9604.276 -> 0 | M36: =M10-9415.787 -> 0 | N36: =N10-8069.825 -> 0 | O36: =O10-8098.015 -> 0 | P36: =P10-7840.778 -> 0 | Q36: =Q10-8816.903 -> 0 | R36: =R10-9266.473 -> 0 | S36: =S10-10482.623 -> 0 | T36: =T10-11506.336 -> 0 | U36: =U10-10779.474 -> 0 | V36: =V10-9918.133 -> 0 | W36: =W10-9921.313 -> 0 | X36: =X10-9615.553 -> 0 | Y36: =Y10-12129.099 -> 0 | Z36: =Z10-13100.379 -> 0 | AA36: =AA10-11697.632 -> 0 | AB36: =AB10-11993.106 -> 0 | AC36: =AC10-12962.935 -> 0 | AD36: =AD10-13020.191 -> 0 | AE36: =AE10-17070.982 -> 0 | AF36: =AF10-13853.303 -> 0
A37: Resíduo de arredondamento do PC (tolerância US$ 1 mi) | B37: Ver linha do resíduo | C37: =C23 -> 0 | D37: =D23 -> 0 | E37: =E23 -> 0 | F37: =F23 -> -0.255 | G37: =G23 -> -0.438 | H37: =H23 -> 0.422 | I37: =I23 -> -0.281 | J37: =J23 -> -0.008 | ... AF37: =AF23 -> 0.214
A38: Resíduo de arredondamento do PNC (tolerância US$ 1 mi) | B38: Ver linha do resíduo | C38: =C28 -> 0 | D38: =D28 -> 0.135 | E38: =E28 -> -0.254 | F38: =F28 -> 0.26 | G38: =G28 -> 0 | H38: =H28 -> 0 | I38: =I28 -> 0 | J38: =J28 -> 0 | ... AF38: =AF28 -> 0

Sheet DFC
A1: Netflix, Inc. — Fluxo de Caixa (trimestral)
A2: US$ milhões · Fonte: SEC EDGAR. 10-Q traz o acumulado do ano; trimestre = acumulado − acumulado anterior.
A4: Conta / indicador | B4: Fonte ou fórmula | C4: 2019T1 | D4: 2019T2 | E4: 2019T3 | F4: 2019T4 | G4: 2020T1 | H4: 2020T2 | I4: 2020T3 | J4: 2020T4 | K4: 2021T1 | L4: 2021T2 | M4: 2021T3 | N4: 2021T4 | O4: 2022T1 | P4: 2022T2 | Q4: 2022T3 | R4: 2022T4 | S4: 2023T1 | T4: 2023T2 | U4: 2023T3 | V4: 2023T4 | W4: 2024T1 | X4: 2024T2 | Y4: 2024T3 | Z4: 2024T4 | AA4: 2025T1 | AB4: 2025T2 | AC4: 2025T3 | AD4: 2025T4 | AE4: 2026T1 | AF4: 2026T2
A6: Fluxos de caixa
A7: Fluxo de caixa operacional (FCO) | B7: NetCashProvidedByOperating | C7: -379.799 | D7: -543.754 | E7: -501.794 | F7: -1461.975 | G7: 259.912 | H7: 1041.076 | I7: 1263.761 | J7: -137.672 | K7: 777.266 | L7: -63.761 | M7: 82.379 | N7: -403.274 | O7: 922.839 | P7: 102.75 | Q7: 556.81 | R7: 443.858 | S7: 2178.74 | T7: 1440.232 | U7: 1992.315 | V7: 1663.014 | W7: 2212.522 | X7: 1290.847 | Y7: 2321.101 | Z7: 1536.894 | AA7: 2789.199 | AB7: 2423.258 | AC7: 2825.174 | AD7: 2111.642 | AE7: 5290.205 | AF7: 1743.812
A8: (−) Compras de imobilizado (Capex) | B8: PaymentsToAcquirePP&E | C8: 60.381 | D8: 39.584 | E8: 45.333 | F8: 107.737 | G8: 98.015 | H8: 141.741 | I8: 109.811 | J8: 148.356 | K8: 81.001 | L8: 110.278 | M8: 167.327 | N8: 165.979 | O8: 121.158 | P8: 90.018 | Q8: 84.96 | R8: 111.593 | S8: 62.019 | T8: 100.972 | U8: 103.929 | V8: 81.632 | W8: 75.714 | X8: 78.287 | Y8: 126.863 | Z8: 158.674 | AA8: 128.277 | AB8: 155.889 | AC8: 164.719 | AD8: 239.335 | AE8: 196.13 | AF8: 218.644
A9: (=) Fluxo de caixa livre simplificado (FCO − Capex) | B9: FCO − Capex | C9: =C7-C8 -> -440.18 | D9: =D7-D8 -> -583.338 | E9: =E7-E8 -> -547.127 | F9: =F7-F8 -> -1569.712 | G9: =G7-G8 -> 161.897 | H9: =H7-H8 -> 899.335 | I9: =I7-I8 -> 1153.95 | J9: =J7-J8 -> -286.028 | ... AF9: =AF7-AF8 -> 1525.168
A10: Fluxo de caixa de investimento | B10: NetCashInvesting | C10: -80.103 | D10: -50.036 | E10: -49.354 | F10: -207.571 | G10: -98.303 | H10: -142.001 | I10: -118.651 | J10: -146.399 | K10: -85.616 | L10: -111.278 | M10: -188.631 | N10: -954.328 | O10: -245.679 | P10: -158.894 | Q10: -84.96 | R10: -1586.859 | S10: -263.653 | T10: 97.737 | U10: 296.071 | V10: 411.596 | W10: -75.714 | X10: -78.287 | Y10: -1869.109 | Z10: -158.674 | AA10: 485.662 | AB10: 768.684 | AC10: 43.871 | AD10: -256.529 | AE10: -781.874 | AF10: -218.644
A11: Fluxo de caixa de financiamento | B11: NetCashFinancing | C11: 22.972 | D11: 2246.9 | E11: 11.989 | F11: 2223.801 | G11: 43.694 | H11: 1090.965 | I11: 68.665 | J11: 33.987 | K11: -451.929 | L11: -480.273 | M11: -81.555 | N11: -136.019 | O11: -686.322 | P11: 11.25 | Q11: 4.113 | R11: 6.705 | S11: -374.073 | T11: -649.349 | U11: -2475.108 | V11: -2452.273 | W11: -2132.944 | X11: -1489.381 | Y11: 226.596 | Z11: -678.698 | AA11: -4028.316 | AB11: -2502.868 | AC11: -1737.029 | AD11: -2077.41 | AE11: -1230.814 | AF11: -4669.627
A12: Recompra de ações (saída de caixa) | B12: PaymentsForRepurchaseOfCommonStock | C12: 0 | D12: 0 | E12: 0 | F12: 0 | G12: 0 | H12: 0 | I12: 0 | J12: 0 | K12: 0 | L12: 500.022 | M12: 100 | N12: 0 | O12: 0 | P12: 0 | Q12: 0 | R12: 0 | S12: 400.101 | T12: 645.146 | U12: 2500.1 | V12: 2500 | W12: 2000 | X12: 1599.998 | Y12: 1700 | Z12: 963.748 | AA12: 3536.396 | AB12: 1654.327 | AC12: 1856.885 | AD12: 2079.559 | AE12: 1270.588 | AF12: 4714.403
A14: Conteúdo: competência x caixa (a chave para entender o caixa da Netflix)
A15: Pagamentos de conteúdo (caixa) | B15: nflx:AdditionsToStreamingContentAssets | C15: 2997.746 | D15: 3325.103 | E15: 3648.292 | F15: 3945.542 | G15: 3294.275 | H15: 2510.782 | I15: 2653.886 | J15: 3320.341 | K15: 3284.576 | L15: 4096.75 | M15: 4666.237 | N15: 5654.639 | O15: 3584.164 | P15: 4687.011 | Q15: 4582.671 | R15: 3985.192 | S15: 2458.666 | T15: 3683.007 | U15: 2883.839 | V15: 3529.191 | W15: 3728.967 | X15: 4048.852 | Y15: 4016.396 | Z15: 4429.402 | AA15: 3549.657 | AB15: 3835.813 | AC15: 4653.935 | AD15: 5057.212 | AE15: 4846.917 | AF15: 4927.523
A16: Amortização de conteúdo (DRE) | B16: Igual à DRE | C16: =DRE!C28 -> 2124.686 | D16: =DRE!D28 -> 2231.915 | E16: =DRE!E28 -> 2279.977 | F16: =DRE!F28 -> 2579.669 | G16: =DRE!G28 -> 2483.385 | H16: =DRE!H28 -> 2607.159 | I16: =DRE!I28 -> 2733.743 | J16: =DRE!J28 -> 2982.625 | ... AF16: =DRE!AF28 -> 4311.309
A17: Razão pagamento / amortização | B17: > 1 = investe mais do que amortiza | C17: =IFERROR(C15/C16,"") -> 1.4109125 | D17: =IFERROR(D15/D16,"") -> 1.4897982 | E17: =IFERROR(E15/E16,"") -> 1.6001442 | F17: =IFERROR(F15/F16,"") -> 1.5294761 | G17: =IFERROR(G15/G16,"") -> 1.3265261 | H17: =IFERROR(H15/H16,"") -> 0.96303371 | I17: =IFERROR(I15/I16,"") -> 0.9707884 | J17: =IFERROR(J15/J16,"") -> 1.1132278 | ... AF17: =IFERROR(AF15/AF16,"") -> 1.1429297
A18: Remuneração em ações (não-caixa) | B18: ShareBasedCompensation | C18: 101.2 | D18: 103.848 | E18: 100.262 | F18: 100.066 | G18: 97.019 | H18: 104.21 | I18: 106.357 | J18: 107.594 | K18: 107.23 | L18: 101.583 | M18: 95.078 | N18: 99.329 | O18: 119.209 | P18: 150.392 | Q18: 152.062 | R18: 153.789 | S18: 99.099 | T18: 78.03 | U18: 79.72 | V18: 82.519 | W18: 76.345 | X18: 68.766 | Y18: 65.65 | Z18: 61.827 | AA18: 71.977 | AB18: 80.862 | AC18: 80.986 | AD18: 134.624 | AE18: 140.405 | AF18: 131.312
A20: A Netflix define FCL como FCO − Capex − variação de outros ativos; a versão simplificada daqui difere em poucos milhões.

Sheet AV
A1: Análise Vertical (AV)
A2: DRE: % da Receita líquida · BP: % do Ativo total — fórmula da disciplina: conta / base
A4: Conta / indicador | B4: Fonte ou fórmula | C4: 2019T1 | D4: 2019T2 | E4: 2019T3 | F4: 2019T4 | G4: 2020T1 | H4: 2020T2 | I4: 2020T3 | J4: 2020T4 | K4: 2021T1 | L4: 2021T2 | M4: 2021T3 | N4: 2021T4 | O4: 2022T1 | P4: 2022T2 | Q4: 2022T3 | R4: 2022T4 | S4: 2023T1 | T4: 2023T2 | U4: 2023T3 | V4: 2023T4 | W4: 2024T1 | X4: 2024T2 | Y4: 2024T3 | Z4: 2024T4 | AA4: 2025T1 | AB4: 2025T2 | AC4: 2025T3 | AD4: 2025T4 | AE4: 2026T1 | AF4: 2026T2
A6: DRE — % da receita líquida
A7: Receita líquida | C7: =IFERROR(DRE!C7/DRE!C7,"") -> 1 | D7: =IFERROR(DRE!D7/DRE!D7,"") -> 1 | E7: =IFERROR(DRE!E7/DRE!E7,"") -> 1 | F7: =IFERROR(DRE!F7/DRE!F7,"") -> 1 | G7: =IFERROR(DRE!G7/DRE!G7,"") -> 1 | H7: =IFERROR(DRE!H7/DRE!H7,"") -> 1 | I7: =IFERROR(DRE!I7/DRE!I7,"") -> 1 | J7: =IFERROR(DRE!J7/DRE!J7,"") -> 1 | ... AF7: =IFERROR(DRE!AF7/DRE!AF7,"") -> 1
A8: Custo dos serviços | C8: =IFERROR(DRE!C8/DRE!C7,"") -> 0.63495224 | D8: =IFERROR(DRE!D8/DRE!D7,"") -> 0.61051923 | E8: =IFERROR(DRE!E8/DRE!E7,"") -> 0.59065302 | F8: =IFERROR(DRE!F8/DRE!F7,"") -> 0.63393961 | G8: =IFERROR(DRE!G8/DRE!G7,"") -> 0.62411475 | H8: =IFERROR(DRE!H8/DRE!H7,"") -> 0.59263785 | I8: =IFERROR(DRE!I8/DRE!I7,"") -> 0.60098961 | J8: =IFERROR(DRE!J8/DRE!J7,"") -> 0.62686378 | ... AF8: =IFERROR(DRE!AF8/DRE!AF7,"") -> 0.48065245
A9: Lucro bruto | C9: =IFERROR(DRE!C9/DRE!C7,"") -> 0.36504776 | D9: =IFERROR(DRE!D9/DRE!D7,"") -> 0.38948077 | E9: =IFERROR(DRE!E9/DRE!E7,"") -> 0.40934698 | F9: =IFERROR(DRE!F9/DRE!F7,"") -> 0.36606039 | G9: =IFERROR(DRE!G9/DRE!G7,"") -> 0.37588525 | H9: =IFERROR(DRE!H9/DRE!H7,"") -> 0.40736215 | I9: =IFERROR(DRE!I9/DRE!I7,"") -> 0.39901039 | J9: =IFERROR(DRE!J9/DRE!J7,"") -> 0.37313622 | ... AF9: =IFERROR(DRE!AF9/DRE!AF7,"") -> 0.51934755
A10: Marketing | C10: =IFERROR(DRE!C10/DRE!C7,"") -> 0.13638113 | D10: =IFERROR(DRE!D10/DRE!D7,"") -> 0.12251387 | E10: =IFERROR(DRE!E10/DRE!E7,"") -> 0.10558761 | F10: =IFERROR(DRE!F10/DRE!F7,"") -> 0.16075859 | G10: =IFERROR(DRE!G10/DRE!G7,"") -> 0.087353847 | H10: =IFERROR(DRE!H10/DRE!H7,"") -> 0.070648958 | I10: =IFERROR(DRE!I10/DRE!I7,"") -> 0.081980541 | J10: =IFERROR(DRE!J10/DRE!J7,"") -> 0.11476735 | ... AF10: =IFERROR(DRE!AF10/DRE!AF7,"") -> 0.065592521
A11: Tecnologia | C11: =IFERROR(DRE!C11/DRE!C7,"") -> 0.082451816 | D11: =IFERROR(DRE!D11/DRE!D7,"") -> 0.077843585 | E11: =IFERROR(DRE!E11/DRE!E7,"") -> 0.072408556 | F11: =IFERROR(DRE!F11/DRE!F7,"") -> 0.074875344 | G11: =IFERROR(DRE!G11/DRE!G7,"") -> 0.078682613 | H11: =IFERROR(DRE!H11/DRE!H7,"") -> 0.070758745 | I11: =IFERROR(DRE!I11/DRE!I7,"") -> 0.070513921 | J11: =IFERROR(DRE!J11/DRE!J7,"") -> 0.073284709 | ... AF11: =IFERROR(DRE!AF11/DRE!AF7,"") -> 0.080229297
A12: Gerais e administrativas | C12: =IFERROR(DRE!C12/DRE!C7,"") -> 0.044669842 | D12: =IFERROR(DRE!D12/DRE!D7,"") -> 0.045633091 | E12: =IFERROR(DRE!E12/DRE!E7,"") -> 0.04445724 | F12: =IFERROR(DRE!F12/DRE!F7,"") -> 0.046564074 | G12: =IFERROR(DRE!G12/DRE!G7,"") -> 0.043706745 | H12: =IFERROR(DRE!H12/DRE!H7,"") -> 0.045091591 | I12: =IFERROR(DRE!I12/DRE!I7,"") -> 0.042206234 | J12: =IFERROR(DRE!J12/DRE!J7,"") -> 0.041469096 | ... AF12: =IFERROR(DRE!AF12/DRE!AF7,"") -> 0.039717553
A13: EBIT | C13: =IFERROR(DRE!C14/DRE!C7,"") -> 0.10154497 | D13: =IFERROR(DRE!D14/DRE!D7,"") -> 0.14349022 | E13: =IFERROR(DRE!E14/DRE!E7,"") -> 0.18689357 | F13: =IFERROR(DRE!F14/DRE!F7,"") -> 0.083862375 | G13: =IFERROR(DRE!G14/DRE!G7,"") -> 0.16614205 | H13: =IFERROR(DRE!H14/DRE!H7,"") -> 0.22086286 | I13: =IFERROR(DRE!I14/DRE!I7,"") -> 0.20430969 | J13: =IFERROR(DRE!J14/DRE!J7,"") -> 0.14361507 | ... AF13: =IFERROR(DRE!AF14/DRE!AF7,"") -> 0.33380818
A14: Despesa de juros | C14: =IFERROR(DRE!C15/DRE!C7,"") -> 0.029977713 | D14: =IFERROR(DRE!D15/DRE!D7,"") -> 0.030881458 | E14: =IFERROR(DRE!E15/DRE!E7,"") -> 0.030631632 | F14: =IFERROR(DRE!F15/DRE!F7,"") -> 0.032520008 | G14: =IFERROR(DRE!G15/DRE!G7,"") -> 0.031916238 | H14: =IFERROR(DRE!H15/DRE!H7,"") -> 0.030764834 | I14: =IFERROR(DRE!I15/DRE!I7,"") -> 0.030623076 | J14: =IFERROR(DRE!J15/DRE!J7,"") -> 0.029676834 | ... AF14: =IFERROR(DRE!AF15/DRE!AF7,"") -> 0.013987728
A15: Outras receitas/despesas financeiras | C15: =IFERROR(DRE!C16/DRE!C7,"") -> 0.016833474 | D15: =IFERROR(DRE!D16/DRE!D7,"") -> -0.010861008 | E15: =IFERROR(DRE!E16/DRE!E7,"") -> 0.036748807 | F15: =IFERROR(DRE!F16/DRE!F7,"") -> -0.024029188 | G15: =IFERROR(DRE!G16/DRE!G7,"") -> 0.0037618173 | H15: =IFERROR(DRE!H16/DRE!H7,"") -> -0.021660508 | I15: =IFERROR(DRE!I16/DRE!I7,"") -> -0.039828847 | J15: =IFERROR(DRE!J16/DRE!J7,"") -> -0.037721603 | ... AF15: =IFERROR(DRE!AF16/DRE!AF7,"") -> 0.0041131572
A16: LAIR | C16: =IFERROR(DRE!C17/DRE!C7,"") -> 0.088400732 | D16: =IFERROR(DRE!D17/DRE!D7,"") -> 0.10174775 | E16: =IFERROR(DRE!E17/DRE!E7,"") -> 0.19301074 | F16: =IFERROR(DRE!F17/DRE!F7,"") -> 0.027313178 | G16: =IFERROR(DRE!G17/DRE!G7,"") -> 0.13798763 | H16: =IFERROR(DRE!H17/DRE!H7,"") -> 0.16843751 | I16: =IFERROR(DRE!I17/DRE!I7,"") -> 0.13385777 | J16: =IFERROR(DRE!J17/DRE!J7,"") -> 0.076216633 | ... AF16: =IFERROR(DRE!AF17/DRE!AF7,"") -> 0.32393361
A17: Imposto de renda | C17: =IFERROR(DRE!C18/DRE!C7,"") -> 0.012299734 | D17: =IFERROR(DRE!D18/DRE!D7,"") -> 0.04677241 | E17: =IFERROR(DRE!E18/DRE!E7,"") -> 0.066174506 | F17: =IFERROR(DRE!F18/DRE!F7,"") -> -0.080044313 | G17: =IFERROR(DRE!G18/DRE!G7,"") -> 0.01504987 | H17: =IFERROR(DRE!H18/DRE!H7,"") -> 0.051299826 | I17: =IFERROR(DRE!I18/DRE!I7,"") -> 0.011107525 | J17: =IFERROR(DRE!J18/DRE!J7,"") -> -0.0053787812 | ... AF17: =IFERROR(DRE!AF18/DRE!AF7,"") -> 0.053119052
A18: Lucro líquido | C18: =IFERROR(DRE!C19/DRE!C7,"") -> 0.076100997 | D18: =IFERROR(DRE!D19/DRE!D7,"") -> 0.054975345 | E18: =IFERROR(DRE!E19/DRE!E7,"") -> 0.12683623 | F18: =IFERROR(DRE!F19/DRE!F7,"") -> 0.10735749 | G18: =IFERROR(DRE!G19/DRE!G7,"") -> 0.12293776 | H18: =IFERROR(DRE!H19/DRE!H7,"") -> 0.11713769 | I18: =IFERROR(DRE!I19/DRE!I7,"") -> 0.12275024 | J18: =IFERROR(DRE!J19/DRE!J7,"") -> 0.081595415 | ... AF18: =IFERROR(DRE!AF19/DRE!AF7,"") -> 0.27081455
A19: Amortização de conteúdo | C19: =IFERROR(DRE!C28/DRE!C7,"") -> 0.46996013 | D19: =IFERROR(DRE!D28/DRE!D7,"") -> 0.45335414 | E19: =IFERROR(DRE!E28/DRE!E7,"") -> 0.4347032 | F19: =IFERROR(DRE!F28/DRE!F7,"") -> 0.47182444 | G19: =IFERROR(DRE!G28/DRE!G7,"") -> 0.43056832 | H19: =IFERROR(DRE!H28/DRE!H7,"") -> 0.42404647 | I19: =IFERROR(DRE!I28/DRE!I7,"") -> 0.42478204 | J19: =IFERROR(DRE!J28/DRE!J7,"") -> 0.44889022 | ... AF19: =IFERROR(DRE!AF28/DRE!AF7,"") -> 0.34325878
A20: EBITDA | C20: =IFERROR(DRE!C30/DRE!C7,"") -> 0.10675644 | D20: =IFERROR(DRE!D30/DRE!D7,"") -> 0.14866905 | E20: =IFERROR(DRE!E30/DRE!E7,"") -> 0.19198498 | F20: =IFERROR(DRE!F30/DRE!F7,"") -> 0.088950319 | G20: =IFERROR(DRE!G30/DRE!G7,"") -> 0.17108632 | H20: =IFERROR(DRE!H30/DRE!H7,"") -> 0.22519919 | I20: =IFERROR(DRE!I30/DRE!I7,"") -> 0.20875199 | J20: =IFERROR(DRE!J30/DRE!J7,"") -> 0.14842255 | ... AF20: =IFERROR(DRE!AF30/DRE!AF7,"") -> 0.3418122
A22: Balanço — % do ativo total
A23: Caixa | C23: =IFERROR(BP!C7/BP!C15,"") -> 0.12302444 | D23: =IFERROR(BP!D7/BP!D15,"") -> 0.16586095 | E23: =IFERROR(BP!E7/BP!E15,"") -> 0.14333461 | F23: =IFERROR(BP!F7/BP!F15,"") -> 0.1477066 | G23: =IFERROR(BP!G7/BP!G15,"") -> 0.14694516 | H23: =IFERROR(BP!H7/BP!H15,"") -> 0.19241947 | I23: =IFERROR(BP!I7/BP!I15,"") -> 0.21729255 | J23: =IFERROR(BP!J7/BP!J15,"") -> 0.20889702 | ... AF23: =IFERROR(BP!AF7/BP!AF15,"") -> 0.15567431
A24: Aplicações CP | C24: =IFERROR(BP!C8/BP!C15,"") -> 0 | D24: =IFERROR(BP!D8/BP!D15,"") -> 0 | E24: =IFERROR(BP!E8/BP!E15,"") -> 0 | F24: =IFERROR(BP!F8/BP!F15,"") -> 0 | G24: =IFERROR(BP!G8/BP!G15,"") -> 0 | H24: =IFERROR(BP!H8/BP!H15,"") -> 0 | I24: =IFERROR(BP!I8/BP!I15,"") -> 0 | J24: =IFERROR(BP!J8/BP!J15,"") -> 0 | ... AF24: =IFERROR(BP!AF8/BP!AF15,"") -> 0.00049063787
A25: Outros AC | C25: =IFERROR(BP!C9/BP!C15,"") -> 0.030139281 | D25: =IFERROR(BP!D9/BP!D15,"") -> 0.028931762 | E25: =IFERROR(BP!E9/BP!E15,"") -> 0.028852315 | F25: =IFERROR(BP!F9/BP!F15,"") -> 0.034144009 | G25: =IFERROR(BP!G9/BP!G15,"") -> 0.03696236 | H25: =IFERROR(BP!H9/BP!H15,"") -> 0.037952396 | I25: =IFERROR(BP!I9/BP!I15,"") -> 0.03713088 | J25: =IFERROR(BP!J9/BP!J15,"") -> 0.039613436 | ... AF25: =IFERROR(BP!AF9/BP!AF15,"") -> 0.080844437
A26: Ativo circulante | C26: =IFERROR(BP!C10/BP!C15,"") -> 0.15316372 | D26: =IFERROR(BP!D10/BP!D15,"") -> 0.19479271 | E26: =IFERROR(BP!E10/BP!E15,"") -> 0.17218692 | F26: =IFERROR(BP!F10/BP!F15,"") -> 0.18185061 | G26: =IFERROR(BP!G10/BP!G15,"") -> 0.18390752 | H26: =IFERROR(BP!H10/BP!H15,"") -> 0.23037187 | I26: =IFERROR(BP!I10/BP!I15,"") -> 0.25442343 | J26: =IFERROR(BP!J10/BP!J15,"") -> 0.24851046 | ... AF26: =IFERROR(BP!AF10/BP!AF15,"") -> 0.23700938
A27: Ativos de conteúdo | C27: =IFERROR(BP!C11/BP!C15,"") -> 0.76744434 | D27: =IFERROR(BP!D11/BP!D15,"") -> 0.72737044 | E27: =IFERROR(BP!E11/BP!E15,"") -> 0.7509279 | F27: =IFERROR(BP!F11/BP!F15,"") -> 0.72123778 | G27: =IFERROR(BP!G11/BP!G15,"") -> 0.72067752 | H27: =IFERROR(BP!H11/BP!H15,"") -> 0.67666246 | I27: =IFERROR(BP!I11/BP!I15,"") -> 0.64904149 | J27: =IFERROR(BP!J11/BP!J15,"") -> 0.646225 | ... AF27: =IFERROR(BP!AF11/BP!AF15,"") -> 0.57891048
A28: Imobilizado | C28: =IFERROR(BP!C12/BP!C15,"") -> 0.015958627 | D28: =IFERROR(BP!D12/BP!D15,"") -> 0.01499433 | E28: =IFERROR(BP!E12/BP!E15,"") -> 0.015577419 | F28: =IFERROR(BP!F12/BP!F15,"") -> 0.016636031 | G28: =IFERROR(BP!G12/BP!G15,"") -> 0.018552672 | H28: =IFERROR(BP!H12/BP!H15,"") -> 0.020226908 | I28: =IFERROR(BP!I12/BP!I15,"") -> 0.021441312 | J28: =IFERROR(BP!J12/BP!J15,"") -> 0.024444354 | ... AF28: =IFERROR(BP!AF12/BP!AF15,"") -> 0.041040717
A29: Outros ANC | C29: =IFERROR(BP!C13/BP!C15,"") -> 0.063433313 | D29: =IFERROR(BP!D13/BP!D15,"") -> 0.062842521 | E29: =IFERROR(BP!E13/BP!E15,"") -> 0.06130776 | F29: =IFERROR(BP!F13/BP!F15,"") -> 0.08027558 | G29: =IFERROR(BP!G13/BP!G15,"") -> 0.076862291 | H29: =IFERROR(BP!H13/BP!H15,"") -> 0.072738764 | I29: =IFERROR(BP!I13/BP!I15,"") -> 0.075093761 | J29: =IFERROR(BP!J13/BP!J15,"") -> 0.080820188 | ... AF29: =IFERROR(BP!AF13/BP!AF15,"") -> 0.14303942
A30: Ativo total | C30: =IFERROR(BP!C15/BP!C15,"") -> 1 | D30: =IFERROR(BP!D15/BP!D15,"") -> 1 | E30: =IFERROR(BP!E15/BP!E15,"") -> 1 | F30: =IFERROR(BP!F15/BP!F15,"") -> 1 | G30: =IFERROR(BP!G15/BP!G15,"") -> 1 | H30: =IFERROR(BP!H15/BP!H15,"") -> 1 | I30: =IFERROR(BP!I15/BP!I15,"") -> 1 | J30: =IFERROR(BP!J15/BP!J15,"") -> 1 | ... AF30: =IFERROR(BP!AF15/BP!AF15,"") -> 1
A31: Passivo de conteúdo CP | C31: =IFERROR(BP!C18/BP!C15,"") -> 0.17867728 | D31: =IFERROR(BP!D18/BP!D15,"") -> 0.16068896 | E31: =IFERROR(BP!E18/BP!E15,"") -> 0.15708705 | F31: =IFERROR(BP!F18/BP!F15,"") -> 0.12990341 | G31: =IFERROR(BP!G18/BP!G15,"") -> 0.13581281 | H31: =IFERROR(BP!H18/BP!H15,"") -> 0.12547943 | I31: =IFERROR(BP!I18/BP!I15,"") -> 0.11909247 | J31: =IFERROR(BP!J18/BP!J15,"") -> 0.1127672 | ... AF31: =IFERROR(BP!AF18/BP!AF15,"") -> 0.066150433
A32: Fornecedores | C32: =IFERROR(BP!C19/BP!C15,"") -> 0.016146881 | D32: =IFERROR(BP!D19/BP!D15,"") -> 0.014656095 | E32: =IFERROR(BP!E19/BP!E15,"") -> 0.014353731 | F32: =IFERROR(BP!F19/BP!F15,"") -> 0.019847914 | G32: =IFERROR(BP!G19/BP!G15,"") -> 0.015558739 | H32: =IFERROR(BP!H19/BP!H15,"") -> 0.012015188 | I32: =IFERROR(BP!I19/BP!I15,"") -> 0.014015079 | J32: =IFERROR(BP!J19/BP!J15,"") -> 0.016705117 | ... AF32: =IFERROR(BP!AF19/BP!AF15,"") -> 0.013935755
A33: Provisões | C33: =IFERROR(BP!C20/BP!C15,"") -> 0.027417543 | D33: =IFERROR(BP!D20/BP!D15,"") -> 0.024884941 | E33: =IFERROR(BP!E20/BP!E15,"") -> 0.033537997 | F33: =IFERROR(BP!F20/BP!F15,"") -> 0.024813108 | G33: =IFERROR(BP!G20/BP!G15,"") -> 0.030265052 | H33: =IFERROR(BP!H20/BP!H15,"") -> 0.026539006 | I33: =IFERROR(BP!I20/BP!I15,"") -> 0.032600753 | J33: =IFERROR(BP!J20/BP!J15,"") -> 0.028059723 | ... AF33: =IFERROR(BP!AF20/BP!AF15,"") -> 0.054278649
A34: Receita diferida | C34: =IFERROR(BP!C21/BP!C15,"") -> 0.029710972 | D34: =IFERROR(BP!D21/BP!D15,"") -> 0.029590235 | E34: =IFERROR(BP!E21/BP!E15,"") -> 0.029588086 | F34: =IFERROR(BP!F21/BP!F15,"") -> 0.027225331 | G34: =IFERROR(BP!G21/BP!G15,"") -> 0.028151812 | H34: =IFERROR(BP!H21/BP!H15,"") -> 0.027679683 | I34: =IFERROR(BP!I21/BP!I15,"") -> 0.026927279 | J34: =IFERROR(BP!J21/BP!J15,"") -> 0.028462062 | ... AF34: =IFERROR(BP!AF21/BP!AF15,"") -> 0.030743994
A35: Dívida CP | C35: =IFERROR(BP!C22/BP!C15,"") -> 0 | D35: =IFERROR(BP!D22/BP!D15,"") -> 0 | E35: =IFERROR(BP!E22/BP!E15,"") -> 0 | F35: =IFERROR(BP!F22/BP!F15,"") -> 0 | G35: =IFERROR(BP!G22/BP!G15,"") -> 0.01423278 | H35: =IFERROR(BP!H22/BP!H15,"") -> 0.013422898 | I35: =IFERROR(BP!I22/BP!I15,"") -> 0.012945807 | J35: =IFERROR(BP!J22/BP!J15,"") -> 0.012725902 | ... AF35: =IFERROR(BP!AF22/BP!AF15,"") -> 0.042497541
A36: Passivo circulante | C36: =IFERROR(BP!C24/BP!C15,"") -> 0.25195267 | D36: =IFERROR(BP!D24/BP!D15,"") -> 0.22982023 | E36: =IFERROR(BP!E24/BP!E15,"") -> 0.23456686 | F36: =IFERROR(BP!F24/BP!F15,"") -> 0.20178226 | G36: =IFERROR(BP!G24/BP!G15,"") -> 0.2240087 | H36: =IFERROR(BP!H24/BP!H15,"") -> 0.20514755 | I36: =IFERROR(BP!I24/BP!I15,"") -> 0.20557411 | J36: =IFERROR(BP!J24/BP!J15,"") -> 0.1987198 | ... AF36: =IFERROR(BP!AF24/BP!AF15,"") -> 0.20761003
A37: Passivo de conteúdo LP | C37: =IFERROR(BP!C25/BP!C15,"") -> 0.13080613 | D37: =IFERROR(BP!D25/BP!D15,"") -> 0.11813993 | E37: =IFERROR(BP!E25/BP!E15,"") -> 0.11051593 | F37: =IFERROR(BP!F25/BP!F15,"") -> 0.098138429 | G37: =IFERROR(BP!G25/BP!G15,"") -> 0.09144493 | H37: =IFERROR(BP!H25/BP!H15,"") -> 0.086298312 | I37: =IFERROR(BP!I25/BP!I15,"") -> 0.075773726 | J37: =IFERROR(BP!J25/BP!J15,"") -> 0.066651224 | ... AF37: =IFERROR(BP!AF25/BP!AF15,"") -> 0.027811595
A38: Dívida LP | C38: =IFERROR(BP!C26/BP!C15,"") -> 0.3786018 | D38: =IFERROR(BP!D26/BP!D15,"") -> 0.41741601 | E38: =IFERROR(BP!E26/BP!E15,"") -> 0.40159382 | F38: =IFERROR(BP!F26/BP!F15,"") -> 0.43439855 | G38: =IFERROR(BP!G26/BP!G15,"") -> 0.40418506 | H38: =IFERROR(BP!H26/BP!H15,"") -> 0.41142925 | I38: =IFERROR(BP!I26/BP!I15,"") -> 0.40255288 | J38: =IFERROR(BP!J26/BP!J15,"") -> 0.40246819 | ... AF38: =IFERROR(BP!AF26/BP!AF15,"") -> 0.20231752
A39: Outros PLP | C39: =IFERROR(BP!C27/BP!C15,"") -> 0.029111676 | D39: =IFERROR(BP!D27/BP!D15,"") -> 0.032256838 | E39: =IFERROR(BP!E27/BP!E15,"") -> 0.031575759 | F39: =IFERROR(BP!F27/BP!F15,"") -> 0.042509072 | G39: =IFERROR(BP!G27/BP!G15,"") -> 0.040506322 | H39: =IFERROR(BP!H27/BP!H15,"") -> 0.046023808 | I39: =IFERROR(BP!I27/BP!I15,"") -> 0.048552862 | J39: =IFERROR(BP!J27/BP!J15,"") -> 0.050461733 | ... AF39: =IFERROR(BP!AF27/BP!AF15,"") -> 0.046404149
A40: Passivo não circulante | C40: =IFERROR(BP!C29/BP!C15,"") -> 0.53851961 | D40: =IFERROR(BP!D29/BP!D15,"") -> 0.56781726 | E40: =IFERROR(BP!E29/BP!E15,"") -> 0.5436773 | F40: =IFERROR(BP!F29/BP!F15,"") -> 0.5750537 | G40: =IFERROR(BP!G29/BP!G15,"") -> 0.53613632 | H40: =IFERROR(BP!H29/BP!H15,"") -> 0.54375137 | I40: =IFERROR(BP!I29/BP!I15,"") -> 0.52687947 | J40: =IFERROR(BP!J29/BP!J15,"") -> 0.51958115 | ... AF40: =IFERROR(BP!AF29/BP!AF15,"") -> 0.27653326
A41: Patrimônio líquido | C41: =IFERROR(BP!C31/BP!C15,"") -> 0.20952772 | D41: =IFERROR(BP!D31/BP!D15,"") -> 0.20236251 | E41: =IFERROR(BP!E31/BP!E15,"") -> 0.22175584 | F41: =IFERROR(BP!F31/BP!F15,"") -> 0.22316404 | G41: =IFERROR(BP!G31/BP!G15,"") -> 0.23985498 | H41: =IFERROR(BP!H31/BP!H15,"") -> 0.25110107 | I41: =IFERROR(BP!I31/BP!I15,"") -> 0.26754642 | J41: =IFERROR(BP!J31/BP!J15,"") -> 0.28169905 | ... AF41: =IFERROR(BP!AF31/BP!AF15,"") -> 0.51585671
A42: Passivo + PL | C42: =IFERROR(BP!C32/BP!C15,"") -> 1 | D42: =IFERROR(BP!D32/BP!D15,"") -> 1 | E42: =IFERROR(BP!E32/BP!E15,"") -> 1 | F42: =IFERROR(BP!F32/BP!F15,"") -> 1 | G42: =IFERROR(BP!G32/BP!G15,"") -> 1 | H42: =IFERROR(BP!H32/BP!H15,"") -> 1 | I42: =IFERROR(BP!I32/BP!I15,"") -> 1 | J42: =IFERROR(BP!J32/BP!J15,"") -> 1 | ... AF42: =IFERROR(BP!AF32/BP!AF15,"") -> 1

Sheet AH
A1: Análise Horizontal (AH) — trimestral
A2: Fórmula da disciplina: (Atual − Anterior) / ABS(Anterior). Cores: azul = alta, vermelho = queda; borda laranja = variação brusca (|AH| ≥ 50%).
A4: Conta / indicador | B4: Fonte ou fórmula | C4: 2019T1 | D4: 2019T2 | E4: 2019T3 | F4: 2019T4 | G4: 2020T1 | H4: 2020T2 | I4: 2020T3 | J4: 2020T4 | K4: 2021T1 | L4: 2021T2 | M4: 2021T3 | N4: 2021T4 | O4: 2022T1 | P4: 2022T2 | Q4: 2022T3 | R4: 2022T4 | S4: 2023T1 | T4: 2023T2 | U4: 2023T3 | V4: 2023T4 | W4: 2024T1 | X4: 2024T2 | Y4: 2024T3 | Z4: 2024T4 | AA4: 2025T1 | AB4: 2025T2 | AC4: 2025T3 | AD4: 2025T4 | AE4: 2026T1 | AF4: 2026T2
A6: AH homóloga — trimestre contra o mesmo trimestre do ano anterior (t vs t−4): elimina a sazonalidade
A7: Receita líquida | B7: DRE | C7: n.d. | D7: n.d. | E7: n.d. | F7: n.d. | G7: =IFERROR((DRE!G7-DRE!C7)/ABS(DRE!C7),"") -> 0.27575784 | H7: =IFERROR((DRE!H7-DRE!D7)/ABS(DRE!D7),"") -> 0.24886068 | I7: =IFERROR((DRE!I7-DRE!E7)/ABS(DRE!E7),"") -> 0.22702642 | J7: =IFERROR((DRE!J7-DRE!F7)/ABS(DRE!F7),"") -> 0.21527612 | K7: =IFERROR((DRE!K7-DRE!G7)/ABS(DRE!G7),"") -> 0.24196702 | L7: =IFERROR((DRE!L7-DRE!H7)/ABS(DRE!H7),"") -> 0.19411768 | M7: =IFERROR((DRE!M7-DRE!I7)/ABS(DRE!I7),"") -> 0.16281683 | N7: =IFERROR((DRE!N7-DRE!J7)/ABS(DRE!J7),"") -> 0.16026568 | ... AF7: =IFERROR((DRE!AF7-DRE!AB7)/ABS(DRE!AB7),"") -> 0.13365374
A8: Custo dos serviços | B8: DRE | C8: n.d. | D8: n.d. | E8: n.d. | F8: n.d. | G8: =IFERROR((DRE!G8-DRE!C8)/ABS(DRE!C8),"") -> 0.25398295 | H8: =IFERROR((DRE!H8-DRE!D8)/ABS(DRE!D8),"") -> 0.21228304 | I8: =IFERROR((DRE!I8-DRE!E8)/ABS(DRE!E8),"") -> 0.24849972 | J8: =IFERROR((DRE!J8-DRE!F8)/ABS(DRE!F8),"") -> 0.20171159 | K8: =IFERROR((DRE!K8-DRE!G8)/ABS(DRE!G8),"") -> 0.074675647 | L8: =IFERROR((DRE!L8-DRE!H8)/ABS(DRE!H8),"") -> 0.10272533 | M8: =IFERROR((DRE!M8-DRE!I8)/ABS(DRE!I8),"") -> 0.08760595 | N8: =IFERROR((DRE!N8-DRE!J8)/ABS(DRE!J8),"") -> 0.25795288 | ... AF8: =IFERROR((DRE!AF8-DRE!AB8)/ABS(DRE!AB8),"") -> 0.13363614
A9: Lucro bruto | B9: DRE | C9: n.d. | D9: n.d. | E9: n.d. | F9: n.d. | G9: =IFERROR((DRE!G9-DRE!C9)/ABS(DRE!C9),"") -> 0.31363239 | H9: =IFERROR((DRE!H9-DRE!D9)/ABS(DRE!D9),"") -> 0.3061969 | I9: =IFERROR((DRE!I9-DRE!E9)/ABS(DRE!E9),"") -> 0.19604227 | J9: =IFERROR((DRE!J9-DRE!F9)/ABS(DRE!F9),"") -> 0.23876705 | K9: =IFERROR((DRE!K9-DRE!G9)/ABS(DRE!G9),"") -> 0.51973533 | L9: =IFERROR((DRE!L9-DRE!H9)/ABS(DRE!H9),"") -> 0.32707693 | M9: =IFERROR((DRE!M9-DRE!I9)/ABS(DRE!I9),"") -> 0.27609948 | N9: =IFERROR((DRE!N9-DRE!J9)/ABS(DRE!J9),"") -> -0.0038474849 | ... AF9: =IFERROR((DRE!AF9-DRE!AB9)/ABS(DRE!AB9),"") -> 0.13367004
A10: Despesas operacionais | B10: DRE | C10: n.d. | D10: n.d. | E10: n.d. | F10: n.d. | G10: =IFERROR((DRE!G13-DRE!C13)/ABS(DRE!C13),"") -> 0.015478967 | H10: =IFERROR((DRE!H13-DRE!D13)/ABS(DRE!D13),"") -> -0.053168351 | I10: =IFERROR((DRE!I13-DRE!E13)/ABS(DRE!E13),"") -> 0.073945765 | J10: =IFERROR((DRE!J13-DRE!F13)/ABS(DRE!F13),"") -> -0.011574964 | K10: =IFERROR((DRE!K13-DRE!G13)/ABS(DRE!G13),"") -> 0.10347812 | L10: =IFERROR((DRE!L13-DRE!H13)/ABS(DRE!H13),"") -> 0.28734811 | M10: =IFERROR((DRE!M13-DRE!I13)/ABS(DRE!I13),"") -> 0.21436318 | N10: =IFERROR((DRE!N13-DRE!J13)/ABS(DRE!J13),"") -> 0.20519659 | ... AF10: =IFERROR((DRE!AF13-DRE!AB13)/ABS(DRE!AB13),"") -> 0.17744994
A11: EBIT | B11: DRE | C11: n.d. | D11: n.d. | E11: n.d. | F11: n.d. | G11: =IFERROR((DRE!G14-DRE!C14)/ABS(DRE!C14),"") -> 1.0873217 | H11: =IFERROR((DRE!H14-DRE!D14)/ABS(DRE!D14),"") -> 0.92226993 | I11: =IFERROR((DRE!I14-DRE!E14)/ABS(DRE!E14),"") -> 0.34136981 | J11: =IFERROR((DRE!J14-DRE!F14)/ABS(DRE!F14),"") -> 1.0811713 | K11: =IFERROR((DRE!K14-DRE!G14)/ABS(DRE!G14),"") -> 1.0452322 | L11: =IFERROR((DRE!L14-DRE!H14)/ABS(DRE!H14),"") -> 0.36062442 | M11: =IFERROR((DRE!M14-DRE!I14)/ABS(DRE!I14),"") -> 0.33493223 | N11: =IFERROR((DRE!N14-DRE!J14)/ABS(DRE!J14),"") -> -0.33793524 | ... AF11: =IFERROR((DRE!AF14-DRE!AB14)/ABS(DRE!AB14),"") -> 0.1107152
A12: EBITDA | B12: DRE | C12: n.d. | D12: n.d. | E12: n.d. | F12: n.d. | G12: =IFERROR((DRE!G30-DRE!C30)/ABS(DRE!C30),"") -> 1.044511 | H12: =IFERROR((DRE!H30-DRE!D30)/ABS(DRE!D30),"") -> 0.8917347 | I12: =IFERROR((DRE!I30-DRE!E30)/ABS(DRE!E30),"") -> 0.33418873 | J12: =IFERROR((DRE!J30-DRE!F30)/ABS(DRE!F30),"") -> 1.0278103 | K12: =IFERROR((DRE!K30-DRE!G30)/ABS(DRE!G30),"") -> 1.0223466 | L12: =IFERROR((DRE!L30-DRE!H30)/ABS(DRE!H30),"") -> 0.36218329 | M12: =IFERROR((DRE!M30-DRE!I30)/ABS(DRE!I30),"") -> 0.35881743 | N12: =IFERROR((DRE!N30-DRE!J30)/ABS(DRE!J30),"") -> -0.29449951 | ... AF12: =IFERROR((DRE!AF30-DRE!AB30)/ABS(DRE!AB30),"") -> 0.11373964
A13: Despesa de juros | B13: DRE | C13: n.d. | D13: n.d. | E13: n.d. | F13: n.d. | G13: =IFERROR((DRE!G15-DRE!C15)/ABS(DRE!C15),"") -> 0.35825543 | H13: =IFERROR((DRE!H15-DRE!D15)/ABS(DRE!D15),"") -> 0.24414436 | I13: =IFERROR((DRE!I15-DRE!E15)/ABS(DRE!E15),"") -> 0.22668368 | J13: =IFERROR((DRE!J15-DRE!F15)/ABS(DRE!F15),"") -> 0.10902638 | K13: =IFERROR((DRE!K15-DRE!G15)/ABS(DRE!G15),"") -> 0.056262664 | L13: =IFERROR((DRE!L15-DRE!H15)/ABS(DRE!H15),"") -> 0.011477603 | M13: =IFERROR((DRE!M15-DRE!I15)/ABS(DRE!I15),"") -> -0.033742814 | N13: =IFERROR((DRE!N15-DRE!J15)/ABS(DRE!J15),"") -> -0.039338493 | ... AF13: =IFERROR((DRE!AF15-DRE!AB15)/ABS(DRE!AB15),"") -> -0.038127775
A14: Lucro líquido | B14: DRE | C14: n.d. | D14: n.d. | E14: n.d. | F14: n.d. | G14: =IFERROR((DRE!G19-DRE!C19)/ABS(DRE!C19),"") -> 1.0609297 | H14: =IFERROR((DRE!H19-DRE!D19)/ABS(DRE!D19),"") -> 1.6609865 | I14: =IFERROR((DRE!I19-DRE!E19)/ABS(DRE!E19),"") -> 0.18749812 | J14: =IFERROR((DRE!J19-DRE!F19)/ABS(DRE!F19),"") -> -0.076348025 | K14: =IFERROR((DRE!K19-DRE!G19)/ABS(DRE!G19),"") -> 1.4069869 | L14: =IFERROR((DRE!L19-DRE!H19)/ABS(DRE!H19),"") -> 0.87867331 | M14: =IFERROR((DRE!M19-DRE!I19)/ABS(DRE!I19),"") -> 0.83432281 | N14: =IFERROR((DRE!N19-DRE!J19)/ABS(DRE!J19),"") -> 0.12039524 | ... AF14: =IFERROR((DRE!AF19-DRE!AB19)/ABS(DRE!AB19),"") -> 0.088308649
A15: Fluxo de caixa operacional | B15: DFC | C15: n.d. | D15: n.d. | E15: n.d. | F15: n.d. | G15: =IFERROR((DFC!G7-DFC!C7)/ABS(DFC!C7),"") -> 1.6843409 | H15: =IFERROR((DFC!H7-DFC!D7)/ABS(DFC!D7),"") -> 2.9146084 | I15: =IFERROR((DFC!I7-DFC!E7)/ABS(DFC!E7),"") -> 3.5184857 | J15: =IFERROR((DFC!J7-DFC!F7)/ABS(DFC!F7),"") -> 0.9058315 | K15: =IFERROR((DFC!K7-DFC!G7)/ABS(DFC!G7),"") -> 1.9904968 | L15: =IFERROR((DFC!L7-DFC!H7)/ABS(DFC!H7),"") -> -1.0612453 | M15: =IFERROR((DFC!M7-DFC!I7)/ABS(DFC!I7),"") -> -0.93481442 | N15: =IFERROR((DFC!N7-DFC!J7)/ABS(DFC!J7),"") -> -1.9292376 | ... AF15: =IFERROR((DFC!AF7-DFC!AB7)/ABS(DFC!AB7),"") -> -0.28038533
A16: Fluxo de caixa livre | B16: DFC | C16: n.d. | D16: n.d. | E16: n.d. | F16: n.d. | G16: =IFERROR((DFC!G9-DFC!C9)/ABS(DFC!C9),"") -> 1.3677973 | H16: =IFERROR((DFC!H9-DFC!D9)/ABS(DFC!D9),"") -> 2.5417048 | I16: =IFERROR((DFC!I9-DFC!E9)/ABS(DFC!E9),"") -> 3.1091081 | J16: =IFERROR((DFC!J9-DFC!F9)/ABS(DFC!F9),"") -> 0.81778313 | K16: =IFERROR((DFC!K9-DFC!G9)/ABS(DFC!G9),"") -> 3.3006665 | L16: =IFERROR((DFC!L9-DFC!H9)/ABS(DFC!H9),"") -> -1.1935197 | M16: =IFERROR((DFC!M9-DFC!I9)/ABS(DFC!I9),"") -> -1.073615 | N16: =IFERROR((DFC!N9-DFC!J9)/ABS(DFC!J9),"") -> -0.99020026 | ... AF16: =IFERROR((DFC!AF9-DFC!AB9)/ABS(DFC!AB9),"") -> -0.32734019
A17: Pagamentos de conteúdo | B17: DFC | C17: n.d. | D17: n.d. | E17: n.d. | F17: n.d. | G17: =IFERROR((DFC!G15-DFC!C15)/ABS(DFC!C15),"") -> 0.09891732 | H17: =IFERROR((DFC!H15-DFC!D15)/ABS(DFC!D15),"") -> -0.24490099 | I17: =IFERROR((DFC!I15-DFC!E15)/ABS(DFC!E15),"") -> -0.27256755 | J17: =IFERROR((DFC!J15-DFC!F15)/ABS(DFC!F15),"") -> -0.15845757 | K17: =IFERROR((DFC!K15-DFC!G15)/ABS(DFC!G15),"") -> -0.0029441986 | L17: =IFERROR((DFC!L15-DFC!H15)/ABS(DFC!H15),"") -> 0.63166296 | M17: =IFERROR((DFC!M15-DFC!I15)/ABS(DFC!I15),"") -> 0.7582658 | N17: =IFERROR((DFC!N15-DFC!J15)/ABS(DFC!J15),"") -> 0.7030296 | ... AF17: =IFERROR((DFC!AF15-DFC!AB15)/ABS(DFC!AB15),"") -> 0.28460981
A18: Caixa e equivalentes | B18: BP | C18: n.d. | D18: n.d. | E18: n.d. | F18: n.d. | G18: =IFERROR((BP!G7-BP!C7)/ABS(BP!C7),"") -> 0.53853854 | H18: =IFERROR((BP!H7-BP!D7)/ABS(BP!D7),"") -> 0.42943544 | I18: =IFERROR((BP!I7-BP!E7)/ABS(BP!E7),"") -> 0.89230145 | J18: =IFERROR((BP!J7-BP!F7)/ABS(BP!F7),"") -> 0.6350808 | K18: =IFERROR((BP!K7-BP!G7)/ABS(BP!G7),"") -> 0.63119065 | L18: =IFERROR((BP!L7-BP!H7)/ABS(BP!H7),"") -> 0.087272523 | M18: =IFERROR((BP!M7-BP!I7)/ABS(BP!I7),"") -> -0.10315415 | N18: =IFERROR((BP!N7-BP!J7)/ABS(BP!J7),"") -> -0.26539915 | ... AF18: =IFERROR((BP!AF7-BP!AB7)/ABS(BP!AB7),"") -> 0.11272855
A19: Ativo circulante | B19: BP | C19: n.d. | D19: n.d. | E19: n.d. | F19: n.d. | G19: =IFERROR((BP!G10-BP!C10)/ABS(BP!C10),"") -> 0.54663584 | H19: =IFERROR((BP!H10-BP!D10)/ABS(BP!D10),"") -> 0.45719078 | I19: =IFERROR((BP!I10-BP!E10)/ABS(BP!E10),"") -> 0.84439308 | J19: =IFERROR((BP!J10-BP!F10)/ABS(BP!F10),"") -> 0.57992614 | K19: =IFERROR((BP!K10-BP!G10)/ABS(BP!G10),"") -> 0.56759481 | L19: =IFERROR((BP!L10-BP!H10)/ABS(BP!H10),"") -> 0.12145261 | M19: =IFERROR((BP!M10-BP!I10)/ABS(BP!I10),"") -> -0.041794518 | N19: =IFERROR((BP!N10-BP!J10)/ABS(BP!J10),"") -> -0.1733075 | ... AF19: =IFERROR((BP!AF10-BP!AB10)/ABS(BP!AB10),"") -> 0.15510552
A20: Ativos de conteúdo | B20: BP | C20: n.d. | D20: n.d. | E20: n.d. | F20: n.d. | G20: =IFERROR((BP!G11-BP!C11)/ABS(BP!C11),"") -> 0.20959113 | H20: =IFERROR((BP!H11-BP!D11)/ABS(BP!D11),"") -> 0.14624146 | I20: =IFERROR((BP!I11-BP!E11)/ABS(BP!E11),"") -> 0.07887409 | J20: =IFERROR((BP!J11-BP!F11)/ABS(BP!F11),"") -> 0.035886494 | K20: =IFERROR((BP!K11-BP!G11)/ABS(BP!G11),"") -> 0.030755745 | L20: =IFERROR((BP!L11-BP!H11)/ABS(BP!H11),"") -> 0.084933932 | M20: =IFERROR((BP!M11-BP!I11)/ABS(BP!I11),"") -> 0.1558349 | N20: =IFERROR((BP!N11-BP!J11)/ABS(BP!J11),"") -> 0.21807437 | ... AF20: =IFERROR((BP!AF11-BP!AB11)/ABS(BP!AB11),"") -> 0.054478405
A21: Ativo total | B21: BP | C21: n.d. | D21: n.d. | E21: n.d. | F21: n.d. | G21: =IFERROR((BP!G15-BP!C15)/ABS(BP!C15),"") -> 0.28808494 | H21: =IFERROR((BP!H15-BP!D15)/ABS(BP!D15),"") -> 0.23213892 | I21: =IFERROR((BP!I15-BP!E15)/ABS(BP!E15),"") -> 0.24823553 | J21: =IFERROR((BP!J15-BP!F15)/ABS(BP!F15),"") -> 0.15613056 | K21: =IFERROR((BP!K15-BP!G15)/ABS(BP!G15),"") -> 0.14441292 | L21: =IFERROR((BP!L15-BP!H15)/ABS(BP!H15),"") -> 0.10210247 | M21: =IFERROR((BP!M15-BP!I15)/ABS(BP!I15),"") -> 0.10660391 | N21: =IFERROR((BP!N15-BP!J15)/ABS(BP!J15),"") -> 0.13503706 | ... AF21: =IFERROR((BP!AF15-BP!AB15)/ABS(BP!AB15),"") -> 0.10076857
A22: Passivo circulante | B22: BP | C22: n.d. | D22: n.d. | E22: n.d. | F22: n.d. | G22: =IFERROR((BP!G24-BP!C24)/ABS(BP!C24),"") -> 0.14522398 | H22: =IFERROR((BP!H24-BP!D24)/ABS(BP!D24),"") -> 0.099860917 | I22: =IFERROR((BP!I24-BP!E24)/ABS(BP!E24),"") -> 0.093952107 | J22: =IFERROR((BP!J24-BP!F24)/ABS(BP!F24),"") -> 0.13858389 | K22: =IFERROR((BP!K24-BP!G24)/ABS(BP!G24),"") -> 0.013757166 | L22: =IFERROR((BP!L24-BP!H24)/ABS(BP!H24),"") -> 0.027072998 | M22: =IFERROR((BP!M24-BP!I24)/ABS(BP!I24),"") -> 0.013785117 | N22: =IFERROR((BP!N24-BP!J24)/ABS(BP!J24),"") -> 0.087522395 | ... AF22: =IFERROR((BP!AF24-BP!AB24)/ABS(BP!AB24),"") -> 0.35701671
A23: Dívida de longo prazo | B23: BP | C23: n.d. | D23: n.d. | E23: n.d. | F23: n.d. | G23: =IFERROR((BP!G26-BP!C26)/ABS(BP!C26),"") -> 0.37512473 | H23: =IFERROR((BP!H26-BP!D26)/ABS(BP!D26),"") -> 0.21446705 | I23: =IFERROR((BP!I26-BP!E26)/ABS(BP!E26),"") -> 0.25121648 | J23: =IFERROR((BP!J26-BP!F26)/ABS(BP!F26),"") -> 0.071149468 | K23: =IFERROR((BP!K26-BP!G26)/ABS(BP!G26),"") -> 0.048682167 | L23: =IFERROR((BP!L26-BP!H26)/ABS(BP!H26),"") -> -0.02406728 | M23: =IFERROR((BP!M26-BP!I26)/ABS(BP!I26),"") -> -0.048491357 | N23: =IFERROR((BP!N26-BP!J26)/ABS(BP!J26),"") -> -0.070593731 | ... AF23: =IFERROR((BP!AF26-BP!AB26)/ABS(BP!AB26),"") -> -0.18180451
A24: Patrimônio líquido | B24: BP | C24: n.d. | D24: n.d. | E24: n.d. | F24: n.d. | G24: =IFERROR((BP!G31-BP!C31)/ABS(BP!C31),"") -> 0.47452367 | H24: =IFERROR((BP!H31-BP!D31)/ABS(BP!D31),"") -> 0.52889683 | I24: =IFERROR((BP!I31-BP!E31)/ABS(BP!E31),"") -> 0.50598491 | J24: =IFERROR((BP!J31-BP!F31)/ABS(BP!F31),"") -> 0.45937891 | K24: =IFERROR((BP!K31-BP!G31)/ABS(BP!G31),"") -> 0.53212386 | L24: =IFERROR((BP!L31-BP!H31)/ABS(BP!H31),"") -> 0.48518884 | M24: =IFERROR((BP!M31-BP!I31)/ABS(BP!I31),"") -> 0.48206119 | N24: =IFERROR((BP!N31-BP!J31)/ABS(BP!J31),"") -> 0.43234562 | ... AF24: =IFERROR((BP!AF31-BP!AB31)/ABS(BP!AB31),"") -> 0.2084071
A26: AH sequencial — trimestre contra o trimestre imediatamente anterior (t vs t−1)
A27: Receita líquida | B27: DRE | C27: n.d. | D27: =IFERROR((DRE!D7-DRE!C7)/ABS(DRE!C7),"") -> 0.088945966 | E27: =IFERROR((DRE!E7-DRE!D7)/ABS(DRE!D7),"") -> 0.065362872 | F27: =IFERROR((DRE!F7-DRE!E7)/ABS(DRE!E7),"") -> 0.042427651 | G27: =IFERROR((DRE!G7-DRE!F7)/ABS(DRE!F7),"") -> 0.054917352 | H27: =IFERROR((DRE!H7-DRE!G7)/ABS(DRE!G7),"") -> 0.065987412 | I27: =IFERROR((DRE!I7-DRE!H7)/ABS(DRE!H7),"") -> 0.046736765 | J27: =IFERROR((DRE!J7-DRE!I7)/ABS(DRE!I7),"") -> 0.032445118 | K27: =IFERROR((DRE!K7-DRE!J7)/ABS(DRE!J7),"") -> 0.078086316 | ... AF27: =IFERROR((DRE!AF7-DRE!AE7)/ABS(DRE!AE7),"") -> 0.0253214
A28: Custo dos serviços | B28: DRE | C28: n.d. | D28: =IFERROR((DRE!D8-DRE!C8)/ABS(DRE!C8),"") -> 0.047043246 | E28: =IFERROR((DRE!E8-DRE!D8)/ABS(DRE!D8),"") -> 0.030696117 | F28: =IFERROR((DRE!F8-DRE!E8)/ABS(DRE!E8),"") -> 0.11882299 | G28: =IFERROR((DRE!G8-DRE!F8)/ABS(DRE!F8),"") -> 0.038568123 | H28: =IFERROR((DRE!H8-DRE!G8)/ABS(DRE!G8),"") -> 0.012224904 | I28: =IFERROR((DRE!I8-DRE!H8)/ABS(DRE!H8),"") -> 0.06148793 | J28: =IFERROR((DRE!J8-DRE!I8)/ABS(DRE!I8),"") -> 0.076894557 | K28: =IFERROR((DRE!K8-DRE!J8)/ABS(DRE!J8),"") -> -0.071221514 | ... AF28: =IFERROR((DRE!AF8-DRE!AE8)/ABS(DRE!AE8),"") -> 0.02525832
A29: Lucro bruto | B29: DRE | C29: n.d. | D29: =IFERROR((DRE!D9-DRE!C9)/ABS(DRE!C9),"") -> 0.1618302 | E29: =IFERROR((DRE!E9-DRE!D9)/ABS(DRE!D9),"") -> 0.11970373 | F29: =IFERROR((DRE!F9-DRE!E9)/ABS(DRE!E9),"") -> -0.067804355 | G29: =IFERROR((DRE!G9-DRE!F9)/ABS(DRE!F9),"") -> 0.083230781 | H29: =IFERROR((DRE!H9-DRE!G9)/ABS(DRE!G9),"") -> 0.15525394 | I29: =IFERROR((DRE!I9-DRE!H9)/ABS(DRE!H9),"") -> 0.025276504 | J29: =IFERROR((DRE!J9-DRE!I9)/ABS(DRE!I9),"") -> -0.034504647 | K29: =IFERROR((DRE!K9-DRE!J9)/ABS(DRE!J9),"") -> 0.32892144 | ... AF29: =IFERROR((DRE!AF9-DRE!AE9)/ABS(DRE!AE9),"") -> 0.025379787
A30: Despesas operacionais | B30: DRE | C30: n.d. | D30: =IFERROR((DRE!D13-DRE!C13)/ABS(DRE!C13),"") -> 0.016575253 | E30: =IFERROR((DRE!E13-DRE!D13)/ABS(DRE!D13),"") -> -0.036574349 | F30: =IFERROR((DRE!F13-DRE!E13)/ABS(DRE!E13),"") -> 0.3223938 | G30: =IFERROR((DRE!G13-DRE!F13)/ABS(DRE!F13),"") -> -0.21593442 | H30: =IFERROR((DRE!H13-DRE!G13)/ABS(DRE!G13),"") -> -0.052146174 | I30: =IFERROR((DRE!I13-DRE!H13)/ABS(DRE!H13),"") -> 0.092767547 | J30: =IFERROR((DRE!J13-DRE!I13)/ABS(DRE!I13),"") -> 0.21708859 | K30: =IFERROR((DRE!K13-DRE!J13)/ABS(DRE!J13),"") -> -0.12466886 | ... AF30: =IFERROR((DRE!AF13-DRE!AE13)/ABS(DRE!AE13),"") -> -0.030841473
A31: EBIT | B31: DRE | C31: n.d. | D31: =IFERROR((DRE!D14-DRE!C14)/ABS(DRE!C14),"") -> 0.53875761 | E31: =IFERROR((DRE!E14-DRE!D14)/ABS(DRE!D14),"") -> 0.38761698 | F31: =IFERROR((DRE!F14-DRE!E14)/ABS(DRE!E14),"") -> -0.53224469 | G31: =IFERROR((DRE!G14-DRE!F14)/ABS(DRE!F14),"") -> 1.0899257 | H31: =IFERROR((DRE!H14-DRE!G14)/ABS(DRE!G14),"") -> 0.4170827 | I31: =IFERROR((DRE!I14-DRE!H14)/ABS(DRE!H14),"") -> -0.031713758 | J31: =IFERROR((DRE!J14-DRE!I14)/ABS(DRE!I14),"") -> -0.27426508 | K31: =IFERROR((DRE!K14-DRE!J14)/ABS(DRE!J14),"") -> 1.0538354 | ... AF31: =IFERROR((DRE!AF14-DRE!AE14)/ABS(DRE!AE14),"") -> 0.059543386
A32: EBITDA | B32: DRE | C32: n.d. | D32: =IFERROR((DRE!D30-DRE!C30)/ABS(DRE!C30),"") -> 0.51646655 | E32: =IFERROR((DRE!E30-DRE!D30)/ABS(DRE!D30),"") -> 0.37576495 | F32: =IFERROR((DRE!F30-DRE!E30)/ABS(DRE!E30),"") -> -0.51702331 | G32: =IFERROR((DRE!G30-DRE!F30)/ABS(DRE!F30),"") -> 1.0290194 | H32: =IFERROR((DRE!H30-DRE!G30)/ABS(DRE!G30),"") -> 0.40314844 | I32: =IFERROR((DRE!I30-DRE!H30)/ABS(DRE!H30),"") -> -0.029710622 | J32: =IFERROR((DRE!J30-DRE!I30)/ABS(DRE!I30),"") -> -0.26593209 | K32: =IFERROR((DRE!K30-DRE!J30)/ABS(DRE!J30),"") -> 1.0235524 | ... AF32: =IFERROR((DRE!AF30-DRE!AE30)/ABS(DRE!AE30),"") -> 0.058578173
A33: Despesa de juros | B33: DRE | C33: n.d. | D33: =IFERROR((DRE!D15-DRE!C15)/ABS(DRE!C15),"") -> 0.12177468 | E33: =IFERROR((DRE!E15-DRE!D15)/ABS(DRE!D15),"") -> 0.056744259 | F33: =IFERROR((DRE!F15-DRE!E15)/ABS(DRE!E15),"") -> 0.10669115 | G33: =IFERROR((DRE!G15-DRE!F15)/ABS(DRE!F15),"") -> 0.035331635 | H33: =IFERROR((DRE!H15-DRE!G15)/ABS(DRE!G15),"") -> 0.027531059 | I33: =IFERROR((DRE!I15-DRE!H15)/ABS(DRE!H15),"") -> 0.041913603 | J33: =IFERROR((DRE!J15-DRE!I15)/ABS(DRE!I15),"") -> 0.00054292949 | K33: =IFERROR((DRE!K15-DRE!J15)/ABS(DRE!J15),"") -> -0.013925938 | ... AF33: =IFERROR((DRE!AF15-DRE!AE15)/ABS(DRE!AE15),"") -> -0.32964358
A34: Lucro líquido | B34: DRE | C34: n.d. | D34: =IFERROR((DRE!D19-DRE!C19)/ABS(DRE!C19),"") -> -0.21334566 | E34: =IFERROR((DRE!E19-DRE!D19)/ABS(DRE!D19),"") -> 1.4579494 | F34: =IFERROR((DRE!F19-DRE!E19)/ABS(DRE!E19),"") -> -0.11766209 | G34: =IFERROR((DRE!G19-DRE!F19)/ABS(DRE!F19),"") -> 0.20801233 | H34: =IFERROR((DRE!H19-DRE!G19)/ABS(DRE!G19),"") -> 0.015695273 | I34: =IFERROR((DRE!I19-DRE!H19)/ABS(DRE!H19),"") -> 0.096890291 | J34: =IFERROR((DRE!J19-DRE!I19)/ABS(DRE!I19),"") -> -0.31370573 | K34: =IFERROR((DRE!K19-DRE!J19)/ABS(DRE!J19),"") -> 2.1480146 | ... AF34: =IFERROR((DRE!AF19-DRE!AE19)/ABS(DRE!AE19),"") -> -0.35613315
A35: Fluxo de caixa operacional | B35: DFC | C35: n.d. | D35: =IFERROR((DFC!D7-DFC!C7)/ABS(DFC!C7),"") -> -0.43168887 | E35: =IFERROR((DFC!E7-DFC!D7)/ABS(DFC!D7),"") -> 0.077167248 | F35: =IFERROR((DFC!F7-DFC!E7)/ABS(DFC!E7),"") -> -1.9134964 | G35: =IFERROR((DFC!G7-DFC!F7)/ABS(DFC!F7),"") -> 1.1777814 | H35: =IFERROR((DFC!H7-DFC!G7)/ABS(DFC!G7),"") -> 3.0054942 | I35: =IFERROR((DFC!I7-DFC!H7)/ABS(DFC!H7),"") -> 0.21389889 | J35: =IFERROR((DFC!J7-DFC!I7)/ABS(DFC!I7),"") -> -1.1089383 | K35: =IFERROR((DFC!K7-DFC!J7)/ABS(DFC!J7),"") -> 6.6457813 | ... AF35: =IFERROR((DFC!AF7-DFC!AE7)/ABS(DFC!AE7),"") -> -0.67036967
A36: Fluxo de caixa livre | B36: DFC | C36: n.d. | D36: =IFERROR((DFC!D9-DFC!C9)/ABS(DFC!C9),"") -> -0.32522604 | E36: =IFERROR((DFC!E9-DFC!D9)/ABS(DFC!D9),"") -> 0.062075503 | F36: =IFERROR((DFC!F9-DFC!E9)/ABS(DFC!E9),"") -> -1.8690085 | G36: =IFERROR((DFC!G9-DFC!F9)/ABS(DFC!F9),"") -> 1.103138 | H36: =IFERROR((DFC!H9-DFC!G9)/ABS(DFC!G9),"") -> 4.5549825 | I36: =IFERROR((DFC!I9-DFC!H9)/ABS(DFC!H9),"") -> 0.28311475 | J36: =IFERROR((DFC!J9-DFC!I9)/ABS(DFC!I9),"") -> -1.2478686 | K36: =IFERROR((DFC!K9-DFC!J9)/ABS(DFC!J9),"") -> 3.4342547 | ... AF36: =IFERROR((DFC!AF9-DFC!AE9)/ABS(DFC!AE9),"") -> -0.70059962
A37: Pagamentos de conteúdo | B37: DFC | C37: n.d. | D37: =IFERROR((DFC!D15-DFC!C15)/ABS(DFC!C15),"") -> 0.10920105 | E37: =IFERROR((DFC!E15-DFC!D15)/ABS(DFC!D15),"") -> 0.097196688 | F37: =IFERROR((DFC!F15-DFC!E15)/ABS(DFC!E15),"") -> 0.081476483 | G37: =IFERROR((DFC!G15-DFC!F15)/ABS(DFC!F15),"") -> -0.16506401 | H37: =IFERROR((DFC!H15-DFC!G15)/ABS(DFC!G15),"") -> -0.23783473 | I37: =IFERROR((DFC!I15-DFC!H15)/ABS(DFC!H15),"") -> 0.056995789 | J37: =IFERROR((DFC!J15-DFC!I15)/ABS(DFC!I15),"") -> 0.2511242 | K37: =IFERROR((DFC!K15-DFC!J15)/ABS(DFC!J15),"") -> -0.010771484 | ... AF37: =IFERROR((DFC!AF15-DFC!AE15)/ABS(DFC!AE15),"") -> 0.016630365
A38: Caixa e equivalentes | B38: BP | C38: n.d. | D38: =IFERROR((BP!D7-BP!C7)/ABS(BP!C7),"") -> 0.4944488 | E38: =IFERROR((BP!E7-BP!D7)/ABS(BP!D7),"") -> -0.11374918 | F38: =IFERROR((BP!F7-BP!E7)/ABS(BP!E7),"") -> 0.13154828 | G38: =IFERROR((BP!G7-BP!F7)/ABS(BP!F7),"") -> 0.026591347 | H38: =IFERROR((BP!H7-BP!G7)/ABS(BP!G7),"") -> 0.38847226 | I38: =IFERROR((BP!I7-BP!H7)/ABS(BP!H7),"") -> 0.17322802 | J38: =IFERROR((BP!J7-BP!I7)/ABS(BP!I7),"") -> -0.022263143 | K38: =IFERROR((BP!K7-BP!J7)/ABS(BP!J7),"") -> 0.024148899 | ... AF38: =IFERROR((BP!AF7-BP!AE7)/ABS(BP!AE7),"") -> -0.25779762
A39: Ativo circulante | B39: BP | C39: n.d. | D39: =IFERROR((BP!D10-BP!C10)/ABS(BP!C10),"") -> 0.40975968 | E39: =IFERROR((BP!E10-BP!D10)/ABS(BP!D10),"") -> -0.093480402 | F39: =IFERROR((BP!F10-BP!E10)/ABS(BP!E10),"") -> 0.1596818 | G39: =IFERROR((BP!G10-BP!F10)/ABS(BP!F10),"") -> 0.04358288 | H39: =IFERROR((BP!H10-BP!G10)/ABS(BP!G10),"") -> 0.32823044 | I39: =IFERROR((BP!I10-BP!H10)/ABS(BP!H10),"") -> 0.14739847 | J39: =IFERROR((BP!J10-BP!I10)/ABS(BP!I10),"") -> -0.0066046031 | K39: =IFERROR((BP!K10-BP!J10)/ABS(BP!J10),"") -> 0.035437706 | ... AF39: =IFERROR((BP!AF10-BP!AE10)/ABS(BP!AE10),"") -> -0.18848822
A40: Ativos de conteúdo | B40: BP | C40: n.d. | D40: =IFERROR((BP!D11-BP!C11)/ABS(BP!C11),"") -> 0.050599161 | E40: =IFERROR((BP!E11-BP!D11)/ABS(BP!D11),"") -> 0.058747347 | F40: =IFERROR((BP!F11-BP!E11)/ABS(BP!E11),"") -> 0.054640556 | G40: =IFERROR((BP!G11-BP!F11)/ABS(BP!F11),"") -> 0.031109385 | H40: =IFERROR((BP!H11-BP!G11)/ABS(BP!G11),"") -> -0.004423655 | I40: =IFERROR((BP!I11-BP!H11)/ABS(BP!H11),"") -> -0.0034777815 | J40: =IFERROR((BP!J11-BP!I11)/ABS(BP!I11),"") -> 0.012618543 | K40: =IFERROR((BP!K11-BP!J11)/ABS(BP!J11),"") -> 0.026002297 | ... AF40: =IFERROR((BP!AF11-BP!AE11)/ABS(BP!AE11),"") -> 0.013820527
A41: Ativo total | B41: BP | C41: n.d. | D41: =IFERROR((BP!D15-BP!C15)/ABS(BP!C15),"") -> 0.10848109 | E41: =IFERROR((BP!E15-BP!D15)/ABS(BP!D15),"") -> 0.025533239 | F41: =IFERROR((BP!F15-BP!E15)/ABS(BP!E15),"") -> 0.098055373 | G41: =IFERROR((BP!G15-BP!F15)/ABS(BP!F15),"") -> 0.031910972 | H41: =IFERROR((BP!H15-BP!G15)/ABS(BP!G15),"") -> 0.060335894 | I41: =IFERROR((BP!I15-BP!H15)/ABS(BP!H15),"") -> 0.038930762 | J41: =IFERROR((BP!J15-BP!I15)/ABS(BP!I15),"") -> 0.017031918 | K41: =IFERROR((BP!K15-BP!J15)/ABS(BP!J15),"") -> 0.021452324 | ... AF41: =IFERROR((BP!AF15-BP!AE15)/ABS(BP!AE15),"") -> -0.042045965
A42: Passivo circulante | B42: BP | C42: n.d. | D42: =IFERROR((BP!D24-BP!C24)/ABS(BP!C24),"") -> 0.01110807 | E42: =IFERROR((BP!E24-BP!D24)/ABS(BP!D24),"") -> 0.04671427 | F42: =IFERROR((BP!F24-BP!E24)/ABS(BP!E24),"") -> -0.055416029 | G42: =IFERROR((BP!G24-BP!F24)/ABS(BP!F24),"") -> 0.14557661 | H42: =IFERROR((BP!H24-BP!G24)/ABS(BP!G24),"") -> -0.028942572 | I42: =IFERROR((BP!I24-BP!H24)/ABS(BP!H24),"") -> 0.041090981 | J42: =IFERROR((BP!J24-BP!I24)/ABS(BP!I24),"") -> -0.01687827 | K42: =IFERROR((BP!K24-BP!J24)/ABS(BP!J24),"") -> 0.019983256 | ... AF42: =IFERROR((BP!AF24-BP!AE24)/ABS(BP!AE24),"") -> 0.00027366596
A43: Dívida de longo prazo | B43: BP | C43: n.d. | D43: =IFERROR((BP!D26-BP!C26)/ABS(BP!C26),"") -> 0.22212245 | E43: =IFERROR((BP!E26-BP!D26)/ABS(BP!D26),"") -> -0.013339686 | F43: =IFERROR((BP!F26-BP!E26)/ABS(BP!E26),"") -> 0.18775149 | G43: =IFERROR((BP!G26-BP!F26)/ABS(BP!F26),"") -> -0.039860966 | H43: =IFERROR((BP!H26-BP!G26)/ABS(BP!G26),"") -> 0.079340233 | I43: =IFERROR((BP!I26-BP!H26)/ABS(BP!H26),"") -> 0.01651638 | J43: =IFERROR((BP!J26-BP!I26)/ABS(BP!I26),"") -> 0.016817948 | K43: =IFERROR((BP!K26-BP!J26)/ABS(BP!J26),"") -> -0.059999829 | ... AF43: =IFERROR((BP!AF26-BP!AE26)/ABS(BP!AE26),"") -> -0.11494237
A44: Patrimônio líquido | B44: BP | C44: n.d. | D44: =IFERROR((BP!D31-BP!C31)/ABS(BP!C31),"") -> 0.070574418 | E44: =IFERROR((BP!E31-BP!D31)/ABS(BP!D31),"") -> 0.12381477 | F44: =IFERROR((BP!F31-BP!E31)/ABS(BP!E31),"") -> 0.10502827 | G44: =IFERROR((BP!G31-BP!F31)/ABS(BP!F31),"") -> 0.10908993 | H44: =IFERROR((BP!H31-BP!G31)/ABS(BP!G31),"") -> 0.11005193 | I44: =IFERROR((BP!I31-BP!H31)/ABS(BP!H31),"") -> 0.10697337 | J44: =IFERROR((BP!J31-BP!I31)/ABS(BP!I31),"") -> 0.070830748 | K44: =IFERROR((BP!K31-BP!J31)/ABS(BP!J31),"") -> 0.1643742 | ... AF44: =IFERROR((BP!AF31-BP!AE31)/ABS(BP!AE31),"") -> -0.031302914
A46: AH com base fixa — índice 2019T4 = 100 (evolução acumulada)
A47: Receita líquida | B47: DRE | C47: n.d. | D47: n.d. | E47: n.d. | F47: =IFERROR(DRE!F7/DRE!$F$7*100,"") -> 100 | G47: =IFERROR(DRE!G7/DRE!$F$7*100,"") -> 105.49174 | H47: =IFERROR(DRE!H7/DRE!$F$7*100,"") -> 112.45286 | I47: =IFERROR(DRE!I7/DRE!$F$7*100,"") -> 117.70854 | J47: =IFERROR(DRE!J7/DRE!$F$7*100,"") -> 121.52761 | K47: =IFERROR(DRE!K7/DRE!$F$7*100,"") -> 131.01726 | L47: =IFERROR(DRE!L7/DRE!$F$7*100,"") -> 134.28195 | M47: =IFERROR(DRE!M7/DRE!$F$7*100,"") -> 136.87348 | ... AF47: =IFERROR(DRE!AF7/DRE!$F$7*100,"") -> 229.72272
A48: Custo dos serviços | B48: DRE | C48: n.d. | D48: n.d. | E48: n.d. | F48: =IFERROR(DRE!F8/DRE!$F$8*100,"") -> 100 | G48: =IFERROR(DRE!G8/DRE!$F$8*100,"") -> 103.85681 | H48: =IFERROR(DRE!H8/DRE!$F$8*100,"") -> 105.12645 | I48: =IFERROR(DRE!I8/DRE!$F$8*100,"") -> 111.59046 | J48: =IFERROR(DRE!J8/DRE!$F$8*100,"") -> 120.17116 | K48: =IFERROR(DRE!K8/DRE!$F$8*100,"") -> 111.61239 | L48: =IFERROR(DRE!L8/DRE!$F$8*100,"") -> 115.9256 | M48: =IFERROR(DRE!M8/DRE!$F$8*100,"") -> 121.36645 | ... AF48: =IFERROR(DRE!AF8/DRE!$F$8*100,"") -> 174.17556
A49: Lucro bruto | B49: DRE | C49: n.d. | D49: n.d. | E49: n.d. | F49: =IFERROR(DRE!F9/DRE!$F$9*100,"") -> 100 | G49: =IFERROR(DRE!G9/DRE!$F$9*100,"") -> 108.32308 | H49: =IFERROR(DRE!H9/DRE!$F$9*100,"") -> 125.14066 | I49: =IFERROR(DRE!I9/DRE!$F$9*100,"") -> 128.30378 | J49: =IFERROR(DRE!J9/DRE!$F$9*100,"") -> 123.8767 | K49: =IFERROR(DRE!K9/DRE!$F$9*100,"") -> 164.62241 | L49: =IFERROR(DRE!L9/DRE!$F$9*100,"") -> 166.07129 | M49: =IFERROR(DRE!M9/DRE!$F$9*100,"") -> 163.72839 | ... AF49: =IFERROR(DRE!AF9/DRE!$F$9*100,"") -> 325.91871
A50: Despesas operacionais | B50: DRE | C50: n.d. | D50: n.d. | E50: n.d. | F50: =IFERROR(DRE!F13/DRE!$F$13*100,"") -> 100 | G50: =IFERROR(DRE!G13/DRE!$F$13*100,"") -> 78.406558 | H50: =IFERROR(DRE!H13/DRE!$F$13*100,"") -> 74.317956 | I50: =IFERROR(DRE!I13/DRE!$F$13*100,"") -> 81.21225 | J50: =IFERROR(DRE!J13/DRE!$F$13*100,"") -> 98.842504 | K50: =IFERROR(DRE!K13/DRE!$F$13*100,"") -> 86.519921 | L50: =IFERROR(DRE!L13/DRE!$F$13*100,"") -> 95.67308 | M50: =IFERROR(DRE!M13/DRE!$F$13*100,"") -> 98.621167 | ... AF50: =IFERROR(DRE!AF13/DRE!$F$13*100,"") -> 151.03795
A51: EBIT | B51: DRE | C51: n.d. | D51: n.d. | E51: n.d. | F51: =IFERROR(DRE!F14/DRE!$F$14*100,"") -> 100 | G51: =IFERROR(DRE!G14/DRE!$F$14*100,"") -> 208.99257 | H51: =IFERROR(DRE!H14/DRE!$F$14*100,"") -> 296.15975 | I51: =IFERROR(DRE!I14/DRE!$F$14*100,"") -> 286.76741 | J51: =IFERROR(DRE!J14/DRE!$F$14*100,"") -> 208.11713 | K51: =IFERROR(DRE!K14/DRE!$F$14*100,"") -> 427.43832 | L51: =IFERROR(DRE!L14/DRE!$F$14*100,"") -> 402.96219 | M51: =IFERROR(DRE!M14/DRE!$F$14*100,"") -> 382.81506 | ... AF51: =IFERROR(DRE!AF14/DRE!$F$14*100,"") -> 914.39482
A52: EBITDA | B52: DRE | C52: n.d. | D52: n.d. | E52: n.d. | F52: =IFERROR(DRE!F30/DRE!$F$30*100,"") -> 100 | G52: =IFERROR(DRE!G30/DRE!$F$30*100,"") -> 202.90194 | H52: =IFERROR(DRE!H30/DRE!$F$30*100,"") -> 284.70154 | I52: =IFERROR(DRE!I30/DRE!$F$30*100,"") -> 276.24288 | J52: =IFERROR(DRE!J30/DRE!$F$30*100,"") -> 202.78103 | K52: =IFERROR(DRE!K30/DRE!$F$30*100,"") -> 410.33804 | L52: =IFERROR(DRE!L30/DRE!$F$30*100,"") -> 387.81568 | M52: =IFERROR(DRE!M30/DRE!$F$30*100,"") -> 375.36364 | ... AF52: =IFERROR(DRE!AF30/DRE!$F$30*100,"") -> 882.76273
A53: Lucro líquido | B53: DRE | C53: n.d. | D53: n.d. | E53: n.d. | F53: =IFERROR(DRE!F19/DRE!$F$19*100,"") -> 100 | G53: =IFERROR(DRE!G19/DRE!$F$19*100,"") -> 120.80123 | H53: =IFERROR(DRE!H19/DRE!$F$19*100,"") -> 122.69724 | I53: =IFERROR(DRE!I19/DRE!$F$19*100,"") -> 134.58541 | J53: =IFERROR(DRE!J19/DRE!$F$19*100,"") -> 92.365198 | K53: =IFERROR(DRE!K19/DRE!$F$19*100,"") -> 290.76699 | L53: =IFERROR(DRE!L19/DRE!$F$19*100,"") -> 230.50803 | M53: =IFERROR(DRE!M19/DRE!$F$19*100,"") -> 246.87309 | ... AF53: =IFERROR(DRE!AF19/DRE!$F$19*100,"") -> 579.48686
A54: Ativo total | B54: BP | C54: n.d. | D54: n.d. | E54: n.d. | F54: =IFERROR(BP!F15/BP!$F$15*100,"") -> 100 | G54: =IFERROR(BP!G15/BP!$F$15*100,"") -> 103.1911 | H54: =IFERROR(BP!H15/BP!$F$15*100,"") -> 109.41722 | I54: =IFERROR(BP!I15/BP!$F$15*100,"") -> 113.67692 | J54: =IFERROR(BP!J15/BP!$F$15*100,"") -> 115.61306 | K54: =IFERROR(BP!K15/BP!$F$15*100,"") -> 118.09322 | L54: =IFERROR(BP!L15/BP!$F$15*100,"") -> 120.58899 | M54: =IFERROR(BP!M15/BP!$F$15*100,"") -> 125.79532 | ... AF54: =IFERROR(BP!AF15/BP!$F$15*100,"") -> 172.03596
A55: Patrimônio líquido | B55: BP | C55: n.d. | D55: n.d. | E55: n.d. | F55: =IFERROR(BP!F31/BP!$F$31*100,"") -> 100 | G55: =IFERROR(BP!G31/BP!$F$31*100,"") -> 110.90899 | H55: =IFERROR(BP!H31/BP!$F$31*100,"") -> 123.11474 | I55: =IFERROR(BP!I31/BP!$F$31*100,"") -> 136.28474 | J55: =IFERROR(BP!J31/BP!$F$31*100,"") -> 145.93789 | K55: =IFERROR(BP!K31/BP!$F$31*100,"") -> 169.92632 | L55: =IFERROR(BP!L31/BP!$F$31*100,"") -> 182.84864 | M55: =IFERROR(BP!M31/BP!$F$31*100,"") -> 201.98233 | ... AF55: =IFERROR(BP!AF31/BP!$F$31*100,"") -> 397.67116

Sheet AH_Anual
A1: Análise Horizontal — anual (e 1º semestre)
A2: Fluxos: soma dos 4 trimestres (1S = T1+T2) · Saldos: posição no fim do período · AH = (Atual − Anterior)/ABS(Anterior)
A4: Conta / indicador | B4: Fonte ou fórmula | C4: 2019 | D4: 2020 | E4: 2021 | F4: 2022 | G4: 2023 | H4: 2024 | I4: 2025 | J4: 1S2025 | K4: 1S2026
A6: Valores (US$ milhões)
A7: Receita líquida | B7: Σ DRE | C7: =SUM(DRE!C7:F7) -> 20156.447 | D7: =SUM(DRE!G7:J7) -> 24996.056 | E7: =SUM(DRE!K7:N7) -> 29697.844 | F7: =SUM(DRE!O7:R7) -> 31615.55 | G7: =SUM(DRE!S7:V7) -> 33723.297 | H7: =SUM(DRE!W7:Z7) -> 39000.966 | I7: =SUM(DRE!AA7:AD7) -> 45183.036 | J7: =SUM(DRE!AA7:AB7) -> 21621.967 | K7: =SUM(DRE!AE7:AF7) -> 24809.695
A8: Custo dos serviços | B8: Σ DRE | C8: =SUM(DRE!C8:F8) -> 12440.213 | D8: =SUM(DRE!G8:J8) -> 15276.319 | E8: =SUM(DRE!K8:N8) -> 17332.683 | F8: =SUM(DRE!O8:R8) -> 19168.285 | G8: =SUM(DRE!S8:V8) -> 19715.368 | H8: =SUM(DRE!W8:Z8) -> 21038.464 | I8: =SUM(DRE!AA8:AD8) -> 23275.329 | J8: =SUM(DRE!AA8:AB8) -> 10588.458 | K8: =SUM(DRE!AE8:AF8) -> 11925.203
A9: Lucro bruto | B9: Σ DRE | C9: =SUM(DRE!C9:F9) -> 7716.234 | D9: =SUM(DRE!G9:J9) -> 9719.737 | E9: =SUM(DRE!K9:N9) -> 12365.161 | F9: =SUM(DRE!O9:R9) -> 12447.265 | G9: =SUM(DRE!S9:V9) -> 14007.929 | H9: =SUM(DRE!W9:Z9) -> 17962.502 | I9: =SUM(DRE!AA9:AD9) -> 21907.707 | J9: =SUM(DRE!AA9:AB9) -> 11033.509 | K9: =SUM(DRE!AE9:AF9) -> 12884.492
A10: Despesas operacionais | B10: Σ DRE | C10: =SUM(DRE!C13:F13) -> 5111.98 | D10: =SUM(DRE!G13:J13) -> 5134.448 | E10: =SUM(DRE!K13:N13) -> 6170.652 | F10: =SUM(DRE!O13:R13) -> 6814.434 | G10: =SUM(DRE!S13:V13) -> 7053.926 | H10: =SUM(DRE!W13:Z13) -> 7544.888 | I10: =SUM(DRE!AA13:AD13) -> 8581.104 | J10: =SUM(DRE!AA13:AB13) -> 3911.816 | K10: =SUM(DRE!AE13:AF13) -> 4734.885
A11: EBIT | B11: Σ DRE | C11: =SUM(DRE!C14:F14) -> 2604.254 | D11: =SUM(DRE!G14:J14) -> 4585.289 | E11: =SUM(DRE!K14:N14) -> 6194.509 | F11: =SUM(DRE!O14:R14) -> 5632.831 | G11: =SUM(DRE!S14:V14) -> 6954.003 | H11: =SUM(DRE!W14:Z14) -> 10417.614 | I11: =SUM(DRE!AA14:AD14) -> 13326.603 | J11: =SUM(DRE!AA14:AB14) -> 7121.693 | K11: =SUM(DRE!AE14:AF14) -> 8149.607
A12: EBITDA | B12: Σ DRE | C12: =SUM(DRE!C30:F30) -> 2707.833 | D12: =SUM(DRE!G30:J30) -> 4700.999 | E12: =SUM(DRE!K30:N30) -> 6402.921 | F12: =SUM(DRE!O30:R30) -> 5969.513 | G12: =SUM(DRE!S30:V30) -> 7310.95 | H12: =SUM(DRE!W30:Z30) -> 10746.528 | I12: =SUM(DRE!AA30:AD30) -> 13659.992 | J12: =SUM(DRE!AA30:AB30) -> 7281.773 | K12: =SUM(DRE!AE30:AF30) -> 8348.712
A13: Despesa de juros | B13: Σ DRE | C13: =SUM(DRE!C15:F15) -> 626.023 | D13: =SUM(DRE!G15:J15) -> 767.499 | E13: =SUM(DRE!K15:N15) -> 765.62 | F13: =SUM(DRE!O15:R15) -> 706.212 | G13: =SUM(DRE!S15:V15) -> 699.826 | H13: =SUM(DRE!W15:Z15) -> 718.733 | I13: =SUM(DRE!AA15:AD15) -> 776.51 | J13: =SUM(DRE!AA15:AB15) -> 366.821 | K13: =SUM(DRE!AE15:AF15) -> 437.762
A14: Outras receitas/despesas financeiras | B14: Σ DRE | C14: =SUM(DRE!C16:F16) -> 84 | D14: =SUM(DRE!G16:J16) -> -618.441 | E14: =SUM(DRE!K16:N16) -> 411.214 | F14: =SUM(DRE!O16:R16) -> 337.31 | G14: =SUM(DRE!S16:V16) -> -48.772 | H14: =SUM(DRE!W16:Z16) -> 266.776 | I14: =SUM(DRE!AA16:AD16) -> 172.459 | J14: =SUM(DRE!AA16:AB16) -> 90.529 | K14: =SUM(DRE!AE16:AF16) -> 2903.827
A15: Lucro líquido | B15: Σ DRE | C15: =SUM(DRE!C19:F19) -> 1866.916 | D15: =SUM(DRE!G19:J19) -> 2761.395 | E15: =SUM(DRE!K19:N19) -> 5116.228 | F15: =SUM(DRE!O19:R19) -> 4491.924 | G15: =SUM(DRE!S19:V19) -> 5407.99 | H15: =SUM(DRE!W19:Z19) -> 8711.631 | I15: =SUM(DRE!AA19:AD19) -> 10981.201 | J15: =SUM(DRE!AA19:AB19) -> 6015.764 | K15: =SUM(DRE!AE19:AF19) -> 8684.205
A16: FCO | B16: Σ DFC | C16: =SUM(DFC!C7:F7) -> -2887.322 | D16: =SUM(DFC!G7:J7) -> 2427.077 | E16: =SUM(DFC!K7:N7) -> 392.61 | F16: =SUM(DFC!O7:R7) -> 2026.257 | G16: =SUM(DFC!S7:V7) -> 7274.301 | H16: =SUM(DFC!W7:Z7) -> 7361.364 | I16: =SUM(DFC!AA7:AD7) -> 10149.273 | J16: =SUM(DFC!AA7:AB7) -> 5212.457 | K16: =SUM(DFC!AE7:AF7) -> 7034.017
A17: FCL (FCO − Capex) | B17: Σ DFC | C17: =SUM(DFC!C9:F9) -> -3140.357 | D17: =SUM(DFC!G9:J9) -> 1929.154 | E17: =SUM(DFC!K9:N9) -> -131.975 | F17: =SUM(DFC!O9:R9) -> 1618.528 | G17: =SUM(DFC!S9:V9) -> 6925.749 | H17: =SUM(DFC!W9:Z9) -> 6921.826 | I17: =SUM(DFC!AA9:AD9) -> 9461.053 | J17: =SUM(DFC!AA9:AB9) -> 4928.291 | K17: =SUM(DFC!AE9:AF9) -> 6619.243
A18: Pagamentos de conteúdo | B18: Σ DFC | C18: =SUM(DFC!C15:F15) -> 13916.683 | D18: =SUM(DFC!G15:J15) -> 11779.284 | E18: =SUM(DFC!K15:N15) -> 17702.202 | F18: =SUM(DFC!O15:R15) -> 16839.038 | G18: =SUM(DFC!S15:V15) -> 12554.703 | H18: =SUM(DFC!W15:Z15) -> 16223.617 | I18: =SUM(DFC!AA15:AD15) -> 17096.617 | J18: =SUM(DFC!AA15:AB15) -> 7385.47 | K18: =SUM(DFC!AE15:AF15) -> 9774.44
A19: Amortização de conteúdo | B19: Σ DRE | C19: =SUM(DRE!C28:F28) -> 9216.247 | D19: =SUM(DRE!G28:J28) -> 10806.912 | E19: =SUM(DRE!K28:N28) -> 12230.367 | F19: =SUM(DRE!O28:R28) -> 14026.132 | G19: =SUM(DRE!S28:V28) -> 14197.437 | H19: =SUM(DRE!W28:Z28) -> 15301.517 | I19: =SUM(DRE!AA28:AD28) -> 16422.166 | J19: =SUM(DRE!AA28:AB28) -> 7655.186 | K19: =SUM(DRE!AE28:AF28) -> 8529.209
A20: Recompra de ações | B20: Σ DFC | C20: =SUM(DFC!C12:F12) -> 0 | D20: =SUM(DFC!G12:J12) -> 0 | E20: =SUM(DFC!K12:N12) -> 600.022 | F20: =SUM(DFC!O12:R12) -> 0 | G20: =SUM(DFC!S12:V12) -> 6045.347 | H20: =SUM(DFC!W12:Z12) -> 6263.746 | I20: =SUM(DFC!AA12:AD12) -> 9127.167 | J20: =SUM(DFC!AA12:AB12) -> 5190.723 | K20: =SUM(DFC!AE12:AF12) -> 5984.991
A21: Caixa (fim do período) | B21: BP fim do período | C21: =BP!F7 -> 5018.437 | D21: =BP!J7 -> 8205.55 | E21: =BP!N7 -> 6027.804 | F21: =BP!R7 -> 5147.176 | G21: =BP!V7 -> 7116.913 | H21: =BP!Z7 -> 7804.733 | I21: =BP!AD7 -> 9033.681 | J21: =BP!AB7 -> 8177.405 | K21: =BP!AF7 -> 9099.232
A22: Ativo circulante | B22: BP fim do período | C22: =BP!F10 -> 6178.504 | D22: =BP!J10 -> 9761.58 | E22: =BP!N10 -> 8069.825 | F22: =BP!R10 -> 9266.473 | G22: =BP!V10 -> 9918.133 | H22: =BP!Z10 -> 13100.379 | I22: =BP!AD10 -> 13020.191 | J22: =BP!AB10 -> 11993.106 | K22: =BP!AF10 -> 13853.303
A23: Ativos de conteúdo | B23: BP fim do período | C23: =BP!F11 -> 24504.567 | D23: =BP!J11 -> 25383.95 | E23: =BP!N11 -> 30919.539 | F23: =BP!R11 -> 32736.713 | G23: =BP!V11 -> 31658.056 | H23: =BP!Z11 -> 32452.462 | I23: =BP!AD11 -> 32778.392 | J23: =BP!AB11 -> 32089.394 | K23: =BP!AF11 -> 33837.573
A24: Ativo total | B24: BP fim do período | C24: =BP!F15 -> 33975.712 | D24: =BP!J15 -> 39280.359 | E24: =BP!N15 -> 44584.663 | F24: =BP!R15 -> 48594.768 | G24: =BP!V15 -> 48731.992 | H24: =BP!Z15 -> 53630.374 | I24: =BP!AD15 -> 55596.993 | J24: =BP!AB15 -> 53099.664 | K24: =BP!AF15 -> 58450.441
A25: Passivo circulante | B25: BP fim do período | C25: =BP!F24 -> 6855.696 | D25: =BP!J24 -> 7805.785 | E25: =BP!N24 -> 8488.966 | F25: =BP!R24 -> 7930.974 | G25: =BP!V24 -> 8860.655 | H25: =BP!Z24 -> 10755.4 | I25: =BP!AD24 -> 10980.93 | J25: =BP!AB24 -> 8942.335 | K25: =BP!AF24 -> 12134.898
A26: Dívida de longo prazo | B26: BP fim do período | C26: =BP!F26 -> 14759 | D26: =BP!J26 -> 15809.095 | E26: =BP!N26 -> 14693.072 | F26: =BP!R26 -> 14353.076 | G26: =BP!V26 -> 14143.417 | H26: =BP!Z26 -> 13798.351 | I26: =BP!AD26 -> 13463.971 | J26: =BP!AB26 -> 14453.206 | K26: =BP!AF26 -> 11825.548
A27: Passivo total | B27: BP fim do período | C27: =BP!F30 -> 26393.555 | D27: =BP!J30 -> 28215.119 | E27: =BP!N30 -> 28735.415 | F27: =BP!R30 -> 27817.367 | G27: =BP!V30 -> 28143.679 | H27: =BP!Z30 -> 28886.807 | I27: =BP!AD30 -> 28981.505 | J27: =BP!AB30 -> 28147.765 | K27: =BP!AF30 -> 28298.389
A28: Patrimônio líquido | B28: BP fim do período | C28: =BP!F31 -> 7582.157 | D28: =BP!J31 -> 11065.24 | E28: =BP!N31 -> 15849.248 | F28: =BP!R31 -> 20777.401 | G28: =BP!V31 -> 20588.313 | H28: =BP!Z31 -> 24743.567 | I28: =BP!AD31 -> 26615.488 | J28: =BP!AB31 -> 24951.899 | K28: =BP!AF31 -> 30152.052
A30: AH ano contra ano (1S contra 1S)
A31: Receita líquida | C31: n.d. | D31: =IFERROR((D7-C7)/ABS(C7),"") -> 0.24010229 | E31: =IFERROR((E7-D7)/ABS(D7),"") -> 0.18810119 | F31: =IFERROR((F7-E7)/ABS(E7),"") -> 0.064573913 | G31: =IFERROR((G7-F7)/ABS(F7),"") -> 0.066668048 | H31: =IFERROR((H7-G7)/ABS(G7),"") -> 0.1564992 | I31: =IFERROR((I7-H7)/ABS(H7),"") -> 0.15851069 | K31: =IFERROR((K7-J7)/ABS(J7),"") -> 0.14743006
A32: Custo dos serviços | C32: n.d. | D32: =IFERROR((D8-C8)/ABS(C8),"") -> 0.22797889 | E32: =IFERROR((E8-D8)/ABS(D8),"") -> 0.13461122 | F32: =IFERROR((F8-E8)/ABS(E8),"") -> 0.10590409 | G32: =IFERROR((G8-F8)/ABS(F8),"") -> 0.028541051 | H32: =IFERROR((H8-G8)/ABS(G8),"") -> 0.067109881 | I32: =IFERROR((I8-H8)/ABS(H8),"") -> 0.10632264 | K32: =IFERROR((K8-J8)/ABS(J8),"") -> 0.12624548
A33: Lucro bruto | C33: n.d. | D33: =IFERROR((D9-C9)/ABS(C9),"") -> 0.25964778 | E33: =IFERROR((E9-D9)/ABS(D9),"") -> 0.27217033 | F33: =IFERROR((F9-E9)/ABS(E9),"") -> 0.0066399459 | G33: =IFERROR((G9-F9)/ABS(F9),"") -> 0.12538208 | H33: =IFERROR((H9-G9)/ABS(G9),"") -> 0.28230961 | I33: =IFERROR((I9-H9)/ABS(H9),"") -> 0.21963561 | K33: =IFERROR((K9-J9)/ABS(J9),"") -> 0.16776014
A34: Despesas operacionais | C34: n.d. | D34: =IFERROR((D10-C10)/ABS(C10),"") -> 0.0043951659 | E34: =IFERROR((E10-D10)/ABS(D10),"") -> 0.2018141 | F34: =IFERROR((F10-E10)/ABS(E10),"") -> 0.10432966 | G34: =IFERROR((G10-F10)/ABS(F10),"") -> 0.035144812 | H34: =IFERROR((H10-G10)/ABS(G10),"") -> 0.069601241 | I34: =IFERROR((I10-H10)/ABS(H10),"") -> 0.13734014 | K34: =IFERROR((K10-J10)/ABS(J10),"") -> 0.21040586
A35: EBIT | C35: n.d. | D35: =IFERROR((D11-C11)/ABS(C11),"") -> 0.76069193 | E35: =IFERROR((E11-D11)/ABS(D11),"") -> 0.3509528 | F35: =IFERROR((F11-E11)/ABS(E11),"") -> -0.09067353 | G35: =IFERROR((G11-F11)/ABS(F11),"") -> 0.23454849 | H35: =IFERROR((H11-G11)/ABS(G11),"") -> 0.49807442 | I35: =IFERROR((I11-H11)/ABS(H11),"") -> 0.27923755 | K35: =IFERROR((K11-J11)/ABS(J11),"") -> 0.14433562
A36: EBITDA | C36: n.d. | D36: =IFERROR((D12-C12)/ABS(C12),"") -> 0.7360742 | E36: =IFERROR((E12-D12)/ABS(D12),"") -> 0.36203411 | F36: =IFERROR((F12-E12)/ABS(E12),"") -> -0.067689106 | G36: =IFERROR((G12-F12)/ABS(F12),"") -> 0.22471465 | H36: =IFERROR((H12-G12)/ABS(G12),"") -> 0.46992224 | I36: =IFERROR((I12-H12)/ABS(H12),"") -> 0.27110747 | K36: =IFERROR((K12-J12)/ABS(J12),"") -> 0.14652187
A37: Despesa de juros | C37: n.d. | D37: =IFERROR((D13-C13)/ABS(C13),"") -> 0.2259917 | E37: =IFERROR((E13-D13)/ABS(D13),"") -> -0.0024482117 | F37: =IFERROR((F13-E13)/ABS(E13),"") -> -0.077594629 | G37: =IFERROR((G13-F13)/ABS(F13),"") -> -0.0090426104 | H37: =IFERROR((H13-G13)/ABS(G13),"") -> 0.027016716 | I37: =IFERROR((I13-H13)/ABS(H13),"") -> 0.080387293 | K37: =IFERROR((K13-J13)/ABS(J13),"") -> 0.19339405
A38: Outras receitas/despesas financeiras | C38: n.d. | D38: =IFERROR((D14-C14)/ABS(C14),"") -> -8.3623929 | E38: =IFERROR((E14-D14)/ABS(D14),"") -> 1.6649203 | F38: =IFERROR((F14-E14)/ABS(E14),"") -> -0.17972151 | G38: =IFERROR((G14-F14)/ABS(F14),"") -> -1.144591 | H38: =IFERROR((H14-G14)/ABS(G14),"") -> 6.4698598 | I38: =IFERROR((I14-H14)/ABS(H14),"") -> -0.3535438 | K38: =IFERROR((K14-J14)/ABS(J14),"") -> 31.076208
A39: Lucro líquido | C39: n.d. | D39: =IFERROR((D15-C15)/ABS(C15),"") -> 0.47912118 | E39: =IFERROR((E15-D15)/ABS(D15),"") -> 0.85276934 | F39: =IFERROR((F15-E15)/ABS(E15),"") -> -0.12202427 | G39: =IFERROR((G15-F15)/ABS(F15),"") -> 0.20393622 | H39: =IFERROR((H15-G15)/ABS(G15),"") -> 0.61088149 | I39: =IFERROR((I15-H15)/ABS(H15),"") -> 0.26052182 | K39: =IFERROR((K15-J15)/ABS(J15),"") -> 0.44357475
A40: FCO | C40: n.d. | D40: =IFERROR((D16-C16)/ABS(C16),"") -> 1.840598 | E40: =IFERROR((E16-D16)/ABS(D16),"") -> -0.83823752 | F40: =IFERROR((F16-E16)/ABS(E16),"") -> 4.1609918 | G40: =IFERROR((G16-F16)/ABS(F16),"") -> 2.5900189 | H40: =IFERROR((H16-G16)/ABS(G16),"") -> 0.011968573 | I40: =IFERROR((I16-H16)/ABS(H16),"") -> 0.3787218 | K40: =IFERROR((K16-J16)/ABS(J16),"") -> 0.34946283
A41: FCL (FCO − Capex) | C41: n.d. | D41: =IFERROR((D17-C17)/ABS(C17),"") -> 1.6143104 | E41: =IFERROR((E17-D17)/ABS(D17),"") -> -1.0684108 | F41: =IFERROR((F17-E17)/ABS(E17),"") -> 13.263898 | G41: =IFERROR((G17-F17)/ABS(F17),"") -> 3.2790418 | H41: =IFERROR((H17-G17)/ABS(G17),"") -> -0.00056643693 | I41: =IFERROR((I17-H17)/ABS(H17),"") -> 0.36684352 | K41: =IFERROR((K17-J17)/ABS(J17),"") -> 0.34311123
A42: Pagamentos de conteúdo | C42: n.d. | D42: =IFERROR((D18-C18)/ABS(C18),"") -> -0.15358538 | E42: =IFERROR((E18-D18)/ABS(D18),"") -> 0.50282496 | F42: =IFERROR((F18-E18)/ABS(E18),"") -> -0.048760262 | G42: =IFERROR((G18-F18)/ABS(F18),"") -> -0.25442873 | H42: =IFERROR((H18-G18)/ABS(G18),"") -> 0.29223423 | I42: =IFERROR((I18-H18)/ABS(H18),"") -> 0.053810442 | K42: =IFERROR((K18-J18)/ABS(J18),"") -> 0.32346892
... A52: Patrimônio líquido | C52: n.d. | D52: =IFERROR((D28-C28)/ABS(C28),"") -> 0.45937891 | E52: =IFERROR((E28-D28)/ABS(D28),"") -> 0.43234562 | F52: =IFERROR((F28-E28)/ABS(E28),"") -> 0.31093923 | G52: =IFERROR((G28-F28)/ABS(F28),"") -> -0.009100657 | H52: =IFERROR((H28-G28)/ABS(G28),"") -> 0.20182586 | I52: =IFERROR((I28-H28)/ABS(H28),"") -> 0.075652835 | K52: =IFERROR((K28-J28)/ABS(J28),"") -> 0.2084071
A54: Margens e alavancagens anuais (fórmula 1 da disciplina: elasticidades)
A55: Margem EBIT | C55: =C11/C7 -> 0.12920204 | D55: =D11/D7 -> 0.1834405 | E55: =E11/E7 -> 0.20858447 | F55: =F11/F7 -> 0.17816647 | G55: =G11/G7 -> 0.20620768 | H55: =H11/H7 -> 0.26711169 | I55: =I11/I7 -> 0.29494705 | J55: =J11/J7 -> 0.32937304 | K55: =K11/K7 -> 0.32848477
A56: Margem líquida | C56: =C15/C7 -> 0.092621284 | D56: =D15/D7 -> 0.11047323 | E56: =E15/E7 -> 0.17227607 | F56: =F15/F7 -> 0.14207958 | G56: =G15/G7 -> 0.16036362 | H56: =H15/H7 -> 0.22336962 | I56: =I15/I7 -> 0.24303814 | J56: =J15/J7 -> 0.27822464 | K56: =K15/K7 -> 0.35003272
A57: GAO = Δ%EBIT / Δ%Receita | C57: n.d. | D57: =IFERROR(D35/D31,"") -> 3.1681994 | E57: =IFERROR(E35/E31,"") -> 1.8657659 | F57: =IFERROR(F35/F31,"") -> -1.4041821 | G57: =IFERROR(G35/G31,"") -> 3.5181544 | H57: =IFERROR(H35/H31,"") -> 3.1826004 | I57: =IFERROR(I35/I31,"") -> 1.7616323 | K57: =IFERROR(K35/K31,"") -> 0.97901078
A58: GAF = Δ%Lucro líquido / Δ%EBIT | C58: n.d. | D58: =IFERROR(D39/D35,"") -> 0.62984917 | E58: =IFERROR(E39/E35,"") -> 2.4298691 | F58: =IFERROR(F39/F35,"") -> 1.3457541 | G58: =IFERROR(G39/G35,"") -> 0.86948426 | H58: =IFERROR(H39/H35,"") -> 1.2264864 | I58: =IFERROR(I39/I35,"") -> 0.93297562 | K58: =IFERROR(K39/K35,"") -> 3.0732174
A59: GAT = GAO × GAF | C59: n.d. | D59: =IFERROR(D57*D58,"") -> 1.9954878 | E59: =IFERROR(E57*E58,"") -> 4.5335669 | F59: =IFERROR(F57*F58,"") -> -1.8896837 | G59: =IFERROR(G57*G58,"") -> 3.0589799 | H59: =IFERROR(H57*H58,"") -> 3.9034161 | I59: =IFERROR(I57*I58,"") -> 1.64356 | K59: =IFERROR(K57*K58,"") -> 3.008713
A61: A disciplina usa Δ%LPA no GAF; aqui usa-se Δ%Lucro líquido porque o desdobramento de ações 10:1 (nov/2025) distorce o LPA histórico.
A63: Em 2026 o lucro líquido inclui a multa rescisória da WBD (US$ 2,8 bi), o que infla o GAF do 1S2026 — ler junto com a aba Variacoes_Bruscas.

Sheet Indicadores
A1: Índices econômico-financeiros (trimestrais)
A2: Valores "LTM" = últimos 12 meses (soma de 4 trimestres): evita multiplicar o trimestre por 4 e ignorar a sazonalidade.
A4: Conta / indicador | B4: Fonte ou fórmula | C4: 2019T1 | D4: 2019T2 | E4: 2019T3 | F4: 2019T4 | G4: 2020T1 | H4: 2020T2 | I4: 2020T3 | J4: 2020T4 | K4: 2021T1 | L4: 2021T2 | M4: 2021T3 | N4: 2021T4 | O4: 2022T1 | P4: 2022T2 | Q4: 2022T3 | R4: 2022T4 | S4: 2023T1 | T4: 2023T2 | U4: 2023T3 | V4: 2023T4 | W4: 2024T1 | X4: 2024T2 | Y4: 2024T3 | Z4: 2024T4 | AA4: 2025T1 | AB4: 2025T2 | AC4: 2025T3 | AD4: 2025T4 | AE4: 2026T1 | AF4: 2026T2
A6: Rentabilidade do trimestre
A7: Margem bruta | C7: =IFERROR(DRE!C9/DRE!C7,"") -> 0.36504776 | D7: =IFERROR(DRE!D9/DRE!D7,"") -> 0.38948077 | E7: =IFERROR(DRE!E9/DRE!E7,"") -> 0.40934698 | F7: =IFERROR(DRE!F9/DRE!F7,"") -> 0.36606039 | G7: =IFERROR(DRE!G9/DRE!G7,"") -> 0.37588525 | H7: =IFERROR(DRE!H9/DRE!H7,"") -> 0.40736215 | I7: =IFERROR(DRE!I9/DRE!I7,"") -> 0.39901039 | J7: =IFERROR(DRE!J9/DRE!J7,"") -> 0.37313622 | ... AF7: =IFERROR(DRE!AF9/DRE!AF7,"") -> 0.51934755
A8: Margem EBIT (operacional) | C8: =IFERROR(DRE!C14/DRE!C7,"") -> 0.10154497 | D8: =IFERROR(DRE!D14/DRE!D7,"") -> 0.14349022 | E8: =IFERROR(DRE!E14/DRE!E7,"") -> 0.18689357 | F8: =IFERROR(DRE!F14/DRE!F7,"") -> 0.083862375 | G8: =IFERROR(DRE!G14/DRE!G7,"") -> 0.16614205 | H8: =IFERROR(DRE!H14/DRE!H7,"") -> 0.22086286 | I8: =IFERROR(DRE!I14/DRE!I7,"") -> 0.20430969 | J8: =IFERROR(DRE!J14/DRE!J7,"") -> 0.14361507 | ... AF8: =IFERROR(DRE!AF14/DRE!AF7,"") -> 0.33380818
A9: Margem EBITDA | C9: =IFERROR(DRE!C30/DRE!C7,"") -> 0.10675644 | D9: =IFERROR(DRE!D30/DRE!D7,"") -> 0.14866905 | E9: =IFERROR(DRE!E30/DRE!E7,"") -> 0.19198498 | F9: =IFERROR(DRE!F30/DRE!F7,"") -> 0.088950319 | G9: =IFERROR(DRE!G30/DRE!G7,"") -> 0.17108632 | H9: =IFERROR(DRE!H30/DRE!H7,"") -> 0.22519919 | I9: =IFERROR(DRE!I30/DRE!I7,"") -> 0.20875199 | J9: =IFERROR(DRE!J30/DRE!J7,"") -> 0.14842255 | ... AF9: =IFERROR(DRE!AF30/DRE!AF7,"") -> 0.3418122
A10: Margem líquida | C10: =IFERROR(DRE!C19/DRE!C7,"") -> 0.076100997 | D10: =IFERROR(DRE!D19/DRE!D7,"") -> 0.054975345 | E10: =IFERROR(DRE!E19/DRE!E7,"") -> 0.12683623 | F10: =IFERROR(DRE!F19/DRE!F7,"") -> 0.10735749 | G10: =IFERROR(DRE!G19/DRE!G7,"") -> 0.12293776 | H10: =IFERROR(DRE!H19/DRE!H7,"") -> 0.11713769 | I10: =IFERROR(DRE!I19/DRE!I7,"") -> 0.12275024 | J10: =IFERROR(DRE!J19/DRE!J7,"") -> 0.081595415 | ... AF10: =IFERROR(DRE!AF19/DRE!AF7,"") -> 0.27081455
A12: Últimos 12 meses (LTM) — US$ milhões
A13: Receita LTM | C13: n.d. | D13: n.d. | E13: n.d. | F13: =DRE!C7+DRE!D7+DRE!E7+DRE!F7 -> 20156.447 | G13: =DRE!D7+DRE!E7+DRE!F7+DRE!G7 -> 21403.146 | H13: =DRE!E7+DRE!F7+DRE!G7+DRE!H7 -> 22628.316 | I13: =DRE!F7+DRE!G7+DRE!H7+DRE!I7 -> 23819.048 | J13: =DRE!G7+DRE!H7+DRE!I7+DRE!J7 -> 24996.056 | K13: =DRE!H7+DRE!I7+DRE!J7+DRE!K7 -> 26391.647 | L13: =DRE!I7+DRE!J7+DRE!K7+DRE!L7 -> 27585.138 | M13: =DRE!J7+DRE!K7+DRE!L7+DRE!M7 -> 28632.968 | ... AF13: =DRE!AC7+DRE!AD7+DRE!AE7+DRE!AF7 -> 48370.764
A14: EBIT LTM | C14: n.d. | D14: n.d. | E14: n.d. | F14: =DRE!C14+DRE!D14+DRE!E14+DRE!F14 -> 2604.254 | G14: =DRE!D14+DRE!E14+DRE!F14+DRE!G14 -> 3103.426 | H14: =DRE!E14+DRE!F14+DRE!G14+DRE!H14 -> 3754.935 | I14: =DRE!F14+DRE!G14+DRE!H14+DRE!I14 -> 4089.559 | J14: =DRE!G14+DRE!H14+DRE!I14+DRE!J14 -> 4585.289 | K14: =DRE!H14+DRE!I14+DRE!J14+DRE!K14 -> 5586.889 | L14: =DRE!I14+DRE!J14+DRE!K14+DRE!L14 -> 6076.591 | M14: =DRE!J14+DRE!K14+DRE!L14+DRE!M14 -> 6516.981 | ... AF14: =DRE!AC14+DRE!AD14+DRE!AE14+DRE!AF14 -> 14354.517
A15: EBITDA LTM | C15: n.d. | D15: n.d. | E15: n.d. | F15: =DRE!C30+DRE!D30+DRE!E30+DRE!F30 -> 2707.833 | G15: =DRE!D30+DRE!E30+DRE!F30+DRE!G30 -> 3211.961 | H15: =DRE!E30+DRE!F30+DRE!G30+DRE!H30 -> 3864.635 | I15: =DRE!F30+DRE!G30+DRE!H30+DRE!I30 -> 4201.144 | J15: =DRE!G30+DRE!H30+DRE!I30+DRE!J30 -> 4700.999 | K15: =DRE!H30+DRE!I30+DRE!J30+DRE!K30 -> 5709.823 | L15: =DRE!I30+DRE!J30+DRE!K30+DRE!L30 -> 6211.298 | M15: =DRE!J30+DRE!K30+DRE!L30+DRE!M30 -> 6693.352 | ... AF15: =DRE!AC30+DRE!AD30+DRE!AE30+DRE!AF30 -> 14726.931
A16: Lucro líquido LTM | C16: n.d. | D16: n.d. | E16: n.d. | F16: =DRE!C19+DRE!D19+DRE!E19+DRE!F19 -> 1866.916 | G16: =DRE!D19+DRE!E19+DRE!F19+DRE!G19 -> 2231.931 | H16: =DRE!E19+DRE!F19+DRE!G19+DRE!H19 -> 2681.477 | I16: =DRE!F19+DRE!G19+DRE!H19+DRE!I19 -> 2806.209 | J16: =DRE!G19+DRE!H19+DRE!I19+DRE!J19 -> 2761.395 | K16: =DRE!H19+DRE!I19+DRE!J19+DRE!K19 -> 3759.043 | L16: =DRE!I19+DRE!J19+DRE!K19+DRE!L19 -> 4391.86 | M16: =DRE!J19+DRE!K19+DRE!L19+DRE!M19 -> 5050.955 | ... AF16: =DRE!AC19+DRE!AD19+DRE!AE19+DRE!AF19 -> 13649.642
A17: Despesa de juros LTM | C17: n.d. | D17: n.d. | E17: n.d. | F17: =DRE!C15+DRE!D15+DRE!E15+DRE!F15 -> 626.023 | G17: =DRE!D15+DRE!E15+DRE!F15+DRE!G15 -> 674.577 | H17: =DRE!E15+DRE!F15+DRE!G15+DRE!H15 -> 711.695 | I17: =DRE!F15+DRE!G15+DRE!H15+DRE!I15 -> 748.114 | J17: =DRE!G15+DRE!H15+DRE!I15+DRE!J15 -> 767.499 | K17: =DRE!H15+DRE!I15+DRE!J15+DRE!K15 -> 777.856 | L17: =DRE!I15+DRE!J15+DRE!K15+DRE!L15 -> 780.027 | M17: =DRE!J15+DRE!K15+DRE!L15+DRE!M15 -> 773.377 | ... AF17: =DRE!AC15+DRE!AD15+DRE!AE15+DRE!AF15 -> 847.451
A18: Custo dos serviços LTM | C18: n.d. | D18: n.d. | E18: n.d. | F18: =DRE!C8+DRE!D8+DRE!E8+DRE!F8 -> 12440.213 | G18: =DRE!D8+DRE!E8+DRE!F8+DRE!G8 -> 13169.3 | H18: =DRE!E8+DRE!F8+DRE!G8+DRE!H8 -> 13807.35 | I18: =DRE!F8+DRE!G8+DRE!H8+DRE!I8 -> 14577.182 | J18: =DRE!G8+DRE!H8+DRE!I8+DRE!J8 -> 15276.319 | K18: =DRE!H8+DRE!I8+DRE!J8+DRE!K8 -> 15545.129 | L18: =DRE!I8+DRE!J8+DRE!K8+DRE!L8 -> 15919.43 | M18: =DRE!J8+DRE!K8+DRE!L8+DRE!M8 -> 16258.268 | ... AF18: =DRE!AC8+DRE!AD8+DRE!AE8+DRE!AF8 -> 24612.074
A20: DuPont (modelo da disciplina): ROA = Margem líquida × Giro; ROE = ROA × MAF
A21: Margem líquida LTM (LL/Receitas) | C21: n.d. | D21: n.d. | E21: n.d. | F21: =F16/F13 -> 0.092621284 | G21: =G16/G13 -> 0.10428051 | H21: =H16/H13 -> 0.11850095 | I21: =I16/I13 -> 0.11781365 | J21: =J16/J13 -> 0.11047323 | K21: =K16/K13 -> 0.14243306 | L21: =L16/L13 -> 0.15921109 | M21: =M16/M13 -> 0.17640347 | ... AF21: =AF16/AF13 -> 0.28218785
A22: Giro do ativo (Receitas LTM / Ativo total) | C22: n.d. | D22: n.d. | E22: n.d. | F22: =F13/BP!F15 -> 0.59326047 | G22: =G13/BP!G15 -> 0.6104735 | H22: =H13/BP!H15 -> 0.60869253 | I22: =I13/BP!I15 -> 0.61671361 | J22: =J13/BP!J15 -> 0.63634999 | K22: =K13/BP!K15 -> 0.65776831 | L22: =L13/BP!L15 -> 0.67328498 | M22: =M13/BP!M15 -> 0.66993598 | ... AF22: =AF13/BP!AF15 -> 0.82755174
A23: ROA = Margem líquida × Giro | C23: n.d. | D23: n.d. | E23: n.d. | F23: =F21*F22 -> 0.054948547 | G23: =G21*G22 -> 0.063660489 | H23: =H21*H22 -> 0.072130645 | I23: =I21*I22 -> 0.072657282 | J23: =J21*J22 -> 0.070299638 | K23: =K21*K22 -> 0.093687952 | L23: =L21*L22 -> 0.10719444 | M23: =M21*M22 -> 0.11817903 | ... AF23: =AF21*AF22 -> 0.23352505
A24: MAF — multiplicador de alavancagem (AT / PL) | C24: =BP!C15/BP!C31 -> 4.7726381 | D24: =BP!D15/BP!D31 -> 4.9416267 | E24: =BP!E15/BP!E31 -> 4.5094642 | F24: =BP!F15/BP!F31 -> 4.4810088 | G24: =BP!G15/BP!G31 -> 4.1691859 | H24: =BP!H15/BP!H31 -> 3.9824601 | I24: =BP!I15/BP!I31 -> 3.7376692 | J24: =BP!J15/BP!J31 -> 3.5498877 | ... AF24: =BP!AF15/BP!AF31 -> 1.9385228
A25: ROE = ROA × MAF | C25: n.d. | D25: n.d. | E25: n.d. | F25: =F23*F24 -> 0.24622492 | G25: =G23*G24 -> 0.26541241 | H25: =H23*H24 -> 0.28725741 | I25: =I23*I24 -> 0.27156888 | J25: =J23*J24 -> 0.24955582 | K25: =K23*K24 -> 0.29175874 | L25: =L23*L24 -> 0.31678454 | M25: =M23*M24 -> 0.32981269 | ... AF25: =AF23*AF24 -> 0.45269363
A26: Conferência: LL LTM / PL | C26: n.d. | D26: n.d. | E26: n.d. | F26: =F16/BP!F31 -> 0.24622492 | G26: =G16/BP!G31 -> 0.26541241 | H26: =H16/BP!H31 -> 0.28725741 | I26: =I16/BP!I31 -> 0.27156888 | J26: =J16/BP!J31 -> 0.24955582 | K26: =K16/BP!K31 -> 0.29175874 | L26: =L16/BP!L31 -> 0.31678454 | M26: =M16/BP!M31 -> 0.32981269 | ... AF26: =AF16/BP!AF31 -> 0.45269363
A28: Liquidez
A29: Liquidez corrente (AC / PC) | C29: =BP!C10/BP!C24 -> 0.60790673 | D29: =BP!D10/BP!D24 -> 0.84758733 | E29: =BP!E10/BP!E24 -> 0.7340633 | F29: =BP!F10/BP!F24 -> 0.90122199 | G29: =BP!G10/BP!G24 -> 0.8209838 | H29: =BP!H10/BP!H24 -> 1.1229569 | I29: =BP!I10/BP!I24 -> 1.2376239 | J29: =BP!J10/BP!J24 -> 1.2505571 | ... AF29: =BP!AF10/BP!AF24 -> 1.1416085
A30: Liquidez seca ((AC − Estoques) / PC) — sem estoques, = LC | C30: =(BP!C10-0)/BP!C24 -> 0.60790673 | D30: =(BP!D10-0)/BP!D24 -> 0.84758733 | E30: =(BP!E10-0)/BP!E24 -> 0.7340633 | F30: =(BP!F10-0)/BP!F24 -> 0.90122199 | G30: =(BP!G10-0)/BP!G24 -> 0.8209838 | H30: =(BP!H10-0)/BP!H24 -> 1.1229569 | I30: =(BP!I10-0)/BP!I24 -> 1.2376239 | J30: =(BP!J10-0)/BP!J24 -> 1.2505571 | ... AF30: =(BP!AF10-0)/BP!AF24 -> 1.1416085
A31: Liquidez imediata ((Caixa + Aplicações) / PC) | C31: =(BP!C7+BP!C8)/BP!C24 -> 0.48828394 | D31: =(BP!D7+BP!D8)/BP!D24 -> 0.72169867 | E31: =(BP!E7+BP!E8)/BP!E24 -> 0.61106078 | F31: =(BP!F7+BP!F8)/BP!F24 -> 0.73200985 | G31: =(BP!G7+BP!G8)/BP!G24 -> 0.65597968 | H31: =(BP!H7+BP!H8)/BP!H24 -> 0.93795646 | I31: =(BP!I7+BP!I8)/BP!I24 -> 1.0570035 | J31: =(BP!J7+BP!J8)/BP!J24 -> 1.0512139 | ... AF31: =(BP!AF7+BP!AF8)/BP!AF24 -> 0.75220327
A33: Modelo Fleuriet (capital de giro) — US$ milhões
A34: CCL / CDG = AC − PC | C34: =BP!C10-BP!C24 -> -2688.9 | D34: =BP!D10-BP!D24 -> -1056.827 | E34: =BP!E10-BP!E24 -> -1930.142 | F34: =BP!F10-BP!F24 -> -677.192 | G34: =BP!G10-BP!G24 -> -1405.944 | H34: =BP!H10-BP!H24 -> 937.721 | I34: =BP!I10-BP!I24 -> 1886.685 | J34: =BP!J10-BP!J24 -> 1955.795 | ... AF34: =BP!AF10-BP!AF24 -> 1718.405
A35: ACO — ativo circulante operacional (outros AC) | C35: =BP!C9 -> 820.35 | D35: =BP!D9 -> 872.91 | E35: =BP!E9 -> 892.74 | F35: =BP!F9 -> 1160.067 | G35: =BP!G9 -> 1295.897 | H35: =BP!H9 -> 1410.891 | I35: =BP!I9 -> 1434.089 | J35: =BP!J9 -> 1556.03 | ... AF35: =BP!AF9 -> 4725.393
A36: PCO — passivo circulante operacional (PC − dívida CP) | C36: =BP!C24-BP!C22 -> 6857.807 | D36: =BP!D24-BP!D22 -> 6933.984 | E36: =BP!E24-BP!E22 -> 7257.9 | F36: =BP!F24-BP!F22 -> 6855.696 | G36: =BP!G24-BP!G22 -> 7354.725 | H36: =BP!H24-BP!H22 -> 7127.418 | I36: =BP!I24-BP!I22 -> 7439.795 | J36: =BP!J24-BP!J22 -> 7305.907 | ... AF36: =BP!AF24-BP!AF22 -> 9650.898
A37: NCG = ACO − PCO | C37: =C35-C36 -> -6037.457 | D37: =D35-D36 -> -6061.074 | E37: =E35-E36 -> -6365.16 | F37: =F35-F36 -> -5695.629 | G37: =G35-G36 -> -6058.828 | H37: =H35-H36 -> -5716.527 | I37: =I35-I36 -> -6005.706 | J37: =J35-J36 -> -5749.877 | ... AF37: =AF35-AF36 -> -4925.505
A38: Saldo de tesouraria ST = CCL − NCG | C38: =C34-C37 -> 3348.557 | D38: =D34-D37 -> 5004.247 | E38: =E34-E37 -> 4435.018 | F38: =F34-F37 -> 5018.437 | G38: =G34-G37 -> 4652.884 | H38: =H34-H37 -> 6654.248 | I38: =I34-I37 -> 7892.391 | J38: =J34-J37 -> 7705.672 | ... AF38: =AF34-AF37 -> 6643.91
A39: Conferência: ST = (Caixa + Aplicações) − Dívida CP | C39: =C38-(BP!C7+BP!C8-BP!C22) -> 0 | D39: =D38-(BP!D7+BP!D8-BP!D22) -> 0 | E39: =E38-(BP!E7+BP!E8-BP!E22) -> 0 | F39: =F38-(BP!F7+BP!F8-BP!F22) -> 0 | G39: =G38-(BP!G7+BP!G8-BP!G22) -> 0 | H39: =H38-(BP!H7+BP!H8-BP!H22) -> 0 | I39: =I38-(BP!I7+BP!I8-BP!I22) -> 0 | J39: =J38-(BP!J7+BP!J8-BP!J22) -> 0 | ... AF39: =AF38-(BP!AF7+BP!AF8-BP!AF22) -> 0
A40: Tipo de estrutura (Fleuriet/Braga: sinais de CCL, NCG e ST) | C40: =IF(AND(C34>0,NOT(C37>0),C38>0),"I - Excelente",IF(AND(C34>0,C37>0,C38>0),"II - Sólida",IF(AND(C34>0,C37>0,NOT(C38>0)),"III - Insatisfatória",IF(AND(NOT(C34>0),C37>0,NOT(C38>0)),"IV - Péssima",IF(AND(NOT(C34>0),NOT(C37>0),NOT(C38>0)),"V - Muito ruim",IF(AND(NOT(C34>0),NOT(C37>0),C38>0),"VI - Alto risco","Outra")))))) -> VI - Alto risco | D40: =IF(AND(D34>0,NOT(D37>0),D38>0),"I - Excelente",IF(AND(D34>0,D37>0,D38>0),"II - Sólida",IF(AND(D34>0,D37>0,NOT(D38>0)),"III - Insatisfatória",IF(AND(NOT(D34>0),D37>0,NOT(D38>0)),"IV - Péssima",IF(AND(NOT(D34>0),NOT(D37>0),NOT(D38>0)),"V - Muito ruim",IF(AND(NOT(D34>0),NOT(D37>0),D38>0),"VI - Alto risco","Outra")))))) -> VI - Alto risco | E40: =IF(AND(E34>0,NOT(E37>0),E38>0),"I - Excelente",IF(AND(E34>0,E37>0,E38>0),"II - Sólida",IF(AND(E34>0,E37>0,NOT(E38>0)),"III - Insatisfatória",IF(AND(NOT(E34>0),E37>0,NOT(E38>0)),"IV - Péssima",IF(AND(NOT(E34>0),NOT(E37>0),NOT(E38>0)),"V - Muito ruim",IF(AND(NOT(E34>0),NOT(E37>0),E38>0),"VI - Alto risco","Outra")))))) -> VI - Alto risco | F40: =IF(AND(F34>0,NOT(F37>0),F38>0),"I - Excelente",IF(AND(F34>0,F37>0,F38>0),"II - Sólida",IF(AND(F34>0,F37>0,NOT(F38>0)),"III - Insatisfatória",IF(AND(NOT(F34>0),F37>0,NOT(F38>0)),"IV - Péssima",IF(AND(NOT(F34>0),NOT(F37>0),NOT(F38>0)),"V - Muito ruim",IF(AND(NOT(F34>0),NOT(F37>0),F38>0),"VI - Alto risco","Outra")))))) -> VI - Alto risco | G40: =IF(AND(G34>0,NOT(G37>0),G38>0),"I - Excelente",IF(AND(G34>0,G37>0,G38>0),"II - Sólida",IF(AND(G34>0,G37>0,NOT(G38>0)),"III - Insatisfatória",IF(AND(NOT(G34>0),G37>0,NOT(G38>0)),"IV - Péssima",IF(AND(NOT(G34>0),NOT(G37>0),NOT(G38>0)),"V - Muito ruim",IF(AND(NOT(G34>0),NOT(G37>0),G38>0),"VI - Alto risco","Outra")))))) -> VI - Alto risco | H40: =IF(AND(H34>0,NOT(H37>0),H38>0),"I - Excelente",IF(AND(H34>0,H37>0,H38>0),"II - Sólida",IF(AND(H34>0,H37>0,NOT(H38>0)),"III - Insatisfatória",IF(AND(NOT(H34>0),H37>0,NOT(H38>0)),"IV - Péssima",IF(AND(NOT(H34>0),NOT(H37>0),NOT(H38>0)),"V - Muito ruim",IF(AND(NOT(H34>0),NOT(H37>0),H38>0),"VI - Alto risco","Outra")))))) -> I - Excelente | I40: =IF(AND(I34>0,NOT(I37>0),I38>0),"I - Excelente",IF(AND(I34>0,I37>0,I38>0),"II - Sólida",IF(AND(I34>0,I37>0,NOT(I38>0)),"III - Insatisfatória",IF(AND(NOT(I34>0),I37>0,NOT(I38>0)),"IV - Péssima",IF(AND(NOT(I34>0),NOT(I37>0),NOT(I38>0)),"V - Muito ruim",IF(AND(NOT(I34>0),NOT(I37>0),I38>0),"VI - Alto risco","Outra")))))) -> I - Excelente | J40: =IF(AND(J34>0,NOT(J37>0),J38>0),"I - Excelente",IF(AND(J34>0,J37>0,J38>0),"II - Sólida",IF(AND(J34>0,J37>0,NOT(J38>0)),"III - Insatisfatória",IF(AND(NOT(J34>0),J37>0,NOT(J38>0)),"IV - Péssima",IF(AND(NOT(J34>0),NOT(J37>0),NOT(J38>0)),"V - Muito ruim",IF(AND(NOT(J34>0),NOT(J37>0),J38>0),"VI - Alto risco","Outra")))))) -> I - Excelente | ... AF40: =IF(AND(AF34>0,NOT(AF37>0),AF38>0),"I - Excelente",IF(AND(AF34>0,AF37>0,AF38>0),"II - Sólida",IF(AND(AF34>0,AF37>0,NOT(AF38>0)),"III - Insatisfatória",IF(AND(NOT(AF34>0),AF37>0,NOT(AF38>0)),"IV - Péssima",IF(AND(NOT(AF34>0),NOT(AF37>0),NOT(AF38>0)),"V - Muito ruim",IF(AND(NOT(AF34>0),NOT(AF37>0),AF38>0),"VI - Alto risco","Outra")))))) -> I - Excelente
A42: Tipo VI (CCL < 0, NCG < 0, ST > 0): o caixa existe, mas é sustentado por passivos operacionais de curto prazo (conteúdo a pagar, receita antecipada) — depende de a empresa continuar crescendo e recebendo antes de pagar.
A44: Estrutura de capital e endividamento
A45: CT/PL — capital de terceiros / PL | C45: =BP!C30/BP!C31 -> 3.7726381 | D45: =BP!D30/BP!D31 -> 3.9416267 | E45: =BP!E30/BP!E31 -> 3.5094642 | F45: =BP!F30/BP!F31 -> 3.4810088 | G45: =BP!G30/BP!G31 -> 3.1691859 | H45: =BP!H30/BP!H31 -> 2.9824601 | I45: =BP!I30/BP!I31 -> 2.7376692 | J45: =BP!J30/BP!J31 -> 2.5498877 | ... AF45: =BP!AF30/BP!AF31 -> 0.93852282
A46: Dívida bruta (CP + LP) — US$ mi | C46: =BP!C22+BP!C26 -> 10305.023 | D46: =BP!D22+BP!D26 -> 12594 | E46: =BP!E22+BP!E26 -> 12426 | F46: =BP!F22+BP!F26 -> 14759 | G46: =BP!G22+BP!G26 -> 14669.692 | H46: =BP!H22+BP!H26 -> 15793.998 | I46: =BP!I22+BP!I26 -> 16047.616 | J46: =BP!J22+BP!J26 -> 16308.973 | ... AF46: =BP!AF22+BP!AF26 -> 14309.548
A47: Dívida líquida (bruta − caixa − aplicações) — US$ mi | C47: =C46-BP!C7-BP!C8 -> 6956.466 | D47: =D46-BP!D7-BP!D8 -> 7589.753 | E47: =E46-BP!E7-BP!E8 -> 7990.982 | F47: =F46-BP!F7-BP!F8 -> 9740.563 | G47: =G46-BP!G7-BP!G8 -> 9517.808 | H47: =H46-BP!H7-BP!H8 -> 8640.75 | I47: =I46-BP!I7-BP!I8 -> 7655.225 | J47: =J46-BP!J7-BP!J8 -> 8103.423 | ... AF47: =AF46-BP!AF7-BP!AF8 -> 5181.638
A48: Dívida líquida / EBITDA LTM | C48: n.d. | D48: n.d. | E48: n.d. | F48: =F47/F15 -> 3.5971801 | G48: =G47/G15 -> 2.963239 | H48: =H47/H15 -> 2.2358515 | I48: =I47/I15 -> 1.8221763 | J48: =J47/J15 -> 1.7237662 | K48: =K47/K15 -> 1.253252 | L48: =L47/L15 -> 1.2635618 | M48: =M47/M15 -> 1.1901376 | ... AF48: =AF47/AF15 -> 0.35184778
A49: Cobertura de juros (EBIT LTM / Juros LTM) | C49: n.d. | D49: n.d. | E49: n.d. | F49: =F14/F17 -> 4.1599973 | G49: =G14/G17 -> 4.6005512 | H49: =H14/H17 -> 5.2760452 | I49: =I14/I17 -> 5.4664917 | J49: =J14/J17 -> 5.9743257 | K49: =K14/K17 -> 7.1824207 | L49: =L14/L17 -> 7.7902316 | M49: =M14/M17 -> 8.4266548 | ... AF49: =AF14/AF17 -> 16.938463
A50: PMPC — prazo médio de pagamento (Fornecedores / Custo LTM × 365), dias | C50: n.d. | D50: n.d. | E50: n.d. | F50: =BP!F19/F18*365 -> 19.785566 | G50: =BP!G19/G18*365 -> 15.118732 | H50: =BP!H19/H18*365 -> 11.807756 | I50: =BP!I19/I18*365 -> 13.553633 | J50: =BP!J19/J18*365 -> 15.678305 | K50: =BP!K19/K18*365 -> 12.513491 | L50: =BP!L19/L18*365 -> 14.282535 | M50: =BP!M19/M18*365 -> 14.436749 | ... AF50: =BP!AF19/AF18*365 -> 12.079889
A52: Conteúdo
A53: Ativos de conteúdo / Ativo total | C53: =BP!C11/BP!C15 -> 0.76744434 | D53: =BP!D11/BP!D15 -> 0.72737044 | E53: =BP!E11/BP!E15 -> 0.7509279 | F53: =BP!F11/BP!F15 -> 0.72123778 | G53: =BP!G11/BP!G15 -> 0.72067752 | H53: =BP!H11/BP!H15 -> 0.67666246 | I53: =BP!I11/BP!I15 -> 0.64904149 | J53: =BP!J11/BP!J15 -> 0.646225 | ... AF53: =BP!AF11/BP!AF15 -> 0.57891048
A54: Amortização de conteúdo / Receita | C54: =DRE!C28/DRE!C7 -> 0.46996013 | D54: =DRE!D28/DRE!D7 -> 0.45335414 | E54: =DRE!E28/DRE!E7 -> 0.4347032 | F54: =DRE!F28/DRE!F7 -> 0.47182444 | G54: =DRE!G28/DRE!G7 -> 0.43056832 | H54: =DRE!H28/DRE!H7 -> 0.42404647 | I54: =DRE!I28/DRE!I7 -> 0.42478204 | J54: =DRE!J28/DRE!J7 -> 0.44889022 | ... AF54: =DRE!AF28/DRE!AF7 -> 0.34325878
A55: Pagamentos / amortização de conteúdo | C55: =DFC!C17 -> 1.4109125 | D55: =DFC!D17 -> 1.4897982 | E55: =DFC!E17 -> 1.6001442 | F55: =DFC!F17 -> 1.5294761 | G55: =DFC!G17 -> 1.3265261 | H55: =DFC!H17 -> 0.96303371 | I55: =DFC!I17 -> 0.9707884 | J55: =DFC!J17 -> 1.1132278 | ... AF55: =DFC!AF17 -> 1.1429297
A57: Graus de alavancagem — fórmula 1 da disciplina, base homóloga (t vs t−4)
A58: GAO = Δ%EBIT / Δ%Receita | C58: n.d. | D58: n.d. | E58: n.d. | F58: n.d. | G58: =IFERROR(AH!G11/AH!G7,"") -> 3.943031 | H58: =IFERROR(AH!H11/AH!H7,"") -> 3.7059688 | I58: =IFERROR(AH!I11/AH!I7,"") -> 1.5036568 | J58: =IFERROR(AH!J11/AH!J7,"") -> 5.0222535 | K58: =IFERROR(AH!K11/AH!K7,"") -> 4.3197299 | L58: =IFERROR(AH!L11/AH!L7,"") -> 1.8577619 | M58: =IFERROR(AH!M11/AH!M7,"") -> 2.0571107 | N58: =IFERROR(AH!N11/AH!N7,"") -> -2.108594 | ... AF58: =IFERROR(AH!AF11/AH!AF7,"") -> 0.82837336
A59: GAF = Δ%Lucro líquido / Δ%EBIT | C59: n.d. | D59: n.d. | E59: n.d. | F59: n.d. | G59: =IFERROR(AH!G14/AH!G11,"") -> 0.97572755 | H59: =IFERROR(AH!H14/AH!H11,"") -> 1.8009766 | I59: =IFERROR(AH!I14/AH!I11,"") -> 0.54925221 | J59: =IFERROR(AH!J14/AH!J11,"") -> -0.070616032 | K59: =IFERROR(AH!K14/AH!K11,"") -> 1.3460999 | L59: =IFERROR(AH!L14/AH!L11,"") -> 2.436533 | M59: =IFERROR(AH!M14/AH!M11,"") -> 2.4910198 | N59: =IFERROR(AH!N14/AH!N11,"") -> -0.35626718 | ... AF59: =IFERROR(AH!AF14/AH!AF11,"") -> 0.79761992
A60: GAT = GAO × GAF | C60: n.d. | D60: n.d. | E60: n.d. | F60: n.d. | G60: =IFERROR(G58*G59,"") -> 3.8473239 | H60: =IFERROR(H58*H59,"") -> 6.674363 | I60: =IFERROR(I58*I59,"") -> 0.82588679 | J60: =IFERROR(J58*J59,"") -> -0.35465161 | K60: =IFERROR(K58*K59,"") -> 5.814788 | L60: =IFERROR(L58*L59,"") -> 4.5264981 | M60: =IFERROR(M58*M59,"") -> 5.1243033 | N60: =IFERROR(N58*N59,"") -> 0.75122284 | ... AF60: =IFERROR(AF58*AF59,"") -> 0.6607271
A62: Elasticidades explodem quando a variação do denominador é próxima de zero (ex.: EBIT 2022T1 +1%): ler sempre junto com a AH. Base homóloga evita a sazonalidade do T4; a versão anual está na aba AH_Anual.

Sheet Regioes
A1: Receita e assinantes por região
A2: Receita em US$ milhões; assinantes pagos em milhões (divulgação encerrada após 2024T4). Fonte: notas dos 10-Q/10-K (XBRL).
A4: Conta / indicador | B4: Fonte ou fórmula | C4: 2019T1 | D4: 2019T2 | E4: 2019T3 | F4: 2019T4 | G4: 2020T1 | H4: 2020T2 | I4: 2020T3 | J4: 2020T4 | K4: 2021T1 | L4: 2021T2 | M4: 2021T3 | N4: 2021T4 | O4: 2022T1 | P4: 2022T2 | Q4: 2022T3 | R4: 2022T4 | S4: 2023T1 | T4: 2023T2 | U4: 2023T3 | V4: 2023T4 | W4: 2024T1 | X4: 2024T2 | Y4: 2024T3 | Z4: 2024T4 | AA4: 2025T1 | AB4: 2025T2 | AC4: 2025T3 | AD4: 2025T4 | AE4: 2026T1 | AF4: 2026T2
A6: Receita por região (US$ milhões)
A7: EUA e Canadá | B7: Revenues × região | C7: 2256.851 | D7: 2501.199 | E7: 2621.25 | F7: 2671.908 | G7: 2702.776 | H7: 2839.67 | I7: 2933.445 | J7: 2979.505 | K7: 3170.972 | L7: 3234.643 | M7: 3257.697 | N7: 3308.788 | O7: 3350.424 | P7: 3537.863 | Q7: 3601.565 | R7: 3594.791 | S7: 3608.645 | T7: 3599.448 | U7: 3735.133 | V7: 3930.557 | W7: 4224.315 | X7: 4295.56 | Y7: 4322.476 | Z7: 4517.018 | AA7: 4617.098 | AB7: 4929.003 | AC7: 5071.781 | AD7: 5339.27 | AE7: 5245.298 | AF7: 5431.667
A8: Europa, Oriente Médio e África | B8: Revenues × região | C8: 1233.379 | D8: 1319.087 | E8: 1428.04 | F8: 1562.561 | G8: 1723.474 | H8: 1892.537 | I8: 2019.083 | J8: 2137.158 | K8: 2343.674 | L8: 2400.48 | M8: 2432.239 | N8: 2523.426 | O8: 2561.831 | P8: 2457.235 | Q8: 2375.814 | R8: 2350.135 | S8: 2517.641 | T8: 2562.17 | U8: 2693.146 | V8: 2783.53 | W8: 2958.193 | X8: 3007.772 | Y8: 3133.466 | Z8: 3287.604 | AA8: 3404.676 | AB8: 3538.175 | AC8: 3699.052 | AD8: 3872.743 | AE8: 3998.419 | AF8: 4033.515
A9: América Latina | B9: Revenues × região | C9: 630.472 | D9: 677.136 | E9: 741.434 | F9: 746.392 | G9: 793.453 | H9: 785.368 | I9: 789.384 | J9: 788.522 | K9: 836.647 | L9: 860.882 | M9: 915.297 | N9: 964.15 | O9: 998.948 | P9: 1030.234 | Q9: 1023.945 | R9: 1016.846 | S9: 1070.192 | T9: 1077.435 | U9: 1142.811 | V9: 1156.023 | W9: 1165.008 | X9: 1204.145 | Y9: 1240.892 | Z9: 1229.771 | AA9: 1261.934 | AB9: 1306.735 | AC9: 1370.913 | AD9: 1417.939 | AE9: 1497.058 | AF9: 1584.29
A10: Ásia-Pacífico | B10: Revenues × região | C10: 319.602 | D10: 349.494 | E10: 382.304 | F10: 418.121 | G10: 483.66 | H10: 569.14 | I10: 634.891 | J10: 684.609 | K10: 762.414 | L10: 799.48 | M10: 834.002 | N10: 870.705 | O10: 916.754 | P10: 907.719 | Q10: 889.037 | R10: 856.711 | S10: 933.523 | T10: 919.273 | U10: 948.216 | V10: 962.715 | W10: 1022.924 | X10: 1051.833 | Y10: 1127.869 | Z10: 1212.12 | AA10: 1259.093 | AB10: 1305.253 | AC10: 1368.561 | AD10: 1420.81 | AE10: 1508.982 | AF10: 1510.466
A11: DVD (encerrado em set/2023) | B11: Total − streaming | C11: =DRE!C7-C7-C8-C9-C10 -> 80.688 | D11: =DRE!D7-D7-D8-D9-D10 -> 76.2 | E11: =DRE!E7-E7-E8-E9-E10 -> 71.877 | F11: =DRE!F7-F7-F8-F9-F10 -> 68.452 | G11: =DRE!G7-G7-G8-G9-G10 -> 64.328 | H11: =DRE!H7-H7-H8-H9-H10 -> 61.571 | I11: =DRE!I7-I7-I8-I9-I10 -> 58.834 | J11: =DRE!J7-J7-J8-J9-J10 -> 54.648 | ... AF11: =DRE!AF7-AF7-AF8-AF9-AF10 -> 0
A13: Participação na receita (AV)
A14: EUA e Canadá | C14: =C7/DRE!C7 -> 0.49919376 | D14: =D7/DRE!D7 -> 0.50805201 | E14: =E7/DRE!E7 -> 0.49977073 | F14: =F7/DRE!F7 -> 0.48869506 | G14: =G7/DRE!G7 -> 0.46860624 | H14: =H7/DRE!H7 -> 0.46186368 | I14: =I7/DRE!I7 -> 0.45581269 | J14: =J7/DRE!J7 -> 0.44842065 | ... AF14: =AF7/DRE!AF7 -> 0.4324597
A15: Europa, Oriente Médio e África | C15: =C8/DRE!C7 -> 0.27281159 | D15: =D8/DRE!D7 -> 0.26793742 | E15: =E8/DRE!E7 -> 0.27227185 | F15: =F8/DRE!F7 -> 0.28579421 | G15: =G8/DRE!G7 -> 0.29881525 | H15: =H8/DRE!H7 -> 0.30781538 | I15: =I8/DRE!I7 -> 0.31373476 | J15: =J8/DRE!J7 -> 0.32164597 | ... AF15: =AF8/DRE!AF7 -> 0.32114131
A16: América Latina | C16: =C9/DRE!C7 -> 0.13945435 | D16: =D9/DRE!D7 -> 0.13754216 | E16: =E9/DRE!E7 -> 0.14136271 | F16: =F9/DRE!F7 -> 0.13651596 | G16: =G9/DRE!G7 -> 0.13756857 | H16: =H9/DRE!H7 -> 0.12773771 | I16: =I9/DRE!I7 -> 0.12265825 | J16: =J9/DRE!J7 -> 0.11867392 | ... AF16: =AF9/DRE!AF7 -> 0.12613836
A17: Ásia-Pacífico | C17: =C10/DRE!C7 -> 0.070692892 | D17: =D10/DRE!D7 -> 0.070990405 | E17: =E10/DRE!E7 -> 0.072890548 | F17: =F10/DRE!F7 -> 0.076474814 | G17: =G10/DRE!G7 -> 0.083856781 | H17: =H10/DRE!H7 -> 0.092568888 | I17: =I10/DRE!I7 -> 0.098652394 | J17: =J10/DRE!J7 -> 0.10303484 | ... AF17: =AF10/DRE!AF7 -> 0.12026063
A19: AH homóloga da receita por região (t vs t−4)
A20: EUA e Canadá | C20: n.d. | D20: n.d. | E20: n.d. | F20: n.d. | G20: =IFERROR((G7-C7)/ABS(C7),"") -> 0.19758726 | H20: =IFERROR((H7-D7)/ABS(D7),"") -> 0.1353235 | I20: =IFERROR((I7-E7)/ABS(E7),"") -> 0.11910157 | J20: =IFERROR((J7-F7)/ABS(F7),"") -> 0.1151226 | K20: =IFERROR((K7-G7)/ABS(G7),"") -> 0.17322782 | L20: =IFERROR((L7-H7)/ABS(H7),"") -> 0.13909116 | M20: =IFERROR((M7-I7)/ABS(I7),"") -> 0.11053625 | N20: =IFERROR((N7-J7)/ABS(J7),"") -> 0.11051601 | ... AF20: =IFERROR((AF7-AB7)/ABS(AB7),"") -> 0.10198087
A21: Europa, Oriente Médio e África | C21: n.d. | D21: n.d. | E21: n.d. | F21: n.d. | G21: =IFERROR((G8-C8)/ABS(C8),"") -> 0.39735961 | H21: =IFERROR((H8-D8)/ABS(D8),"") -> 0.43473251 | I21: =IFERROR((I8-E8)/ABS(E8),"") -> 0.41388406 | J21: =IFERROR((J8-F8)/ABS(F8),"") -> 0.36772772 | K21: =IFERROR((K8-G8)/ABS(G8),"") -> 0.35985457 | L21: =IFERROR((L8-H8)/ABS(H8),"") -> 0.26839264 | M21: =IFERROR((M8-I8)/ABS(I8),"") -> 0.20462557 | N21: =IFERROR((N8-J8)/ABS(J8),"") -> 0.18073909 | ... AF21: =IFERROR((AF8-AB8)/ABS(AB8),"") -> 0.13999873
A22: América Latina | C22: n.d. | D22: n.d. | E22: n.d. | F22: n.d. | G22: =IFERROR((G9-C9)/ABS(C9),"") -> 0.25850633 | H22: =IFERROR((H9-D9)/ABS(D9),"") -> 0.15983791 | I22: =IFERROR((I9-E9)/ABS(E9),"") -> 0.064671974 | J22: =IFERROR((J9-F9)/ABS(F9),"") -> 0.056444871 | K22: =IFERROR((K9-G9)/ABS(G9),"") -> 0.054438007 | L22: =IFERROR((L9-H9)/ABS(H9),"") -> 0.096151104 | M22: =IFERROR((M9-I9)/ABS(I9),"") -> 0.15950792 | N22: =IFERROR((N9-J9)/ABS(J9),"") -> 0.22273063 | ... AF22: =IFERROR((AF9-AB9)/ABS(AB9),"") -> 0.21240343
A23: Ásia-Pacífico | C23: n.d. | D23: n.d. | E23: n.d. | F23: n.d. | G23: =IFERROR((G10-C10)/ABS(C10),"") -> 0.51331969 | H23: =IFERROR((H10-D10)/ABS(D10),"") -> 0.62846859 | I23: =IFERROR((I10-E10)/ABS(E10),"") -> 0.66069672 | J23: =IFERROR((J10-F10)/ABS(F10),"") -> 0.63734661 | K23: =IFERROR((K10-G10)/ABS(G10),"") -> 0.57634289 | L23: =IFERROR((L10-H10)/ABS(H10),"") -> 0.40471589 | M23: =IFERROR((M10-I10)/ABS(I10),"") -> 0.31361446 | N23: =IFERROR((N10-J10)/ABS(J10),"") -> 0.27182815 | ... AF23: =IFERROR((AF10-AB10)/ABS(AB10),"") -> 0.15722086
A25: Assinantes pagos (milhões, fim do trimestre)
A26: EUA e Canadá | B26: NumberOfPaidMemberships | C26: 66.633 | D26: 66.501 | E26: 67.114 | F26: 67.662 | G26: 69.969 | H26: 72.904 | I26: 73.081 | J26: 73.936 | K26: 74.384 | L26: 73.951 | M26: 74.024 | N26: 75.215 | O26: 74.579 | P26: 73.283 | Q26: 73.387 | R26: 74.296 | S26: 74.398 | T26: 75.571 | U26: 77.321 | V26: 80.128 | W26: 82.658 | X26: 84.109 | Y26: 84.803 | Z26: 89.625
A27: Europa, Oriente Médio e África | B27: NumberOfPaidMemberships | C27: 42.542 | D27: 44.229 | E27: 47.355 | F27: 51.778 | G27: 58.734 | H27: 61.483 | I27: 62.242 | J27: 66.698 | K27: 68.508 | L27: 68.696 | M27: 70.5 | N27: 74.036 | O27: 73.733 | P27: 72.966 | Q27: 73.534 | R27: 76.729 | S27: 77.373 | T27: 79.807 | U27: 83.76 | V27: 88.813 | W27: 91.729 | X27: 93.964 | Y27: 96.131 | Z27: 101.133
A28: América Latina | B28: NumberOfPaidMemberships | C28: 27.547 | D28: 27.89 | E28: 29.38 | F28: 31.417 | G28: 34.318 | H28: 36.068 | I28: 36.324 | J28: 37.537 | K28: 37.894 | L28: 38.658 | M28: 38.988 | N28: 39.961 | O28: 39.61 | P28: 39.624 | Q28: 39.936 | R28: 41.699 | S28: 41.249 | T28: 42.466 | U28: 43.645 | V28: 45.997 | W28: 47.72 | X28: 49.25 | Y28: 49.182 | Z28: 53.327
A29: Ásia-Pacífico | B29: NumberOfPaidMemberships | C29: 12.141 | D29: 12.942 | E29: 14.485 | F29: 16.233 | G29: 19.835 | H29: 22.492 | I29: 23.504 | J29: 25.492 | K29: 26.853 | L29: 27.875 | M29: 30.051 | N29: 32.632 | O29: 33.719 | P29: 34.799 | Q29: 36.228 | R29: 38.023 | S29: 39.478 | T29: 40.546 | U29: 42.427 | V29: 45.338 | W29: 47.495 | X29: 50.324 | Y29: 52.604 | Z29: 57.541
A30: Total | C30: =IF(COUNT(C26,C27,C28,C29)=4,C26+C27+C28+C29,"") -> 148.863 | D30: =IF(COUNT(D26,D27,D28,D29)=4,D26+D27+D28+D29,"") -> 151.562 | E30: =IF(COUNT(E26,E27,E28,E29)=4,E26+E27+E28+E29,"") -> 158.334 | F30: =IF(COUNT(F26,F27,F28,F29)=4,F26+F27+F28+F29,"") -> 167.09 | G30: =IF(COUNT(G26,G27,G28,G29)=4,G26+G27+G28+G29,"") -> 182.856 | H30: =IF(COUNT(H26,H27,H28,H29)=4,H26+H27+H28+H29,"") -> 192.947 | I30: =IF(COUNT(I26,I27,I28,I29)=4,I26+I27+I28+I29,"") -> 195.151 | J30: =IF(COUNT(J26,J27,J28,J29)=4,J26+J27+J28+J29,"") -> 203.663 | ... AF30: =IF(COUNT(AF26,AF27,AF28,AF29)=4,AF26+AF27+AF28+AF29,"")
A31: Adições líquidas no trimestre | C31: n.d. | D31: =IFERROR(IF(D30="","",D30-C30),"") -> 2.699 | E31: =IFERROR(IF(E30="","",E30-D30),"") -> 6.772 | F31: =IFERROR(IF(F30="","",F30-E30),"") -> 8.756 | G31: =IFERROR(IF(G30="","",G30-F30),"") -> 15.766 | H31: =IFERROR(IF(H30="","",H30-G30),"") -> 10.091 | I31: =IFERROR(IF(I30="","",I30-H30),"") -> 2.204 | J31: =IFERROR(IF(J30="","",J30-I30),"") -> 8.512 | K31: =IFERROR(IF(K30="","",K30-J30),"") -> 3.976 | ... AF31: =IFERROR(IF(AF30="","",AF30-AE30),"")
A33: ARM — receita média mensal por assinante (US$/mês) = receita / média de assinantes / 3
A34: EUA e Canadá | C34: n.d. | D34: =IFERROR(D7/AVERAGE(D26,C26)/3,"") -> 12.524719 | E34: =IFERROR(E7/AVERAGE(E26,D26)/3,"") -> 13.078621 | F34: =IFERROR(F7/AVERAGE(F26,E26)/3,"") -> 13.216537 | G34: =IFERROR(G7/AVERAGE(G26,F26)/3,"") -> 13.091895 | H34: =IFERROR(H7/AVERAGE(H26,G26)/3,"") -> 13.250323 | I34: =IFERROR(I7/AVERAGE(I26,H26)/3,"") -> 13.396102 | J34: =IFERROR(J7/AVERAGE(J26,I26)/3,"") -> 13.510932 | K34: =IFERROR(K7/AVERAGE(K26,J26)/3,"") -> 14.252841 | ... AF34: =IFERROR(AF7/AVERAGE(AF26,AE26)/3,"")
A35: Europa, Oriente Médio e África | C35: n.d. | D35: =IFERROR(D8/AVERAGE(D27,C27)/3,"") -> 10.134623 | E35: =IFERROR(E8/AVERAGE(E27,D27)/3,"") -> 10.39512 | F35: =IFERROR(F8/AVERAGE(F27,E27)/3,"") -> 10.508179 | G35: =IFERROR(G8/AVERAGE(G27,F27)/3,"") -> 10.396904 | H35: =IFERROR(H8/AVERAGE(H27,G27)/3,"") -> 10.495116 | I35: =IFERROR(I8/AVERAGE(I27,H27)/3,"") -> 10.879413 | J35: =IFERROR(J8/AVERAGE(J27,I27)/3,"") -> 11.049884 | K35: =IFERROR(K8/AVERAGE(K27,J27)/3,"") -> 11.556065 | ... AF35: =IFERROR(AF8/AVERAGE(AF27,AE27)/3,"")
A36: América Latina | C36: n.d. | D36: =IFERROR(D9/AVERAGE(D28,C28)/3,"") -> 8.1430092 | E36: =IFERROR(E9/AVERAGE(E28,D28)/3,"") -> 8.6308597 | F36: =IFERROR(F9/AVERAGE(F28,E28)/3,"") -> 8.1845266 | G36: =IFERROR(G9/AVERAGE(G28,F28)/3,"") -> 8.0469866 | H36: =IFERROR(H9/AVERAGE(H28,G28)/3,"") -> 7.4386763 | I36: =IFERROR(I9/AVERAGE(I28,H28)/3,"") -> 7.2695325 | J36: =IFERROR(J9/AVERAGE(J28,I28)/3,"") -> 7.1171705 | K36: =IFERROR(K9/AVERAGE(K28,J28)/3,"") -> 7.3943692 | ... AF36: =IFERROR(AF9/AVERAGE(AF28,AE28)/3,"")
A37: Ásia-Pacífico | C37: n.d. | D37: =IFERROR(D10/AVERAGE(D29,C29)/3,"") -> 9.2890005 | E37: =IFERROR(E10/AVERAGE(E29,D29)/3,"") -> 9.2926435 | F37: =IFERROR(F10/AVERAGE(F29,E29)/3,"") -> 9.0743972 | G37: =IFERROR(G10/AVERAGE(G29,F29)/3,"") -> 8.9397804 | H37: =IFERROR(H10/AVERAGE(H29,G29)/3,"") -> 8.9641757 | I37: =IFERROR(I10/AVERAGE(I29,H29)/3,"") -> 9.202119 | J37: =IFERROR(J10/AVERAGE(J29,I29)/3,"") -> 9.3151686 | K37: =IFERROR(K10/AVERAGE(K29,J29)/3,"") -> 9.7101156 | ... AF37: =IFERROR(AF10/AVERAGE(AF29,AE29)/3,"")
A39: A Netflix deixou de divulgar assinantes a partir de 2025 (anúncio na carta do 1º tri/2024); carta do 4º tri/2025 cita "325 milhões".

Sheet Macro
A1: Contexto macroeconômico (médias trimestrais)
A2: Fontes oficiais: Federal Reserve (H.15), U.S. Treasury, BLS (CPI-U e desemprego), Banco Central Europeu (câmbio).
A4: Conta / indicador | B4: Fonte ou fórmula | C4: 2019T1 | D4: 2019T2 | E4: 2019T3 | F4: 2019T4 | G4: 2020T1 | H4: 2020T2 | I4: 2020T3 | J4: 2020T4 | K4: 2021T1 | L4: 2021T2 | M4: 2021T3 | N4: 2021T4 | O4: 2022T1 | P4: 2022T2 | Q4: 2022T3 | R4: 2022T4 | S4: 2023T1 | T4: 2023T2 | U4: 2023T3 | V4: 2023T4 | W4: 2024T1 | X4: 2024T2 | Y4: 2024T3 | Z4: 2024T4 | AA4: 2025T1 | AB4: 2025T2 | AC4: 2025T3 | AD4: 2025T4 | AE4: 2026T1 | AF4: 2026T2
A6: Estados Unidos
A7: Juro básico — Fed Funds efetivo (% a.a.) | B7: Fed H.15 | C7: 0.024018 | D7: 0.023974 | E7: 0.021922 | F7: 0.016457 | G7: 0.012549 | H7: 0.000588 | I7: 0.000926 | J7: 0.000888 | K7: 0.000769 | L7: 0.000682 | M7: 0.0009 | N7: 0.000795 | O7: 0.001214 | P7: 0.007668 | Q7: 0.021829 | R7: 0.036534 | S7: 0.045146 | T7: 0.049881 | U7: 0.052592 | V7: 0.0533 | W7: 0.0533 | X7: 0.0533 | Y7: 0.052648 | Z7: 0.046479 | AA7: 0.0433 | AB7: 0.0433 | AC7: 0.042957 | AD7: 0.038952 | AE7: 0.0364 | AF7: 0.03631
A8: Título do Tesouro de 10 anos (% a.a.) | B8: U.S. Treasury | C8: 0.02653 | D8: 0.023389 | E8: 0.01798 | F8: 0.017919 | G8: 0.01365 | H8: 0.006876 | I8: 0.006506 | J8: 0.008645 | K8: 0.013359 | L8: 0.015908 | M8: 0.013248 | N8: 0.015334 | O8: 0.019511 | P8: 0.029326 | Q8: 0.031011 | R8: 0.038267 | S8: 0.036463 | T8: 0.035957 | U8: 0.041497 | V8: 0.044471 | W8: 0.041564 | X8: 0.044487 | Y8: 0.039547 | Z8: 0.042755 | AA8: 0.044536 | AB8: 0.043618 | AC8: 0.042611 | AD8: 0.041 | AE8: 0.041979 | AF8: 0.044219
A9: Inflação ao consumidor CPI-U (% em 12 meses) | B9: BLS CUUR0000SA0 | C9: 0.016446 | D9: 0.018117 | E9: 0.017575 | F9: 0.020335 | G9: 0.021203 | H9: 0.003643 | I9: 0.012224 | J9: 0.012395 | K9: 0.018986 | L9: 0.04848 | M9: 0.053357 | N9: 0.066891 | O9: 0.079645 | P9: 0.086333 | Q9: 0.083297 | R9: 0.071034 | S9: 0.058102 | T9: 0.039824 | U9: 0.035142 | V9: 0.032435 | W9: 0.032405 | X9: 0.031993 | Y9: 0.02622 | Z9: 0.027451 | AA9: 0.027376 | AB9: 0.024451 | AC9: 0.028779 | AD9: 0.027061 | AE9: 0.026857 | AF9: 0.038636
A10: Taxa de desemprego (%) | B10: BLS LNS14000000 | C10: 0.038667 | D10: 0.036333 | E10: 0.036 | F10: 0.036 | G10: 0.038333 | H10: 0.13 | I10: 0.088 | J10: 0.067667 | K10: 0.062333 | L10: 0.059333 | M10: 0.050667 | N10: 0.041667 | O10: 0.038667 | P10: 0.036333 | Q10: 0.035333 | R10: 0.035667 | S10: 0.035333 | T10: 0.035333 | U10: 0.036333 | V10: 0.038 | W10: 0.038333 | X10: 0.039667 | Y10: 0.041667 | Z10: 0.041333 | AA10: 0.041333 | AB10: 0.042 | AC10: 0.043333 | AD10: 0.0445 | AE10: 0.043333 | AF10: 0.042667
A12: Câmbio — unidades de moeda local por 1 US$ (alta = dólar mais forte = receita em US$ menor)
A13: Euro | B13: BCE (via EUR) | C13: 0.8806 | D13: 0.8898 | E13: 0.8996 | F13: 0.9032 | G13: 0.9073 | H13: 0.9088 | I13: 0.8553 | J13: 0.8386 | K13: 0.8295 | L13: 0.8294 | M13: 0.8483 | N13: 0.8742 | O13: 0.891 | P13: 0.9387 | Q13: 0.9932 | R13: 0.9808 | S13: 0.932 | T13: 0.9182 | U13: 0.919 | V13: 0.9297 | W13: 0.9211 | X13: 0.9288 | Y13: 0.9102 | Z13: 0.9374 | AA13: 0.9505 | AB13: 0.8823 | AC13: 0.8562 | AD13: 0.8596 | AE13: 0.8543 | AF13: 0.8597
A14: Real brasileiro | B14: BCE (via EUR) | C14: 3.766 | D14: 3.9193 | E14: 3.9704 | F14: 4.1188 | G14: 4.4551 | H14: 5.3834 | I14: 5.3757 | J14: 5.4006 | K14: 5.4697 | L14: 5.3007 | M14: 5.2252 | N14: 5.5798 | O14: 5.2378 | P14: 4.9136 | Q14: 5.25 | R14: 5.2619 | S14: 5.1947 | T14: 4.951 | U14: 4.8795 | V14: 4.9555 | W14: 4.9517 | X14: 5.2134 | Y14: 5.5449 | Z14: 5.8372 | AA14: 5.8554 | AB14: 5.6651 | AC14: 5.4528 | AD14: 5.3909 | AE14: 5.2591 | AF14: 5.044
A15: Peso mexicano | B15: BCE (via EUR) | C15: 19.1992 | D15: 19.1335 | E15: 19.4302 | F15: 19.2593 | G15: 19.9947 | H15: 23.3354 | I15: 22.0901 | J15: 20.5496 | K15: 20.3388 | L15: 20.0087 | M15: 20.0208 | N15: 20.7361 | O15: 20.4955 | P15: 20.0324 | Q15: 20.2418 | R15: 19.6837 | S15: 18.681 | T15: 17.686 | U15: 17.0629 | V15: 17.5555 | W15: 16.9872 | X15: 17.2686 | Y15: 18.9503 | Z15: 20.0927 | AA15: 20.4307 | AB15: 19.5168 | AC15: 18.6398 | AD15: 18.3119 | AE15: 17.5522 | AF15: 17.3703
A16: Libra esterlina | B16: BCE (via EUR) | C16: 0.7681 | D16: 0.7784 | E16: 0.8114 | F16: 0.7768 | G16: 0.7816 | H16: 0.806 | I16: 0.774 | J16: 0.7574 | K16: 0.7255 | L16: 0.7151 | M16: 0.7256 | N16: 0.7412 | O16: 0.7453 | P16: 0.796 | Q16: 0.8507 | R16: 0.853 | S16: 0.8231 | T16: 0.7988 | U16: 0.7901 | V16: 0.8058 | W16: 0.7886 | X16: 0.7922 | Y16: 0.7692 | Z16: 0.7801 | AA16: 0.7943 | AB16: 0.7491 | AC16: 0.7417 | AD16: 0.7526 | AE16: 0.7418 | AF16: 0.7447
A17: Iene | B17: BCE (via EUR) | C17: 110.1579 | D17: 109.8802 | E17: 107.2971 | F17: 108.7058 | G17: 108.9553 | H17: 107.5021 | I17: 106.119 | J17: 104.4649 | K17: 105.9648 | L17: 109.3906 | M17: 110.0806 | N17: 113.6805 | O17: 116.2423 | P17: 129.682 | Q17: 138.2636 | R17: 141.4781 | S17: 132.3215 | T17: 137.3014 | U17: 144.5043 | V17: 147.8513 | W17: 148.478 | X17: 155.8477 | Y17: 149.1127 | Z17: 152.3146 | AA17: 152.4494 | AB17: 144.475 | AC17: 147.5058 | AD17: 154.1459 | AE17: 156.8419 | AF17: 159.3382
A18: Índice do dólar vs. cesta das 5 moedas (2019T4 = 100) | B18: Média simples das 5 moedas | C18: 97.7657 | D18: 98.8623 | E18: 100.0106 | F18: 100 | G18: 102.6569 | H18: 111.0292 | I18: 107.434 | J18: 104.8537 | K18: 104.2248 | L18: 103.4208 | M18: 103.8821 | N18: 107.9869 | O18: 107.0227 | P18: 109.8032 | Q18: 115.8458 | R18: 115.701 | S18: 110.7984 | T18: 108.5663 | U18: 108.6912 | V18: 110.8299 | W18: 109.7021 | X18: 112.8856 | Y18: 113.9973 | Z18: 118.0748 | AA18: 119.1948 | AB18: 113.1793 | AC18: 111.0276 | AD18: 111.967 | AE18: 110.6353 | AF18: 110.0568
A20: Ligação com a Netflix
A21: Variação do índice do dólar em 12 meses | C21: n.d. | D21: n.d. | E21: n.d. | F21: n.d. | G21: =IFERROR(G18/C18-1,"") -> 0.050029816 | H21: =IFERROR(H18/D18-1,"") -> 0.12306916 | I21: =IFERROR(I18/E18-1,"") -> 0.074226132 | J21: =IFERROR(J18/F18-1,"") -> 0.048537 | K21: =IFERROR(K18/G18-1,"") -> 0.015273206 | L21: =IFERROR(L18/H18-1,"") -> -0.068526117 | M21: =IFERROR(M18/I18-1,"") -> -0.033061228 | N21: =IFERROR(N18/J18-1,"") -> 0.029881635 | ... AF21: =IFERROR(AF18/AB18-1,"") -> -0.027588967
A22: Netflix: crescimento da receita em 12 meses (AH homóloga) | C22: n.d. | D22: n.d. | E22: n.d. | F22: n.d. | G22: =AH!G7 -> 0.27575784 | H22: =AH!H7 -> 0.24886068 | I22: =AH!I7 -> 0.22702642 | J22: =AH!J7 -> 0.21527612 | K22: =AH!K7 -> 0.24196702 | L22: =AH!L7 -> 0.19411768 | M22: =AH!M7 -> 0.16281683 | N22: =AH!N7 -> 0.16026568 | ... AF22: =AH!AF7 -> 0.13365374
A23: Netflix: crescimento da receita EMEA em 12 meses | C23: n.d. | D23: n.d. | E23: n.d. | F23: n.d. | G23: =Regioes!G21 -> 0.39735961 | H23: =Regioes!H21 -> 0.43473251 | I23: =Regioes!I21 -> 0.41388406 | J23: =Regioes!J21 -> 0.36772772 | K23: =Regioes!K21 -> 0.35985457 | L23: =Regioes!L21 -> 0.26839264 | M23: =Regioes!M21 -> 0.20462557 | N23: =Regioes!N21 -> 0.18073909 | ... AF23: =Regioes!AF21 -> 0.13999873
A24: Netflix: despesa de juros (US$ mi) | C24: =DRE!C15 -> 135.529 | D24: =DRE!D15 -> 152.033 | E24: =DRE!E15 -> 160.66 | F24: =DRE!F15 -> 177.801 | G24: =DRE!G15 -> 184.083 | H24: =DRE!H15 -> 189.151 | I24: =DRE!I15 -> 197.079 | J24: =DRE!J15 -> 197.186 | ... AF24: =DRE!AF15 -> 175.685
A26: Leitura: dólar forte (2022, 2024T4-2025T1) reduz a receita convertida; juros altos (2023-24) não elevaram a despesa de juros porque a dívida é de taxa fixa.
A28: CPI de out/2025 não foi coletado pelo BLS (paralisação do governo dos EUA); a média do 4º tri/2025 usa os meses disponíveis.

Sheet Setor
A1: Análise setorial — streaming e mídia (dados anuais, SEC EDGAR)
A2: US$ milhões · Disney: ano fiscal termina em set/out · Netflix, WBD, Paramount e Comcast: ano-calendário
A4: Receita (US$ mi) | B4: 2019 | C4: 2020 | D4: 2021 | E4: 2022 | F4: 2023 | G4: 2024 | H4: 2025
A5: Netflix | B5: 20156.45 | C5: 24996.06 | D5: 29697.84 | E5: 31615.55 | F5: 33723.3 | G5: 39000.97 | H5: 45183.04
A6: Disney | B6: 69607 | C6: 65388 | D6: 67418 | E6: 82722 | F6: 88898 | G6: 91361 | H6: 94425
A7: Warner Bros. Discovery | B7: 11144 | C7: 10671 | D7: 12191 | E7: 33817 | F7: 41321 | G7: 39321 | H7: 37296
A8: Paramount Global | B8: 26998 | C8: 25285 | D8: 28586 | E8: 30154 | F8: 29652 | G8: 29213
A9: Comcast (NBCU/Peacock) | B9: 108942 | C9: 103564 | D9: 116385 | E9: 121427 | F9: 121572 | G9: 123731 | H9: 123707
A11: Lucro operacional (US$ mi) | B11: 2019 | C11: 2020 | D11: 2021 | E11: 2022 | F11: 2023 | G11: 2024 | H11: 2025
A12: Netflix | B12: 2604.25 | C12: 4585.29 | D12: 6194.51 | E12: 5632.83 | F12: 6954 | G12: 10417.61 | H12: 13326.6
A13: Disney | B13: 14847 | C13: 8108 | D13: 7766 | E13: 12121 | F13: 12863 | G13: 15601 | H13: 17551
A14: Warner Bros. Discovery | B14: 3009 | C14: 2515 | D14: 2012 | E14: -7370 | F14: -1548 | G14: -10032 | H14: 738
A15: Paramount Global | B15: 4146 | C15: 4139 | D15: 6297 | E15: 2342 | F15: -451 | G15: -5269
A16: Comcast (NBCU/Peacock) | B16: 21125 | C16: 17493 | D16: 20817 | E16: 14041 | F16: 23314 | G16: 23297 | H16: 20672
A18: Crescimento da receita (AH anual) | B18: 2019 | C18: 2020 | D18: 2021 | E18: 2022 | F18: 2023 | G18: 2024 | H18: 2025
A19: Netflix | C19: =IFERROR((C5-B5)/ABS(B5),"") -> 0.2401023 | D19: =IFERROR((D5-C5)/ABS(C5),"") -> 0.18810084 | E19: =IFERROR((E5-D5)/ABS(D5),"") -> 0.064574057 | F19: =IFERROR((F5-E5)/ABS(E5),"") -> 0.066668143 | G19: =IFERROR((G5-F5)/ABS(F5),"") -> 0.15649922 | H19: =IFERROR((H5-G5)/ABS(G5),"") -> 0.15851067
A20: Disney | C20: =IFERROR((C6-B6)/ABS(B6),"") -> -0.06061172 | D20: =IFERROR((D6-C6)/ABS(C6),"") -> 0.031045452 | E20: =IFERROR((E6-D6)/ABS(D6),"") -> 0.22700169 | F20: =IFERROR((F6-E6)/ABS(E6),"") -> 0.074659704 | G20: =IFERROR((G6-F6)/ABS(F6),"") -> 0.02770591 | H20: =IFERROR((H6-G6)/ABS(G6),"") -> 0.033537286
A21: Warner Bros. Discovery | C21: =IFERROR((C7-B7)/ABS(B7),"") -> -0.042444365 | D21: =IFERROR((D7-C7)/ABS(C7),"") -> 0.14244213 | E21: =IFERROR((E7-D7)/ABS(D7),"") -> 1.7739316 | F21: =IFERROR((F7-E7)/ABS(E7),"") -> 0.22190023 | G21: =IFERROR((G7-F7)/ABS(F7),"") -> -0.048401539 | H21: =IFERROR((H7-G7)/ABS(G7),"") -> -0.051499199
A22: Paramount Global | C22: =IFERROR((C8-B8)/ABS(B8),"") -> -0.063449144 | D22: =IFERROR((D8-C8)/ABS(C8),"") -> 0.13055171 | E22: =IFERROR((E8-D8)/ABS(D8),"") -> 0.054852025 | F22: =IFERROR((F8-E8)/ABS(E8),"") -> -0.016647874 | G22: =IFERROR((G8-F8)/ABS(F8),"") -> -0.014805072 | H22: =IFERROR((H8-G8)/ABS(G8),"") -> -1
A23: Comcast (NBCU/Peacock) | C23: =IFERROR((C9-B9)/ABS(B9),"") -> -0.049365718 | D23: =IFERROR((D9-C9)/ABS(C9),"") -> 0.12379784 | E23: =IFERROR((E9-D9)/ABS(D9),"") -> 0.043321734 | F23: =IFERROR((F9-E9)/ABS(E9),"") -> 0.0011941331 | G23: =IFERROR((G9-F9)/ABS(F9),"") -> 0.017759023 | H23: =IFERROR((H9-G9)/ABS(G9),"") -> -0.00019396918
A25: Margem operacional (AV: EBIT / Receita) | B25: 2019 | C25: 2020 | D25: 2021 | E25: 2022 | F25: 2023 | G25: 2024 | H25: 2025
A26: Netflix | B26: =IFERROR(B12/B5,"") -> 0.12920182 | C26: =IFERROR(C12/C5,"") -> 0.18344051 | D26: =IFERROR(D12/D5,"") -> 0.20858453 | E26: =IFERROR(E12/E5,"") -> 0.17816644 | F26: =IFERROR(F12/F5,"") -> 0.20620758 | G26: =IFERROR(G12/G5,"") -> 0.26711156 | H26: =IFERROR(H12/H5,"") -> 0.29494695
A27: Disney | B27: =IFERROR(B13/B6,"") -> 0.21329751 | C27: =IFERROR(C13/C6,"") -> 0.12399829 | D27: =IFERROR(D13/D6,"") -> 0.11519179 | E27: =IFERROR(E13/E6,"") -> 0.14652692 | F27: =IFERROR(F13/F6,"") -> 0.14469392 | G27: =IFERROR(G13/G6,"") -> 0.17076214 | H27: =IFERROR(H13/H6,"") -> 0.18587239
A28: Warner Bros. Discovery | B28: =IFERROR(B14/B7,"") -> 0.27001077 | C28: =IFERROR(C14/C7,"") -> 0.2356855 | D28: =IFERROR(D14/D7,"") -> 0.16503978 | E28: =IFERROR(E14/E7,"") -> -0.21793772 | F28: =IFERROR(F14/F7,"") -> -0.037462791 | G28: =IFERROR(G14/G7,"") -> -0.25513085 | H28: =IFERROR(H14/H7,"") -> 0.019787645
A29: Paramount Global | B29: =IFERROR(B15/B8,"") -> 0.15356693 | C29: =IFERROR(C15/C8,"") -> 0.16369389 | D29: =IFERROR(D15/D8,"") -> 0.22028266 | E29: =IFERROR(E15/E8,"") -> 0.077667971 | F29: =IFERROR(F15/F8,"") -> -0.015209767 | G29: =IFERROR(G15/G8,"") -> -0.18036491 | H29: =IFERROR(H15/H8,"")
A30: Comcast (NBCU/Peacock) | B30: =IFERROR(B16/B9,"") -> 0.19391052 | C30: =IFERROR(C16/C9,"") -> 0.16891005 | D30: =IFERROR(D16/D9,"") -> 0.17886326 | E30: =IFERROR(E16/E9,"") -> 0.11563326 | F30: =IFERROR(F16/F9,"") -> 0.19177113 | G30: =IFERROR(G16/G9,"") -> 0.18828749 | H30: =IFERROR(H16/H9,"") -> 0.16710453
A32: WBD 2022: fusão Discovery + WarnerMedia (abr/2022) explica o salto de receita — não é crescimento orgânico. Prejuízos operacionais de WBD e Paramount incluem baixas contábeis (impairments) de TV linear.
A33: ATENÇÃO — Disney: a linha de lucro operacional acima é o "lucro operacional dos segmentos" (a Disney não divulga uma linha de resultado operacional GAAP). Para comparar com as demais, use a linha reconstruída abaixo.
A34: Disney — resultado operacional comparável (US$ mi) | B34: 11082 | C34: -1290 | D34: 3766 | E34: 7349 | F34: 5882 | G34: 8894 | H34: 13510
A35: Disney — margem operacional comparável | B35: =IFERROR(B34/B6,"") -> 0.15920813 | C35: =IFERROR(C34/C6,"") -> -0.019728391 | D35: =IFERROR(D34/D6,"") -> 0.055860453 | E35: =IFERROR(E34/E6,"") -> 0.088839728 | F35: =IFERROR(F34/F6,"") -> 0.066165718 | G35: =IFERROR(G34/G6,"") -> 0.097350073 | H35: =IFERROR(H34/H6,"") -> 0.14307652
A36: Fonte: reconciliação "segment operating income" → resultado antes de juros nos 10-K da Disney (AF2020, AF2022, AF2024, AF2025): lucro dos segmentos − despesas corporativas − reestruturação e impairments − amortização TFCF/Hulu.
A38: Resultado dos negócios de streaming dos concorrentes (US$ milhões) — enquanto a Netflix lucrava, os rivais perdiam
A39: Empresa | B39: Ano fiscal | C39: Métrica | D39: Valor (US$ mi) | E39: Fonte (documento SEC) | F39: Nota
A40: Disney (Disney+, Hulu) | B40: 2020 | C40: Resultado operacional do segmento DTC | D40: -2913 | E40: 10-K DIS 0001744489-21-000220 (MD&A) | F40: Definição antiga do segmento (incluía ESPN+); não reapresentada
A41: Disney (Disney+, Hulu) | B41: 2021 | C41: Resultado operacional do segmento DTC | D41: -1252 | E41: 10-K DIS 0001744489-23-000216 (MD&A)
A42: Disney (Disney+, Hulu) | B42: 2022 | C42: Resultado operacional do segmento DTC | D42: -3424 | E42: 10-K DIS 0001744489-23-000216 (MD&A)
A43: Disney (Disney+, Hulu) | B43: 2023 | C43: Resultado operacional do segmento DTC | D43: -2496 | E43: 10-K DIS 0001744489-24-000276 (MD&A)
A44: Disney (Disney+, Hulu) | B44: 2024 | C44: Resultado operacional do segmento DTC | D44: 143 | E44: 10-K DIS 0001744489-25-000155 (MD&A)
A45: Disney (Disney+, Hulu) | B45: 2025 | C45: Resultado operacional do segmento DTC | D45: 1327 | E45: 10-K DIS 0001744489-25-000155 (MD&A)
A46: Paramount (Paramount+, Pluto TV) | B46: 2021 | C46: Adjusted OIBDA do segmento DTC | D46: -992 | E46: 10-K PARA 0000813828-23-000005 (MD&A)
A47: Paramount (Paramount+, Pluto TV) | B47: 2022 | C47: Adjusted OIBDA do segmento DTC | D47: -1819 | E47: 10-K PARA 0000813828-24-000007 (MD&A)
A48: Paramount (Paramount+, Pluto TV) | B48: 2023 | C48: Adjusted OIBDA do segmento DTC | D48: -1663 | E48: 10-K PARA 0000813828-25-000005 (MD&A)
A49: Paramount (Paramount+, Pluto TV) | B49: 2024 | C49: Adjusted OIBDA do segmento DTC | D49: -497 | E49: 10-K PARA 0000813828-25-000005 (MD&A) | F49: Último 10-K da Paramount Global antes da fusão com a Skydance (ago/2025)
A50: Warner Bros. Discovery (Max/HBO Max) | B50: 2022 | C50: Adjusted EBITDA do segmento DTC/Streaming | D50: -1596 | E50: 10-K WBD 0001437107-23-000019 (MD&A) | F50: Inclui WarnerMedia (HBO Max) só a partir de 08/04/2022 (fusão)
A51: Warner Bros. Discovery (Max/HBO Max) | B51: 2023 | C51: Adjusted EBITDA do segmento DTC/Streaming | D51: 103 | E51: 10-K WBD 0001437107-26-000020 (XBRL)
A52: Warner Bros. Discovery (Max/HBO Max) | B52: 2024 | C52: Adjusted EBITDA do segmento DTC/Streaming | D52: 677 | E52: 10-K WBD 0001437107-26-000020 (XBRL)
A53: Warner Bros. Discovery (Max/HBO Max) | B53: 2025 | C53: Adjusted EBITDA do segmento DTC/Streaming | D53: 1370 | E53: 10-K WBD 0001437107-26-000020 (XBRL)
A55: Netflix (para comparação): EBIT anual na tabela acima — US$ 4,6 bi (2020) → US$ 13,3 bi (2025).

Sheet Variacoes_Bruscas
A1: Variações bruscas — "perguntas ruins" e as respostas oficiais
A2: Cada resposta é sustentada por um trecho do documento arquivado na SEC (10-Q, 10-K ou carta aos acionistas, Ex. 99.1 do 8-K).
A4: Trimestre | B4: Indicador | C4: Pergunta ruim | D4: Resposta | E4: Trecho oficial (inglês) | F4: Documento | G4: Accession SEC
A5: 2020T2 | B5: FCO e FCL | C5: Como o caixa operacional saltou de US$ 0,26 bi para US$ 1,04 bi no meio da pandemia? | D5: As produções pararam (Covid-19): o gasto de caixa com conteúdo caiu 24% no trimestre e ficou abaixo da amortização (0,96x), enquanto o confinamento trouxe 26 milhões de novos assinantes no 1º semestre. | E5: dollar) remains a wildcard. As always, our intention is to grow our annual operating margin year over year - we’re currently targeting 19% for 2021. Content As the world slowly re-opens, our main business priority is to restart our productions safely and in a manner consistent with local health and safety standards to ensure that our members can enjoy a diverse range of high quality new content. Given the significant differences between countries (e.g., incid | F5: Carta aos acionistas (8-K, Ex. 99.1) q220 | G5: 0001065280-20-000306
A6: 2021T2-2021T4 | B6: FCL negativo | C6: Por que a Netflix lucrou US$ 5,1 bi em 2021 e mesmo assim queimou caixa? | D6: Com a retomada das produções, o pagamento de conteúdo superou a amortização contábil em US$ 5,2 bi. Lucro (competência) e caixa se descolaram: o conteúdo é pago antes e amortizado ao longo de anos. | E6: rchases of common stock for an aggregate amount of $600 million in the year ended December 31, 2021 and repayment upon maturity of the $500 million aggregate principal amount of our 5.375% Senior Notes in February 2021. Free cash flow was $5,275 million lower than net income for the year ended December 31, 2021 primarily due to $5,239 million of cash payments for content assets over amortization expense, $431 million of non-cash remeasurement gain on our euro-denominated deb | F6: 10-K 2021-12-31 | G6: 0001065280-22-000036
A7: Todo T4 | B7: Margem operacional | C7: Por que a margem operacional despenca em todo 4º trimestre (8% em 2021T4, 7% em 2022T4)? | D7: Sazonalidade planejada: a Netflix concentra os grandes lançamentos (e a amortização e o marketing deles) no fim do ano. Por isso a comparação correta é contra o mesmo trimestre do ano anterior (AH homóloga). | E7: er year on both a reported and foreign exchange (F/X) neutral basis, two percentage points faster than Q3’21 (ex-F/X). Operating margin for Q4 amounted to 8%, a six percentage point decrease vs. the year ago period. The decline in operating margin was expected given our large content slate in Q4 this year. Operating margin was above our beginning of quarter forecast of 6.5% due to slightly lower than forecasted content spend. As a result, our full year operating margin was 21 | F7: Carta aos acionistas (8-K, Ex. 99.1) q421 | G7: 0001065280-22-000035
A8: 2022T1-2022T2 | B8: Assinantes | C8: Por que a Netflix perdeu assinantes pela primeira vez em mais de uma década? | D8: Saída da Rússia (-0,7 mi), aquisição fraca em todas as regiões, compartilhamento de senhas e pressão macro (inflação, guerra). Foram -0,2 mi no 1º tri e -0,97 mi no 2º tri de 2022. | E8: uded a $162 million non-cash unrealized gain from F/X remeasurement on our Euro denominated debt. Paid net additions were -0.2m compared against our guidance forecast of 2.5m and 4.0m in the same quarter a year ago. The suspension of our service in Russia and winding-down of all Russian paid memberships resulted in a -0.7m impact on paid net adds; excluding this impact, paid net additions totaled +0.5m. The main challenge for membership growth is continued soft acquisiti | F8: Carta aos acionistas (8-K, Ex. 99.1) q122 | G8: 0001065280-22-000144
A9: 2022T2-2022T4 | B9: Receita (câmbio) | C9: Por que a receita cresceu só 2% no 4º tri/2022 e a receita da EMEA caiu ao longo de 2022? | D9: Dólar forte: o euro chegou à paridade e o índice do dólar contra as moedas das regiões da Netflix subiu ~16% vs. 2019. Em moeda constante a receita cresceu 10%. | E9: creativity. I couldn’t be more excited to work alongside them as we seek to delight audiences for years to come.” For full details of Netflix leadership see here 3 . Q4 Results Year over year revenue growth of 2% in Q4 (10% on a foreign exchange (F/X) neutral basis 4 ) was driven by a 4% increase in average paid memberships. ARM 5 declined 2% year over year, but grew 5% on a F/X neutral basis 4 . Revenue was slightly above our beginning-of-quarter projection, a | F9: Carta aos acionistas (8-K, Ex. 99.1) q422 | G9: 0001065280-23-000034
A10: 2022T4 | B10: Lucro líquido | C10: Por que o lucro do 4º tri/2022 caiu 96% (US$ 55 mi), se o EBIT foi de US$ 550 mi? | D10: Perda cambial não-caixa de US$ 462 mi na remensuração da dívida em euros (o dólar se desvalorizou no trimestre), somada à margem sazonalmente baixa do T4. | E10: o not include sales taxes or VAT. 6 https://s22.q4cdn.com/959853165/files/doc_financials/2021/q4/FINAL-Q4-21-Shareholder-Letter.pdf 2 EPS in Q4’22 was $0.12 vs. $1.33 in Q4‘21. This was below our $0.36 forecast due to a $462M non-cash unrealized loss from the F/X remeasurement on our Euro denominated debt as a result of the depreciation of the US dollar vs. the Euro during Q4’22. As a reminder, our approximately $5B of Euro bonds provides us with some natural hedge | F10: Carta aos acionistas (8-K, Ex. 99.1) q422 | G10: 0001065280-23-000034
A11: 2022-2023 | B11: Despesa de juros | C11: O Fed subiu os juros de ~0% para 5,3%: por que a despesa financeira da Netflix não subiu? | D11: Toda a dívida está em notas de taxa fixa emitidas antes do ciclo de alta; a despesa de juros ficou estável (US$ 170-195 mi por trimestre até 2025T3). O salto pontual em 2025T4-2026T1 (US$ 234-262 mi) coincide com o empréstimo-ponte de US$ 59 bi contratado em 04/12/2025 para a compra da WBD, e volta ao normal em 2026T2. | E11: investments were generally invested in money market funds and time deposits. Interest paid on such funds fluctuates with the prevailing interest rate. As of December 31, 2022, we had $14.4 billion of debt, consisting of fixed rate unsecured debt in fourteen tranches due between 2024 and 2030. Refer to Note 6 to the consolidated financial statements for details about all issuances. The fair value of our debt will fluctuate with movements of intere | F11: 10-K 2022-12-31 | G11: 0001065280-23-000035
A12: 2023 | B12: FCO e FCL | C12: Como o caixa livre de 2023 (US$ 6,9 bi) superou o lucro, se a receita só cresceu 7%? | D12: As greves de roteiristas (WGA) e atores (SAG-AFTRA) pararam as produções: a amortização superou o gasto de caixa com conteúdo em US$ 1,06 bi. Caixa reforçado temporariamente, não recorrente. | E12: rtially offset by the absence of debt maturities in the year ended December 31, 2023 as compared to the repayment upon maturity of the $700 million aggregate principal amount of our 5.500% Senior Notes in February 2022. Free cash flow was $1,518 million higher than net income for the year ended December 31, 2023 primarily due to $1,057 million of amortization expense exceeding cash payments for content assets, $339 million of non-cash stock-based compensation expense, $176 mi | F12: 10-K 2023-12-31 | G12: 0001065280-24-000030
A13: 2023T3-2023T4 | B13: Patrimônio líquido | C13: Por que o patrimônio líquido encolheu no 2º semestre de 2023, com a empresa lucrando? | D13: Recompra de ações de US$ 5 bi no semestre (US$ 6 bi no ano): devolução de caixa ao acionista maior que o lucro do período. | E13: business and market conditions, and alternative investment opportunities. We may discontinue any repurchases of our common stock at any time without prior notice. In the fiscal year ended December 31, 2023, the Company repurchased 14,513,790 shares of common stock for an aggregate amount of $6,045 million. As of December 31, 2023, $8.4 billion remains available for repurchases. Our primary uses of cash include the acquisition, licensing and production of content, | F13: 10-K 2023-12-31 | G13: 0001065280-24-000030
A14: 2023T3-2024T4 | B14: Receita | C14: O que fez a receita voltar a crescer mais de 15% ao ano a partir de 2024? | D14: Compartilhamento pago (bloqueio de senhas, mai/2023 em 100+ países), plano com anúncios (nov/2022) e reajustes de preço. Os assinantes saltaram de 238 mi (2023T2) para 302 mi (2024T4). | E14: EX-99.1 2 ex991_q223.htm EX-99.1 Document Exhibit 99.1 July 19, 2023 Summary: • In May, we successfully launched paid sharing in 100+ countries, representing more than 80% of our revenue base. ◦ Revenue in each region is now higher than pre-launch, with sign-ups already exceeding cancellations. ◦ Paid net additions were 5.9M in Q2, and today w | F14: Carta aos acionistas (8-K, Ex. 99.1) q223 | G14: 0001065280-23-000197
A15: 2025T3 | B15: Margem operacional | C15: Por que a margem do 3º tri/2025 (28%) ficou abaixo da meta de 31,5%? | D15: Despesa de ~US$ 619 mi com disputa de tributos (não sobre a renda) no Brasil, reconhecida de uma vez no trimestre. | E15: cument Exhibit 99.1 October 21, 2025 Fellow shareholders, • Revenue in Q3 grew 17%, in-line with our forecast. Operating margin of 28% was below our guidance of 31.5% due to an expense related to an ongoing dispute with Brazilian tax authorities that was not in our forecast. Absent this expense, we would have exceeded our Q3'25 operating margin forecast. We don’t expect this matter to have a material impact on future results. • Engagement remains healthy. We hi | F15: Carta aos acionistas (8-K, Ex. 99.1) q325 | G15: 0001065280-25-000404
... A17: 2026T2 | B17: FCO | C17: Por que o caixa operacional caiu 67% no 2º tri/2026? | D17: Pagamento de impostos sobre a multa rescisória recebida no trimestre anterior; a operação seguiu crescendo (margem 33,4%). | E17: n 90 countries). Cash Flow and Capital Structure Net cash generated from operating activities was $1.7B vs $2.4B in the prior year period. Free cash flow (FCF) 10 in Q2’26 totaled $1.5B vs. $2.3B in Q2’25. This included higher cash tax payments due in part to the Warner Bros. termination fee. For the full year, we continue to expect FCF of approximately $12.5B, and an annual cash content spend to amortization ratio of ~1.1x. Our capital allocation approach is | F17: Carta aos acionistas (8-K, Ex. 99.1) q226 | G17: 0001065280-26-000211
A18: 2019-2020T1, 2021T4, 2024T2 | B18: Fleuriet (tipo VI) | C18: Se a Netflix tem caixa de sobra, por que o modelo Fleuriet a classifica como "alto risco" em alguns trimestres? | D18: Nesses trimestres o CCL ficou negativo (passivo circulante > ativo circulante): o saldo de tesouraria positivo era sustentado por obrigações de curto prazo — conteúdo a pagar, receita recebida antecipadamente e, em 2024T2, US$ 1,8 bi de dívida vencendo em 12 meses. Funciona enquanto a empresa cresce e recebe antes de pagar; desde 2024T3 a estrutura é do tipo I (excelente). | F18: Cálculo próprio — aba Indicadores (Fleuriet)
A19: 2025 em diante | B19: Assinantes | C19: Por que a Netflix parou de divulgar o número de assinantes? | D19: Decisão anunciada em abr/2024: com planos e preços diferentes por país, cada assinante tem impacto distinto na receita. Limitação da análise: a partir de 2025 só há receita por região. | E19: ng on the country, each incremental paid membership has a very different business impact. It’s why we stopped providing quarterly paid membership guidance in 2023 and, starting next year with our Q1'25 earnings, we will stop reporting quarterly membership numbers and ARM. We’ll continue to provide a breakout of revenue by region each quarter and the F/X impact to complement our financials. For guidance, we’ll add annual revenue guidance on top of what we already provide | F19: Carta aos acionistas (8-K, Ex. 99.1) q124 | G19: 0001065280-24-000127

Sheet Validacao
A1: Validação — conferências contábeis
A2: Maior desvio absoluto em um trimestre (US$ milhões). Tolerância: 1 (arredondamento entre balanço e notas na SEC).
A4: Conferência | B4: Maior |desvio| | C4: Status
A5: EBIT montado (receita − custos − despesas) = EBIT informado | B5: =MAX(MAX(DRE!$C$22:$AF$22),-MIN(DRE!$C$22:$AF$22)) -> 0 | C5: =IF(B5<=1,"OK","VERIFICAR") -> OK
A6: LAIR montado = LAIR informado | B6: =MAX(MAX(DRE!$C$23:$AF$23),-MIN(DRE!$C$23:$AF$23)) -> 0 | C6: =IF(B6<=1,"OK","VERIFICAR") -> OK
A7: Lucro líquido montado = informado | B7: =MAX(MAX(DRE!$C$24:$AF$24),-MIN(DRE!$C$24:$AF$24)) -> 0 | C7: =IF(B7<=1,"OK","VERIFICAR") -> OK
A8: Ativo = Passivo + PL | B8: =MAX(MAX(BP!$C$35:$AF$35),-MIN(BP!$C$35:$AF$35)) -> 0 | C8: =IF(B8<=1,"OK","VERIFICAR") -> OK
A9: Ativo circulante montado = informado | B9: =MAX(MAX(BP!$C$36:$AF$36),-MIN(BP!$C$36:$AF$36)) -> 0 | C9: =IF(B9<=1,"OK","VERIFICAR") -> OK
A10: Passivo circulante: soma das linhas = total informado (resíduo de arredondamento) | B10: =MAX(MAX(BP!$C$37:$AF$37),-MIN(BP!$C$37:$AF$37)) -> 0.633 | C10: =IF(B10<=1,"OK","VERIFICAR") -> OK
A11: Passivo não circulante: soma das linhas = PT − PC (resíduo de arredondamento) | B11: =MAX(MAX(BP!$C$38:$AF$38),-MIN(BP!$C$38:$AF$38)) -> 0.26 | C11: =IF(B11<=1,"OK","VERIFICAR") -> OK
A12: Fleuriet: ST = CCL − NCG = disponibilidades − dívida CP | B12: =MAX(MAX(Indicadores!$C$39:$AF$39),-MIN(Indicadores!$C$39:$AF$39)) -> 0 | C12: =IF(B12<=1,"OK","VERIFICAR") -> OK
A14: Validação da base trimestral (gerado por scripts/02_base_trimestral.py)
A16: 1. Identidades contábeis
A17: - Ativo = Passivo + PL: OK (maior diferença 0.00 US$ mi)
A18: - Passivo + PL informado = Ativo: OK (maior diferença 0.00 US$ mi)
A19: - EBIT = Receita - Custos - Marketing - Tecnologia - G&A: OK (maior diferença 0.00 US$ mi)
A20: - LAIR = EBIT - Juros + Outras receitas/despesas financeiras: OK (maior diferença 0.00 US$ mi)
A21: - Lucro líquido = LAIR - IR: OK (maior diferença 0.00 US$ mi)
A22: - AC = Caixa + Aplicações CP + Outros AC: OK (maior diferença 0.00 US$ mi)
A23: - PC = Passivo conteúdo CP + Fornecedores + Provisões + Receita diferida + Dívida CP: OK (maior diferença 0.63 US$ mi)
A24: - Receita DVD (total - 4 regiões de streaming) = DVD informado no 10-Q: OK (maior diferença 0.50 US$ mi)
A25: - Receita DVD nunca negativa e zerada após 2023T3: OK
A27: 2. Conferência cruzada com a API companyfacts da SEC (fonte independente do XBRL bruto)
... A36: - Assinantes pagos por região: a Netflix deixou de divulgar a partir de 2025T1 (decisão anunciada na carta aos acionistas do 1º tri/2024). Último dado avulso: "325 milhões de assinantes pagos" citado na carta do 4º tri/2025.

Sheet Fontes
A1: Documentos oficiais usados (SEC EDGAR)
A3: Formulário | B3: Período | C3: Arquivado em | D3: Accession | E3: Link
A4: 10-Q | B4: 2019-03-31 | C4: 2019-04-18 | D4: 0001065280-19-000157 | E4: https://www.sec.gov/Archives/edgar/data/1065280/000106528019000157/form10q_q119.htm
A5: 10-Q | B5: 2019-06-30 | C5: 2019-07-19 | D5: 0001065280-19-000260 | E5: https://www.sec.gov/Archives/edgar/data/1065280/000106528019000260/form10qq219.htm
A6: 10-Q | B6: 2019-09-30 | C6: 2019-10-18 | D6: 0001065280-19-000368 | E6: https://www.sec.gov/Archives/edgar/data/1065280/000106528019000368/form10qq319.htm
A7: 10-K | B7: 2019-12-31 | C7: 2020-01-29 | D7: 0001065280-20-000040 | E7: https://www.sec.gov/Archives/edgar/data/1065280/000106528020000040/form10kq419.htm
A8: 10-Q | B8: 2020-03-31 | C8: 2020-04-21 | D8: 0001065280-20-000155 | E8: https://www.sec.gov/Archives/edgar/data/1065280/000106528020000155/form10qq120.htm
A9: 10-Q | B9: 2020-06-30 | C9: 2020-07-20 | D9: 0001065280-20-000309 | E9: https://www.sec.gov/Archives/edgar/data/1065280/000106528020000309/form10qq220.htm
A10: 10-Q | B10: 2020-09-30 | C10: 2020-10-22 | D10: 0001065280-20-000451 | E10: https://www.sec.gov/Archives/edgar/data/1065280/000106528020000451/form10qq320.htm
A11: 10-K | B11: 2020-12-31 | C11: 2021-01-28 | D11: 0001065280-21-000040 | E11: https://www.sec.gov/Archives/edgar/data/1065280/000106528021000040/nflx-20201231.htm
A12: 10-Q | B12: 2021-03-31 | C12: 2021-04-22 | D12: 0001065280-21-000144 | E12: https://www.sec.gov/Archives/edgar/data/1065280/000106528021000144/nflx-20210331.htm
A13: 10-Q | B13: 2021-06-30 | C13: 2021-07-22 | D13: 0001065280-21-000250 | E13: https://www.sec.gov/Archives/edgar/data/1065280/000106528021000250/nflx-20210630.htm
A14: 10-Q | B14: 2021-09-30 | C14: 2021-10-21 | D14: 0001065280-21-000363 | E14: https://www.sec.gov/Archives/edgar/data/1065280/000106528021000363/nflx-20210930.htm
... A33: 10-Q | B33: 2026-06-30 | C33: 2026-07-17 | D33: 0001065280-26-000212 | E33: https://www.sec.gov/Archives/edgar/data/1065280/000106528026000212/nflx-20260630.htm
A35: Macro: Federal Reserve H.15 (federalreserve.gov/datadownload) · U.S. Treasury Daily Par Yield Curve (home.treasury.gov) · BLS API (api.bls.gov: CUUR0000SA0, LNS14000000) · Banco Central Europeu (data-api.ecb.europa.eu, EXR mensal).
A36: Concorrentes: 10-K de Disney (CIK 1744489), Warner Bros. Discovery (1437107), Paramount Global (813828), Comcast (1166691).
A37: Cartas aos acionistas da Netflix: Exhibit 99.1 dos 8-K de resultados (item 2.02), 2019-2026.
